Workbook
Name \p: #REF!
Name \s: #REF!
Name AGE: #REF!
Name AREA: #REF!
Name GROSS: #REF!
Name LOOP: #REF!
Name NET: #REF!
Name NUMBER: #REF!
Name RATIO: #REF!
Name STOP: #REF!

Sheet Cover Page
A1: Client's Input:
A2: Yearly Income | B2: 142609
A3: Gender | B3: Male
A4: Residency from age 18 to age 65 | B4: 15
A6: Time Value:
A7: Interest Rate | B7: 0.03
A10: Optimal solution:
A11: Max PV | B11: =Calculations!$B$19 -> 63813.215
A12: Age to receive payment | B12: =Calculations!$C$19 -> 69
A13: Monthly Payment:
A14: Before age 75 | B14: =Calculations!$B$22 -> 351.46461
A15: 75 and above | B15: =Calculations!$C$22 -> 386.61107
A17: ="You should defer your OAS payment to "&ROUND(MOD(B12*12,12),1)&" months after age "&FLOOR(B12,1)&"." -> You should defer your OAS payment to 0 months after age 69.

Sheet Calculations
F1: X | G1: PV(Benefit) | H1: PV | I1: Max PV | J1: PV(Revised) | K1: PV | L1: Max PV
B2: Income | C2: Gender | D2: Residency | F2: =Payments!B8 -> 65 | G2: {=Payments!DT8:DT128} -> 61623.917 | H2: =IF(G2=MAX($G$2:$G$122),"",G2) -> 61623.917 | I2: =IF(G2=MAX($G$2:$G$122),G2,"") | J2: {='Annuity (Revised)'!C8:C128} -> 61623.917 | K2: =IF(J2=MAX(J$2:J$122),"",J2) -> 61623.917 | L2: =IF(J2=MAX(J$2:J$128),J2,"") | Y2: Below age 75 | Z2: 75 and above
B3: ='Cover Page'!B2 -> 142609 | C3: ='Cover Page'!B3 -> Male | D3: ='Cover Page'!B4 -> 15 | E3: years | F3: =Payments!B9 -> 65.083333 | G3: 61719.147 | H3: =IF(G3=MAX($G$2:$G$122),"",G3) -> 61719.147 | I3: =IF(G3=MAX($G$2:$G$122),G3,"") | J3: 61719.147 | K3: =IF(J3=MAX(J$2:J$122),"",J3) -> 61719.147 | L3: =IF(J3=MAX(J$2:J$128),J3,"") | Y3: 142609 | Z3: 148179
F4: =Payments!B10 -> 65.166667 | G4: 61812.043 | H4: =IF(G4=MAX($G$2:$G$122),"",G4) -> 61812.043 | I4: =IF(G4=MAX($G$2:$G$122),G4,"") | J4: 61812.043 | K4: =IF(J4=MAX(J$2:J$122),"",J4) -> 61812.043 | L4: =IF(J4=MAX(J$2:J$128),J4,"")
B5: Interest Rate | F5: =Payments!B11 -> 65.25 | G5: 61902.617 | H5: =IF(G5=MAX($G$2:$G$122),"",G5) -> 61902.617 | I5: =IF(G5=MAX($G$2:$G$122),G5,"") | J5: 61902.617 | K5: =IF(J5=MAX(J$2:J$122),"",J5) -> 61902.617 | L5: =IF(J5=MAX(J$2:J$128),J5,"") | V5: Recovery tax period | W5: Income year | X5: Minimum income recovery threshold | Y5: Maximum income recovery threshold
B6: ='Cover Page'!B7 -> 0.03 | F6: =Payments!B12 -> 65.333333 | G6: 61990.885 | H6: =IF(G6=MAX($G$2:$G$122),"",G6) -> 61990.885 | I6: =IF(G6=MAX($G$2:$G$122),G6,"") | J6: 61990.885 | K6: =IF(J6=MAX(J$2:J$122),"",J6) -> 61990.885 | L6: =IF(J6=MAX(J$2:J$128),J6,"") | Y6: Age 65 to 74 | Z6: Age 75 and over
F7: =Payments!B13 -> 65.416667 | G7: 62076.86 | H7: =IF(G7=MAX($G$2:$G$122),"",G7) -> 62076.86 | I7: =IF(G7=MAX($G$2:$G$122),G7,"") | J7: 62076.86 | K7: =IF(J7=MAX(J$2:J$122),"",J7) -> 62076.86 | L7: =IF(J7=MAX(J$2:J$128),J7,"") | V7: July 2024 to June 2025 | W7: 2023 | X7: 86912 | Y7: 142609 | Z7: 148179 | AA7: =Z7/Y7 -> 1.0390578
A8: Max Income | C8: 75 and above | F8: =Payments!B14 -> 65.5 | G8: 62160.555 | H8: =IF(G8=MAX($G$2:$G$122),"",G8) -> 62160.555 | I8: =IF(G8=MAX($G$2:$G$122),G8,"") | J8: 62160.555 | K8: =IF(J8=MAX(J$2:J$122),"",J8) -> 62160.555 | L8: =IF(J8=MAX(J$2:J$128),J8,"") | V8: July 2025 to June 2026 | W8: 2024 | X8: 90997 | Y8: 148451 | Z8: 154196 | AA8: =Z8/Y8 -> 1.0386996
B9: 142609 | C9: 148179 | F9: =Payments!B15 -> 65.583333 | G9: 62241.984 | H9: =IF(G9=MAX($G$2:$G$122),"",G9) -> 62241.984 | I9: =IF(G9=MAX($G$2:$G$122),G9,"") | J9: 62241.984 | K9: =IF(J9=MAX(J$2:J$122),"",J9) -> 62241.984 | L9: =IF(J9=MAX(J$2:J$128),J9,"") | V9: July 2026 to June 2027 | W9: 2025 | X9: 93454 | Y9: 151668 | Z9: 157490 | AA9: =Z9/Y9 -> 1.0383865
F10: =Payments!B16 -> 65.666667 | G10: 62321.16 | H10: =IF(G10=MAX($G$2:$G$122),"",G10) -> 62321.16 | I10: =IF(G10=MAX($G$2:$G$122),G10,"") | J10: 62321.16 | K10: =IF(J10=MAX(J$2:J$122),"",J10) -> 62321.16 | L10: =IF(J10=MAX(J$2:J$128),J10,"")
B11: Max PV | C11: Age to receive payment | F11: =Payments!B17 -> 65.75 | G11: 62398.096 | H11: =IF(G11=MAX($G$2:$G$122),"",G11) -> 62398.096 | I11: =IF(G11=MAX($G$2:$G$122),G11,"") | J11: 62398.096 | K11: =IF(J11=MAX(J$2:J$122),"",J11) -> 62398.096 | L11: =IF(J11=MAX(J$2:J$128),J11,"") | X11: =X8/X7 -> 1.0470016 | Y11: =Y8/Y7 -> 1.0409652 | Z11: =Z8/Z7 -> 1.0406063
B12: =MAX(G2:G122) -> 63813.215 | C12: =INDEX(F2:F122, MATCH(MAX(G2:G122), G2:G122, 0)) -> 69 | F12: =Payments!B18 -> 65.833333 | G12: 62472.806 | H12: =IF(G12=MAX($G$2:$G$122),"",G12) -> 62472.806 | I12: =IF(G12=MAX($G$2:$G$122),G12,"") | J12: 62472.806 | K12: =IF(J12=MAX(J$2:J$122),"",J12) -> 62472.806 | L12: =IF(J12=MAX(J$2:J$128),J12,"") | X12: =X9/X8 -> 1.0270009 | Y12: =Y9/Y8 -> 1.0216705 | Z12: =Z9/Z8 -> 1.0213624
F13: =Payments!B19 -> 65.916667 | G13: 62545.304 | H13: =IF(G13=MAX($G$2:$G$122),"",G13) -> 62545.304 | I13: =IF(G13=MAX($G$2:$G$122),G13,"") | J13: 62545.304 | K13: =IF(J13=MAX(J$2:J$122),"",J13) -> 62545.304 | L13: =IF(J13=MAX(J$2:J$128),J13,"")
A14: Monthly Payment | C14: 75 and above | F14: =Payments!B20 -> 66 | G14: 62615.602 | H14: =IF(G14=MAX($G$2:$G$122),"",G14) -> 62615.602 | I14: =IF(G14=MAX($G$2:$G$122),G14,"") | J14: 62615.602 | K14: =IF(J14=MAX(J$2:J$122),"",J14) -> 62615.602 | L14: =IF(J14=MAX(J$2:J$128),J14,"")
B15: =INDEX(Payments!DR8:DR128, MATCH(MAX($G$2:$G$122), $G$2:$G$122, 0)) -> 351.46461 | C15: =INDEX(Payments!DS8:DS128, MATCH(MAX($G$2:$G$122), $G$2:$G$122, 0)) -> 386.61107 | F15: =Payments!B21 -> 66.083333 | G15: 62683.713 | H15: =IF(G15=MAX($G$2:$G$122),"",G15) -> 62683.713 | I15: =IF(G15=MAX($G$2:$G$122),G15,"") | J15: 62683.713 | K15: =IF(J15=MAX(J$2:J$122),"",J15) -> 62683.713 | L15: =IF(J15=MAX(J$2:J$128),J15,"")
F16: =Payments!B22 -> 66.166667 | G16: 62749.673 | H16: =IF(G16=MAX($G$2:$G$122),"",G16) -> 62749.673 | I16: =IF(G16=MAX($G$2:$G$122),G16,"") | J16: 62749.673 | K16: =IF(J16=MAX(J$2:J$122),"",J16) -> 62749.673 | L16: =IF(J16=MAX(J$2:J$128),J16,"")
A17: Revised: | B17: Only matters when Residency less than 15 years | F17: =Payments!B23 -> 66.25 | G17: 62813.496 | H17: =IF(G17=MAX($G$2:$G$122),"",G17) -> 62813.496 | I17: =IF(G17=MAX($G$2:$G$122),G17,"") | J17: 62813.496 | K17: =IF(J17=MAX(J$2:J$122),"",J17) -> 62813.496 | L17: =IF(J17=MAX(J$2:J$128),J17,"")
B18: Max PV | C18: Age to receive payment | F18: =Payments!B24 -> 66.333333 | G18: 62875.194 | H18: =IF(G18=MAX($G$2:$G$122),"",G18) -> 62875.194 | I18: =IF(G18=MAX($G$2:$G$122),G18,"") | J18: 62875.194 | K18: =IF(J18=MAX(J$2:J$122),"",J18) -> 62875.194 | L18: =IF(J18=MAX(J$2:J$128),J18,"")
B19: =MAX(J2:J128) -> 63813.215 | C19: =INDEX(F2:F122, MATCH(MAX(J2:J122), J2:J122, 0)) -> 69 | F19: =Payments!B25 -> 66.416667 | G19: 62934.781 | H19: =IF(G19=MAX($G$2:$G$122),"",G19) -> 62934.781 | I19: =IF(G19=MAX($G$2:$G$122),G19,"") | J19: 62934.781 | K19: =IF(J19=MAX(J$2:J$122),"",J19) -> 62934.781 | L19: =IF(J19=MAX(J$2:J$128),J19,"")
F20: =Payments!B26 -> 66.5 | G20: 62992.27 | H20: =IF(G20=MAX($G$2:$G$122),"",G20) -> 62992.27 | I20: =IF(G20=MAX($G$2:$G$122),G20,"") | J20: 62992.27 | K20: =IF(J20=MAX(J$2:J$122),"",J20) -> 62992.27 | L20: =IF(J20=MAX(J$2:J$128),J20,"")
A21: Monthly Payment | C21: 75 and above | F21: =Payments!B27 -> 66.583333 | G21: 63047.673 | H21: =IF(G21=MAX($G$2:$G$122),"",G21) -> 63047.673 | I21: =IF(G21=MAX($G$2:$G$122),G21,"") | J21: 63047.673 | K21: =IF(J21=MAX(J$2:J$122),"",J21) -> 63047.673 | L21: =IF(J21=MAX(J$2:J$128),J21,"")
B22: =INDEX('Annuity (Revised)'!DS8:DS128, MATCH(MAX($J$2:$J$122), $J$2:$J$122, 0)) -> 351.46461 | C22: =INDEX('Annuity (Revised)'!DT8:DT128, MATCH(MAX($J$2:$J$122), $J$2:$J$122, 0)) -> 386.61107 | F22: =Payments!B28 -> 66.666667 | G22: 63101.005 | H22: =IF(G22=MAX($G$2:$G$122),"",G22) -> 63101.005 | I22: =IF(G22=MAX($G$2:$G$122),G22,"") | J22: 63101.005 | K22: =IF(J22=MAX(J$2:J$122),"",J22) -> 63101.005 | L22: =IF(J22=MAX(J$2:J$128),J22,"")
F23: =Payments!B29 -> 66.75 | G23: 63152.277 | H23: =IF(G23=MAX($G$2:$G$122),"",G23) -> 63152.277 | I23: =IF(G23=MAX($G$2:$G$122),G23,"") | J23: 63152.277 | K23: =IF(J23=MAX(J$2:J$122),"",J23) -> 63152.277 | L23: =IF(J23=MAX(J$2:J$128),J23,"")
F24: =Payments!B30 -> 66.833333 | G24: 63201.502 | H24: =IF(G24=MAX($G$2:$G$122),"",G24) -> 63201.502 | I24: =IF(G24=MAX($G$2:$G$122),G24,"") | J24: 63201.502 | K24: =IF(J24=MAX(J$2:J$122),"",J24) -> 63201.502 | L24: =IF(J24=MAX(J$2:J$128),J24,"")
F25: =Payments!B31 -> 66.916667 | G25: 63248.695 | H25: =IF(G25=MAX($G$2:$G$122),"",G25) -> 63248.695 | I25: =IF(G25=MAX($G$2:$G$122),G25,"") | J25: 63248.695 | K25: =IF(J25=MAX(J$2:J$122),"",J25) -> 63248.695 | L25: =IF(J25=MAX(J$2:J$128),J25,"")
F26: =Payments!B32 -> 67 | G26: 63293.866 | H26: =IF(G26=MAX($G$2:$G$122),"",G26) -> 63293.866 | I26: =IF(G26=MAX($G$2:$G$122),G26,"") | J26: 63293.866 | K26: =IF(J26=MAX(J$2:J$122),"",J26) -> 63293.866 | L26: =IF(J26=MAX(J$2:J$128),J26,"")
F27: =Payments!B33 -> 67.083333 | G27: 63337.029 | H27: =IF(G27=MAX($G$2:$G$122),"",G27) -> 63337.029 | I27: =IF(G27=MAX($G$2:$G$122),G27,"") | J27: 63337.029 | K27: =IF(J27=MAX(J$2:J$122),"",J27) -> 63337.029 | L27: =IF(J27=MAX(J$2:J$128),J27,"")
F28: =Payments!B34 -> 67.166667 | G28: 63378.222 | H28: =IF(G28=MAX($G$2:$G$122),"",G28) -> 63378.222 | I28: =IF(G28=MAX($G$2:$G$122),G28,"") | J28: 63378.222 | K28: =IF(J28=MAX(J$2:J$122),"",J28) -> 63378.222 | L28: =IF(J28=MAX(J$2:J$128),J28,"")
F29: =Payments!B35 -> 67.25 | G29: 63417.458 | H29: =IF(G29=MAX($G$2:$G$122),"",G29) -> 63417.458 | I29: =IF(G29=MAX($G$2:$G$122),G29,"") | J29: 63417.458 | K29: =IF(J29=MAX(J$2:J$122),"",J29) -> 63417.458 | L29: =IF(J29=MAX(J$2:J$128),J29,"")
F30: =Payments!B36 -> 67.333333 | G30: 63454.748 | H30: =IF(G30=MAX($G$2:$G$122),"",G30) -> 63454.748 | I30: =IF(G30=MAX($G$2:$G$122),G30,"") | J30: 63454.748 | K30: =IF(J30=MAX(J$2:J$122),"",J30) -> 63454.748 | L30: =IF(J30=MAX(J$2:J$128),J30,"")
F31: =Payments!B37 -> 67.416667 | G31: 63490.106 | H31: =IF(G31=MAX($G$2:$G$122),"",G31) -> 63490.106 | I31: =IF(G31=MAX($G$2:$G$122),G31,"") | J31: 63490.106 | K31: =IF(J31=MAX(J$2:J$122),"",J31) -> 63490.106 | L31: =IF(J31=MAX(J$2:J$128),J31,"")
F32: =Payments!B38 -> 67.5 | G32: 63523.545 | H32: =IF(G32=MAX($G$2:$G$122),"",G32) -> 63523.545 | I32: =IF(G32=MAX($G$2:$G$122),G32,"") | J32: 63523.545 | K32: =IF(J32=MAX(J$2:J$122),"",J32) -> 63523.545 | L32: =IF(J32=MAX(J$2:J$128),J32,"")
F33: =Payments!B39 -> 67.583333 | G33: 63555.077 | H33: =IF(G33=MAX($G$2:$G$122),"",G33) -> 63555.077 | I33: =IF(G33=MAX($G$2:$G$122),G33,"") | J33: 63555.077 | K33: =IF(J33=MAX(J$2:J$122),"",J33) -> 63555.077 | L33: =IF(J33=MAX(J$2:J$128),J33,"")
F34: =Payments!B40 -> 67.666667 | G34: 63584.715 | H34: =IF(G34=MAX($G$2:$G$122),"",G34) -> 63584.715 | I34: =IF(G34=MAX($G$2:$G$122),G34,"") | J34: 63584.715 | K34: =IF(J34=MAX(J$2:J$122),"",J34) -> 63584.715 | L34: =IF(J34=MAX(J$2:J$128),J34,"")
... F122: =Payments!B128 -> 75 | G122: 47815.985 | H122: =IF(G122=MAX($G$2:$G$122),"",G122) -> 47815.985 | I122: =IF(G122=MAX($G$2:$G$122),G122,"") | J122: 47815.985 | K122: =IF(J122=MAX(J$2:J$122),"",J122) -> 47815.985 | L122: =IF(J122=MAX(J$2:J$128),J122,"")

Sheet StatCan
A1: https://www.soa.org/resources/experience-studies/2015/2017-cso-tables/ | C1: x | D1: q_x | E1: mu_x | F1: A_x | G1: a_x | H1: a(12)_x (UDD) | I1: a(12)_x (WH3) | J1: npx | K1: 0 | L1: 1 | M1: 2 | N1: 3 | O1: 4 | P1: 5 | Q1: 6 | R1: 7 | S1: 8 | T1: 9 | U1: 10 | V1: 11 | W1: 12 | X1: 13 | Y1: 14 | Z1: 15 | AA1: 16 | AB1: 17 | AC1: 18 | AD1: 19 | AE1: 20 | AF1: 21 | AG1: 22 | AH1: 23 | AI1: 24 | AJ1: 25 | AK1: 26 | AL1: 27 | AM1: 28 | AN1: 29 | AO1: 30 | AP1: 31 | AQ1: 32 | AR1: 33 | AS1: 34 | AT1: 35 | AU1: 36 | AV1: 37 | AW1: 38 | AX1: 39 | AY1: 40 | AZ1: 41 | BA1: 42 | BB1: 43 | BC1: 44 | BD1: 45 | BE1: 46 | BF1: 47 | BG1: 48 | BH1: 49 | BI1: 50 | BJ1: 51 | BK1: 52 | BL1: 53 | BM1: 54 | BN1: 55 | BO1: 56 | BP1: 57 | BQ1: 58 | BR1: 59 | BS1: 60 | BT1: 61 | BU1: 62 | BV1: 63 | BW1: 64 | BX1: 65 | BY1: 66 | BZ1: 67 | CA1: 68 | CB1: 69 | CC1: 70 | CD1: 71 | CE1: 72 | CF1: 73 | CG1: 74 | CH1: 75 | CI1: 76 | CJ1: 77 | CK1: 78 | CL1: 79 | CM1: 80 | CN1: 81 | CO1: 82 | CP1: 83 | CQ1: 84 | CR1: 85 | CS1: 86 | CT1: 87 | CU1: 88 | CV1: 89 | CW1: 90 | CX1: 91 | CY1: 92 | CZ1: 93 | DA1: 94 | DB1: 95 | DC1: 96 | DD1: 97 | DE1: 98 | DF1: 99 | DG1: 100 | DH1: 101 | DI1: 102 | DJ1: 103 | DK1: 104 | DL1: 105 | DM1: 106 | DN1: 107 | DO1: 108 | DP1: 109 | DQ1: 110 | DR1: 111 | DS1: 112 | DT1: 113 | DU1: 114 | DV1: 115 | DW1: 116 | DX1: 117 | DZ1: Age group | EA1: 2019 | EB1: 2020 | EC1: 2021 | ED1: 2022 | EE1: 2023 | EF1: Average
C2: 64 | D2: =EF2 -> 0.008422 | K2: 1 | L2: {=IFERROR(K2*(1-INDEX($D2:$D$71,L$1)),0)} -> 0.991578 | M2: {=IFERROR(L2*(1-INDEX($D2:$D$71,M$1)),0)} -> 0.98231005 | N2: {=IFERROR(M2*(1-INDEX($D2:$D$71,N$1)),0)} -> 0.9722512 | O2: {=IFERROR(N2*(1-INDEX($D2:$D$71,O$1)),0)} -> 0.96132957 | P2: {=IFERROR(O2*(1-INDEX($D2:$D$71,P$1)),0)} -> 0.94947638 | Q2: {=IFERROR(P2*(1-INDEX($D2:$D$71,Q$1)),0)} -> 0.93661414 | R2: {=IFERROR(Q2*(1-INDEX($D2:$D$71,R$1)),0)} -> 0.92265235 | S2: {=IFERROR(R2*(1-INDEX($D2:$D$71,S$1)),0)} -> 0.90751162 | ... DX2: {=IFERROR(DW2*(1-INDEX($D2:$D$71,DX$1)),0)} -> 0 | DZ2: 64 years | EA2: 0.00805 | EB2: 0.00843 | EC2: 0.00861 | ED2: 0.00868 | EE2: 0.00834 | EF2: =AVERAGE(EA2:EE2) -> 0.008422 | EG2: =ED2/EC2-1 -> 0.0081300813 | EH2: =EE2/ED2-1 -> -0.039170507
A3: i | C3: 65 | D3: =EF3 -> 0.0093466667 | E3: =-1/2*(LN(1-D2)+LN(1-D3)) -> 0.0089241431 | F3: {=SUMPRODUCT($A$6^($K$1:$DT$1+1),K3:DT3,TRANSPOSE(D3:D116))} -> 0.55223883 | G3: {=SUMPRODUCT($A$6^($K$1:$DT$1),K3:DT3)} -> 15.373134 | H3: =(1-$A$4/$A$9*F3)/$A$15 -> 14.910983 | I3: =G3-(12-1)/2/12-(12^2-1)/12/12^2*(E3+LN(1+$A$4)) -> 14.911616 | K3: 1 | L3: {=IFERROR(K3*(1-INDEX($D3:$D$71,L$1)),0)} -> 0.99065333 | M3: {=IFERROR(L3*(1-INDEX($D3:$D$71,M$1)),0)} -> 0.98050904 | N3: {=IFERROR(M3*(1-INDEX($D3:$D$71,N$1)),0)} -> 0.96949466 | O3: {=IFERROR(N3*(1-INDEX($D3:$D$71,O$1)),0)} -> 0.95754079 | P3: {=IFERROR(O3*(1-INDEX($D3:$D$71,P$1)),0)} -> 0.9445693 | Q3: {=IFERROR(P3*(1-INDEX($D3:$D$71,Q$1)),0)} -> 0.93048892 | R3: {=IFERROR(Q3*(1-INDEX($D3:$D$71,R$1)),0)} -> 0.9152196 | S3: {=IFERROR(R3*(1-INDEX($D3:$D$71,S$1)),0)} -> 0.89866633 | ... DX3: {=IFERROR(DW3*(1-INDEX($D3:$D$71,DX$1)),0)} -> 0 | DZ3: 65 years | EA3: 0.00884 | EB3: 0.00923 | EC3: 0.00942 | ED3: 0.0095 | EE3: 0.00912 | EF3: =AVERAGE(EC3:EE3) -> 0.0093466667 | EG3: =ED3/EC3-1 -> 0.008492569 | EH3: =EE3/ED3-1 -> -0.04
A4: =Payments!K2 -> 0.03 | C4: 66 | D4: =EF4 -> 0.01024 | E4: =-1/2*(LN(1-D3)+LN(1-D4)) -> 0.0098417052 | F4: {=SUMPRODUCT($A$6^($K$1:$DT$1+1),K4:DT4,TRANSPOSE(D4:D117))} -> 0.56473774 | G4: {=SUMPRODUCT($A$6^($K$1:$DT$1),K4:DT4)} -> 14.944004 | H4: =(1-$A$4/$A$9*F4)/$A$15 -> 14.481823 | I4: =G4-(12-1)/2/12-(12^2-1)/12/12^2*(E4+LN(1+$A$4)) -> 14.48241 | K4: 1 | L4: {=IFERROR(K4*(1-INDEX($D4:$D$71,L$1)),0)} -> 0.98976 | M4: {=IFERROR(L4*(1-INDEX($D4:$D$71,M$1)),0)} -> 0.9786417 | N4: {=IFERROR(M4*(1-INDEX($D4:$D$71,N$1)),0)} -> 0.96657504 | O4: {=IFERROR(N4*(1-INDEX($D4:$D$71,O$1)),0)} -> 0.95348117 | P4: {=IFERROR(O4*(1-INDEX($D4:$D$71,P$1)),0)} -> 0.93926795 | Q4: {=IFERROR(P4*(1-INDEX($D4:$D$71,Q$1)),0)} -> 0.92385456 | R4: {=IFERROR(Q4*(1-INDEX($D4:$D$71,R$1)),0)} -> 0.90714511 | S4: {=IFERROR(R4*(1-INDEX($D4:$D$71,S$1)),0)} -> 0.88903849 | ... DX4: {=IFERROR(DW4*(1-INDEX($D4:$D$71,DX$1)),0)} -> 0 | DZ4: 66 years | EA4: 0.00972 | EB4: 0.01012 | EC4: 0.01031 | ED4: 0.01042 | EE4: 0.00999 | EF4: =AVERAGE(EC4:EE4) -> 0.01024 | EG4: =ED4/EC4-1 -> 0.010669253 | EH4: =EE4/ED4-1 -> -0.041266795
A5: v | C5: 67 | D5: =EF5 -> 0.011233333 | E5: =-1/2*(LN(1-D4)+LN(1-D5)) -> 0.010794847 | F5: {=SUMPRODUCT($A$6^($K$1:$DT$1+1),K5:DT5,TRANSPOSE(D5:D118))} -> 0.57735196 | G5: {=SUMPRODUCT($A$6^($K$1:$DT$1),K5:DT5)} -> 14.510916 | H5: =(1-$A$4/$A$9*F5)/$A$15 -> 14.048703 | I5: =G5-(12-1)/2/12-(12^2-1)/12/12^2*(E5+LN(1+$A$4)) -> 14.049243 | K5: 1 | L5: {=IFERROR(K5*(1-INDEX($D5:$D$71,L$1)),0)} -> 0.98876667 | M5: {=IFERROR(L5*(1-INDEX($D5:$D$71,M$1)),0)} -> 0.97657517 | N5: {=IFERROR(M5*(1-INDEX($D5:$D$71,N$1)),0)} -> 0.96334584 | O5: {=IFERROR(N5*(1-INDEX($D5:$D$71,O$1)),0)} -> 0.94898556 | P5: {=IFERROR(O5*(1-INDEX($D5:$D$71,P$1)),0)} -> 0.93341271 | Q5: {=IFERROR(P5*(1-INDEX($D5:$D$71,Q$1)),0)} -> 0.91653038 | R5: {=IFERROR(Q5*(1-INDEX($D5:$D$71,R$1)),0)} -> 0.89823644 | S5: {=IFERROR(R5*(1-INDEX($D5:$D$71,S$1)),0)} -> 0.87843631 | ... DX5: {=IFERROR(DW5*(1-INDEX($D5:$D$71,DX$1)),0)} -> 0 | DZ5: 67 years | EA5: 0.0107 | EB5: 0.01111 | EC5: 0.0113 | ED5: 0.01144 | EE5: 0.01096 | EF5: =AVERAGE(EC5:EE5) -> 0.011233333 | EG5: =ED5/EC5-1 -> 0.012389381 | EH5: =EE5/ED5-1 -> -0.041958042
A6: =(1+A4)^-1 -> 0.97087379 | C6: 68 | D6: =EF6 -> 0.01233 | E6: =-1/2*(LN(1-D5)+LN(1-D6)) -> 0.011851774 | F6: {=SUMPRODUCT($A$6^($K$1:$DT$1+1),K6:DT6,TRANSPOSE(D6:D119))} -> 0.59006761 | G6: {=SUMPRODUCT($A$6^($K$1:$DT$1),K6:DT6)} -> 14.074345 | H6: =(1-$A$4/$A$9*F6)/$A$15 -> 13.612101 | I6: =G6-(12-1)/2/12-(12^2-1)/12/12^2*(E6+LN(1+$A$4)) -> 13.612585 | K6: 1 | L6: {=IFERROR(K6*(1-INDEX($D6:$D$71,L$1)),0)} -> 0.98767 | M6: {=IFERROR(L6*(1-INDEX($D6:$D$71,M$1)),0)} -> 0.97429036 | N6: {=IFERROR(M6*(1-INDEX($D6:$D$71,N$1)),0)} -> 0.95976694 | O6: {=IFERROR(N6*(1-INDEX($D6:$D$71,O$1)),0)} -> 0.94401717 | P6: {=IFERROR(O6*(1-INDEX($D6:$D$71,P$1)),0)} -> 0.92694304 | Q6: {=IFERROR(P6*(1-INDEX($D6:$D$71,Q$1)),0)} -> 0.90844126 | R6: {=IFERROR(Q6*(1-INDEX($D6:$D$71,R$1)),0)} -> 0.88841619 | S6: {=IFERROR(R6*(1-INDEX($D6:$D$71,S$1)),0)} -> 0.86676548 | ... DX6: {=IFERROR(DW6*(1-INDEX($D6:$D$71,DX$1)),0)} -> 0 | DZ6: 68 years | EA6: 0.01179 | EB6: 0.01221 | EC6: 0.01239 | ED6: 0.01257 | EE6: 0.01203 | EF6: =AVERAGE(EC6:EE6) -> 0.01233 | EG6: =ED6/EC6-1 -> 0.014527845 | EH6: =EE6/ED6-1 -> -0.042959427
C7: 69 | D7: =EF7 -> 0.013546667 | E7: =-1/2*(LN(1-D6)+LN(1-D7)) -> 0.013022953 | F7: {=SUMPRODUCT($A$6^($K$1:$DT$1+1),K7:DT7,TRANSPOSE(D7:D120))} -> 0.60287306 | G7: {=SUMPRODUCT($A$6^($K$1:$DT$1),K7:DT7)} -> 13.634691 | H7: =(1-$A$4/$A$9*F7)/$A$15 -> 13.172415 | I7: =G7-(12-1)/2/12-(12^2-1)/12/12^2*(E7+LN(1+$A$4)) -> 13.172834 | K7: 1 | L7: {=IFERROR(K7*(1-INDEX($D7:$D$71,L$1)),0)} -> 0.98645333 | M7: {=IFERROR(L7*(1-INDEX($D7:$D$71,M$1)),0)} -> 0.9717486 | N7: {=IFERROR(M7*(1-INDEX($D7:$D$71,N$1)),0)} -> 0.95580221 | O7: {=IFERROR(N7*(1-INDEX($D7:$D$71,O$1)),0)} -> 0.93851493 | P7: {=IFERROR(O7*(1-INDEX($D7:$D$71,P$1)),0)} -> 0.91978217 | Q7: {=IFERROR(P7*(1-INDEX($D7:$D$71,Q$1)),0)} -> 0.89950711 | R7: {=IFERROR(Q7*(1-INDEX($D7:$D$71,R$1)),0)} -> 0.87758612 | S7: {=IFERROR(R7*(1-INDEX($D7:$D$71,S$1)),0)} -> 0.8539147 | ... DX7: {=IFERROR(DW7*(1-INDEX($D7:$D$71,DX$1)),0)} -> 0 | DZ7: 69 years | EA7: 0.01299 | EB7: 0.01344 | EC7: 0.01361 | ED7: 0.01382 | EE7: 0.01321 | EF7: =AVERAGE(EC7:EE7) -> 0.013546667 | EG7: =ED7/EC7-1 -> 0.015429831 | EH7: =EE7/ED7-1 -> -0.044138929
A8: i_12 | C8: 70 | D8: =EF8 -> 0.014906667 | E8: =-1/2*(LN(1-D7)+LN(1-D8)) -> 0.014329074 | F8: {=SUMPRODUCT($A$6^($K$1:$DT$1+1),K8:DT8,TRANSPOSE(D8:D121))} -> 0.615754 | G8: {=SUMPRODUCT($A$6^($K$1:$DT$1),K8:DT8)} -> 13.192446 | H8: =(1-$A$4/$A$9*F8)/$A$15 -> 12.730138 | I8: =G8-(12-1)/2/12-(12^2-1)/12/12^2*(E8+LN(1+$A$4)) -> 12.730481 | K8: 1 | L8: {=IFERROR(K8*(1-INDEX($D8:$D$71,L$1)),0)} -> 0.98509333 | M8: {=IFERROR(L8*(1-INDEX($D8:$D$71,M$1)),0)} -> 0.96892795 | N8: {=IFERROR(M8*(1-INDEX($D8:$D$71,N$1)),0)} -> 0.95140327 | O8: {=IFERROR(N8*(1-INDEX($D8:$D$71,O$1)),0)} -> 0.93241327 | P8: {=IFERROR(O8*(1-INDEX($D8:$D$71,P$1)),0)} -> 0.91185977 | Q8: {=IFERROR(P8*(1-INDEX($D8:$D$71,Q$1)),0)} -> 0.88963775 | R8: {=IFERROR(Q8*(1-INDEX($D8:$D$71,R$1)),0)} -> 0.86564125 | S8: {=IFERROR(R8*(1-INDEX($D8:$D$71,S$1)),0)} -> 0.839773 | ... DX8: {=IFERROR(DW8*(1-INDEX($D8:$D$71,DX$1)),0)} -> 0 | DZ8: 70 years | EA8: 0.01433 | EB8: 0.0148 | EC8: 0.01496 | ED8: 0.01522 | EE8: 0.01454 | EF8: =AVERAGE(EC8:EE8) -> 0.014906667 | EG8: =ED8/EC8-1 -> 0.017379679 | EH8: =EE8/ED8-1 -> -0.044678055
A9: =12*((1+A4)^(1/12)-1) -> 0.029595237 | C9: 71 | D9: =EF9 -> 0.01641 | E9: =-1/2*(LN(1-D8)+LN(1-D9)) -> 0.015782512 | F9: {=SUMPRODUCT($A$6^($K$1:$DT$1+1),K9:DT9,TRANSPOSE(D9:D122))} -> 0.62869165 | G9: {=SUMPRODUCT($A$6^($K$1:$DT$1),K9:DT9)} -> 12.748253 | H9: =(1-$A$4/$A$9*F9)/$A$15 -> 12.285913 | I9: =G9-(12-1)/2/12-(12^2-1)/12/12^2*(E9+LN(1+$A$4)) -> 12.286168 | K9: 1 | L9: {=IFERROR(K9*(1-INDEX($D9:$D$71,L$1)),0)} -> 0.98359 | M9: {=IFERROR(L9*(1-INDEX($D9:$D$71,M$1)),0)} -> 0.96580014 | N9: {=IFERROR(M9*(1-INDEX($D9:$D$71,N$1)),0)} -> 0.94652276 | O9: {=IFERROR(N9*(1-INDEX($D9:$D$71,O$1)),0)} -> 0.92565825 | P9: {=IFERROR(O9*(1-INDEX($D9:$D$71,P$1)),0)} -> 0.90309996 | Q9: {=IFERROR(P9*(1-INDEX($D9:$D$71,Q$1)),0)} -> 0.87874034 | R9: {=IFERROR(Q9*(1-INDEX($D9:$D$71,R$1)),0)} -> 0.85248065 | S9: {=IFERROR(R9*(1-INDEX($D9:$D$71,S$1)),0)} -> 0.82423228 | ... DX9: {=IFERROR(DW9*(1-INDEX($D9:$D$71,DX$1)),0)} -> 0 | DZ9: 71 years | EA9: 0.01583 | EB9: 0.01631 | EC9: 0.01645 | ED9: 0.01677 | EE9: 0.01601 | EF9: =AVERAGE(EC9:EE9) -> 0.01641 | EG9: =ED9/EC9-1 -> 0.019452888 | EH9: =EE9/ED9-1 -> -0.045319022
C10: 72 | D10: =EF10 -> 0.018086667 | E10: =-1/2*(LN(1-D9)+LN(1-D10)) -> 0.017399183 | F10: {=SUMPRODUCT($A$6^($K$1:$DT$1+1),K10:DT10,TRANSPOSE(D10:D123))} -> 0.64167224 | G10: {=SUMPRODUCT($A$6^($K$1:$DT$1),K10:DT10)} -> 12.302586 | H10: =(1-$A$4/$A$9*F10)/$A$15 -> 11.840214 | I10: =G10-(12-1)/2/12-(12^2-1)/12/12^2*(E10+LN(1+$A$4)) -> 11.840367 | K10: 1 | L10: {=IFERROR(K10*(1-INDEX($D10:$D$71,L$1)),0)} -> 0.98191333 | M10: {=IFERROR(L10*(1-INDEX($D10:$D$71,M$1)),0)} -> 0.96231434 | N10: {=IFERROR(M10*(1-INDEX($D10:$D$71,N$1)),0)} -> 0.94110173 | O10: {=IFERROR(N10*(1-INDEX($D10:$D$71,O$1)),0)} -> 0.91816708 | P10: {=IFERROR(O10*(1-INDEX($D10:$D$71,P$1)),0)} -> 0.89340105 | Q10: {=IFERROR(P10*(1-INDEX($D10:$D$71,Q$1)),0)} -> 0.86670325 | R10: {=IFERROR(Q10*(1-INDEX($D10:$D$71,R$1)),0)} -> 0.83798359 | S10: {=IFERROR(R10*(1-INDEX($D10:$D$71,S$1)),0)} -> 0.80715976 | ... DX10: {=IFERROR(DW10*(1-INDEX($D10:$D$71,DX$1)),0)} -> 0 | DZ10: 72 years | EA10: 0.01749 | EB10: 0.018 | EC10: 0.01812 | ED10: 0.0185 | EE10: 0.01764 | EF10: =AVERAGE(EC10:EE10) -> 0.018086667 | EG10: =ED10/EC10-1 -> 0.020971302 | EH10: =EE10/ED10-1 -> -0.046486486
A11: d | C11: 73 | D11: =EF11 -> 0.01996 | E11: =-1/2*(LN(1-D10)+LN(1-D11)) -> 0.019207061 | F11: {=SUMPRODUCT($A$6^($K$1:$DT$1+1),K11:DT11,TRANSPOSE(D11:D124))} -> 0.65467666 | G11: {=SUMPRODUCT($A$6^($K$1:$DT$1),K11:DT11)} -> 11.856101 | H11: =(1-$A$4/$A$9*F11)/$A$15 -> 11.393697 | I11: =G11-(12-1)/2/12-(12^2-1)/12/12^2*(E11+LN(1+$A$4)) -> 11.393732 | K11: 1 | L11: {=IFERROR(K11*(1-INDEX($D11:$D$71,L$1)),0)} -> 0.98004 | M11: {=IFERROR(L11*(1-INDEX($D11:$D$71,M$1)),0)} -> 0.95843665 | N11: {=IFERROR(M11*(1-INDEX($D11:$D$71,N$1)),0)} -> 0.93507955 | O11: {=IFERROR(N11*(1-INDEX($D11:$D$71,O$1)),0)} -> 0.90985734 | P11: {=IFERROR(O11*(1-INDEX($D11:$D$71,P$1)),0)} -> 0.88266777 | Q11: {=IFERROR(P11*(1-INDEX($D11:$D$71,Q$1)),0)} -> 0.8534191 | R11: {=IFERROR(Q11*(1-INDEX($D11:$D$71,R$1)),0)} -> 0.8220275 | S11: {=IFERROR(R11*(1-INDEX($D11:$D$71,S$1)),0)} -> 0.78842576 | ... DX11: {=IFERROR(DW11*(1-INDEX($D11:$D$71,DX$1)),0)} -> 0 | DZ11: 73 years | EA11: 0.01934 | EB11: 0.01989 | EC11: 0.01997 | ED11: 0.02044 | EE11: 0.01947 | EF11: =AVERAGE(EC11:EE11) -> 0.01996 | EG11: =ED11/EC11-1 -> 0.023535303 | EH11: =EE11/ED11-1 -> -0.047455969
A12: =1-1/(1+A4) -> 0.029126214 | C12: 74 | D12: =EF12 -> 0.022043333 | E12: =-1/2*(LN(1-D11)+LN(1-D12)) -> 0.021225905 | F12: {=SUMPRODUCT($A$6^($K$1:$DT$1+1),K12:DT12,TRANSPOSE(D12:D125))} -> 0.66768393 | G12: {=SUMPRODUCT($A$6^($K$1:$DT$1),K12:DT12)} -> 11.409518 | H12: =(1-$A$4/$A$9*F12)/$A$15 -> 10.947081 | I12: =G12-(12-1)/2/12-(12^2-1)/12/12^2*(E12+LN(1+$A$4)) -> 10.946982 | K12: 1 | L12: {=IFERROR(K12*(1-INDEX($D12:$D$71,L$1)),0)} -> 0.97795667 | M12: {=IFERROR(L12*(1-INDEX($D12:$D$71,M$1)),0)} -> 0.95412386 | N12: {=IFERROR(M12*(1-INDEX($D12:$D$71,N$1)),0)} -> 0.92838796 | O12: {=IFERROR(N12*(1-INDEX($D12:$D$71,O$1)),0)} -> 0.90064463 | P12: {=IFERROR(O12*(1-INDEX($D12:$D$71,P$1)),0)} -> 0.87080027 | Q12: {=IFERROR(P12*(1-INDEX($D12:$D$71,Q$1)),0)} -> 0.83876934 | R12: {=IFERROR(Q12*(1-INDEX($D12:$D$71,R$1)),0)} -> 0.80448324 | S12: {=IFERROR(R12*(1-INDEX($D12:$D$71,S$1)),0)} -> 0.76790339 | ... DX12: {=IFERROR(DW12*(1-INDEX($D12:$D$71,DX$1)),0)} -> 0 | DZ12: 74 years | EA12: 0.02141 | EB12: 0.022 | EC12: 0.02203 | ED12: 0.02259 | EE12: 0.02151 | EF12: =AVERAGE(EC12:EE12) -> 0.022043333 | EG12: =ED12/EC12-1 -> 0.025419882 | EH12: =EE12/ED12-1 -> -0.047808765
C13: 75 | D13: =EF13 -> 0.02437 | E13: =-1/2*(LN(1-D12)+LN(1-D13)) -> 0.02348089 | F13: {=SUMPRODUCT($A$6^($K$1:$DT$1+1),K13:DT13,TRANSPOSE(D13:D126))} -> 0.68067548 | G13: {=SUMPRODUCT($A$6^($K$1:$DT$1),K13:DT13)} -> 10.963475 | H13: =(1-$A$4/$A$9*F13)/$A$15 -> 10.501006 | I13: =G13-(12-1)/2/12-(12^2-1)/12/12^2*(E13+LN(1+$A$4)) -> 10.500753 | K13: 1 | L13: {=IFERROR(K13*(1-INDEX($D13:$D$71,L$1)),0)} -> 0.97563 | M13: {=IFERROR(L13*(1-INDEX($D13:$D$71,M$1)),0)} -> 0.94931401 | N13: {=IFERROR(M13*(1-INDEX($D13:$D$71,N$1)),0)} -> 0.92094534 | O13: {=IFERROR(N13*(1-INDEX($D13:$D$71,O$1)),0)} -> 0.89042828 | P13: {=IFERROR(O13*(1-INDEX($D13:$D$71,P$1)),0)} -> 0.85767536 | Q13: {=IFERROR(P13*(1-INDEX($D13:$D$71,Q$1)),0)} -> 0.82261645 | R13: {=IFERROR(Q13*(1-INDEX($D13:$D$71,R$1)),0)} -> 0.78521208 | S13: {=IFERROR(R13*(1-INDEX($D13:$D$71,S$1)),0)} -> 0.74545941 | ... DX13: {=IFERROR(DW13*(1-INDEX($D13:$D$71,DX$1)),0)} -> 0 | DZ13: 75 years | EA13: 0.02371 | EB13: 0.02435 | EC13: 0.02433 | ED13: 0.025 | EE13: 0.02378 | EF13: =AVERAGE(EC13:EE13) -> 0.02437 | EG13: =ED13/EC13-1 -> 0.027538019 | EH13: =EE13/ED13-1 -> -0.0488
A14: d_12 | C14: 76 | D14: =EF14 -> 0.026973333 | E14: =-1/2*(LN(1-D13)+LN(1-D14)) -> 0.026007827 | F14: {=SUMPRODUCT($A$6^($K$1:$DT$1+1),K14:DT14,TRANSPOSE(D14:D127))} -> 0.69362949 | G14: {=SUMPRODUCT($A$6^($K$1:$DT$1),K14:DT14)} -> 10.518721 | H14: =(1-$A$4/$A$9*F14)/$A$15 -> 10.056219 | I14: =G14-(12-1)/2/12-(12^2-1)/12/12^2*(E14+LN(1+$A$4)) -> 10.055789 | K14: 1 | L14: {=IFERROR(K14*(1-INDEX($D14:$D$71,L$1)),0)} -> 0.97302667 | M14: {=IFERROR(L14*(1-INDEX($D14:$D$71,M$1)),0)} -> 0.94394939 | N14: {=IFERROR(M14*(1-INDEX($D14:$D$71,N$1)),0)} -> 0.91267005 | O14: {=IFERROR(N14*(1-INDEX($D14:$D$71,O$1)),0)} -> 0.879099 | P14: {=IFERROR(O14*(1-INDEX($D14:$D$71,P$1)),0)} -> 0.84316437 | Q14: {=IFERROR(P14*(1-INDEX($D14:$D$71,Q$1)),0)} -> 0.80482568 | R14: {=IFERROR(Q14*(1-INDEX($D14:$D$71,R$1)),0)} -> 0.76408004 | S14: {=IFERROR(R14*(1-INDEX($D14:$D$71,S$1)),0)} -> 0.72096555 | ... DX14: {=IFERROR(DW14*(1-INDEX($D14:$D$71,DX$1)),0)} -> 0 | DZ14: 76 years | EA14: 0.02629 | EB14: 0.02699 | EC14: 0.02689 | ED14: 0.0277 | EE14: 0.02633 | EF14: =AVERAGE(EC14:EE14) -> 0.026973333 | EG14: =ED14/EC14-1 -> 0.030122722 | EH14: =EE14/ED14-1 -> -0.049458484
A15: =(1-(1+A4)^(-1/12))*12 -> 0.029522427 | C15: 77 | D15: =EF15 -> 0.029883333 | E15: =-1/2*(LN(1-D14)+LN(1-D15)) -> 0.028841365 | F15: {=SUMPRODUCT($A$6^($K$1:$DT$1+1),K15:DT15,TRANSPOSE(D15:D128))} -> 0.7065223 | G15: {=SUMPRODUCT($A$6^($K$1:$DT$1),K15:DT15)} -> 10.076068 | H15: =(1-$A$4/$A$9*F15)/$A$15 -> 9.6135342 | I15: =G15-(12-1)/2/12-(12^2-1)/12/12^2*(E15+LN(1+$A$4)) -> 9.6129014 | K15: 1 | L15: {=IFERROR(K15*(1-INDEX($D15:$D$71,L$1)),0)} -> 0.97011667 | M15: {=IFERROR(L15*(1-INDEX($D15:$D$71,M$1)),0)} -> 0.93797023 | N15: {=IFERROR(M15*(1-INDEX($D15:$D$71,N$1)),0)} -> 0.90346856 | O15: {=IFERROR(N15*(1-INDEX($D15:$D$71,O$1)),0)} -> 0.86653778 | P15: {=IFERROR(O15*(1-INDEX($D15:$D$71,P$1)),0)} -> 0.82713631 | Q15: {=IFERROR(P15*(1-INDEX($D15:$D$71,Q$1)),0)} -> 0.78526115 | R15: {=IFERROR(Q15*(1-INDEX($D15:$D$71,R$1)),0)} -> 0.74095148 | S15: {=IFERROR(R15*(1-INDEX($D15:$D$71,S$1)),0)} -> 0.69430365 | ... DX15: {=IFERROR(DW15*(1-INDEX($D15:$D$71,DX$1)),0)} -> 0 | DZ15: 77 years | EA15: 0.02917 | EB15: 0.02995 | EC15: 0.02975 | ED15: 0.03072 | EE15: 0.02918 | EF15: =AVERAGE(EC15:EE15) -> 0.029883333 | EG15: =ED15/EC15-1 -> 0.032605042 | EH15: =EE15/ED15-1 -> -0.050130208
C16: 78 | D16: =EF16 -> 0.033136667 | E16: =-1/2*(LN(1-D15)+LN(1-D16)) -> 0.032018532 | F16: {=SUMPRODUCT($A$6^($K$1:$DT$1+1),K16:DT16,TRANSPOSE(D16:D129))} -> 0.71933064 | G16: {=SUMPRODUCT($A$6^($K$1:$DT$1),K16:DT16)} -> 9.6363148 | H16: =(1-$A$4/$A$9*F16)/$A$15 -> 9.1737496 | I16: =G16-(12-1)/2/12-(12^2-1)/12/12^2*(E16+LN(1+$A$4)) -> 9.1728857 | K16: 1 | L16: {=IFERROR(K16*(1-INDEX($D16:$D$71,L$1)),0)} -> 0.96686333 | M16: {=IFERROR(L16*(1-INDEX($D16:$D$71,M$1)),0)} -> 0.93129888 | N16: {=IFERROR(M16*(1-INDEX($D16:$D$71,N$1)),0)} -> 0.89323048 | O16: {=IFERROR(N16*(1-INDEX($D16:$D$71,O$1)),0)} -> 0.85261529 | P16: {=IFERROR(O16*(1-INDEX($D16:$D$71,P$1)),0)} -> 0.80945022 | Q16: {=IFERROR(P16*(1-INDEX($D16:$D$71,Q$1)),0)} -> 0.76377565 | R16: {=IFERROR(Q16*(1-INDEX($D16:$D$71,R$1)),0)} -> 0.71569088 | S16: {=IFERROR(R16*(1-INDEX($D16:$D$71,S$1)),0)} -> 0.66536588 | ... DX16: {=IFERROR(DW16*(1-INDEX($D16:$D$71,DX$1)),0)} -> 0 | DZ16: 78 years | EA16: 0.03239 | EB16: 0.03326 | EC16: 0.03294 | ED16: 0.0341 | EE16: 0.03237 | EF16: =AVERAGE(EC16:EE16) -> 0.033136667 | EG16: =ED16/EC16-1 -> 0.035215543 | EH16: =EE16/ED16-1 -> -0.050733138
C17: 79 | D17: =EF17 -> 0.036783333 | E17: =-1/2*(LN(1-D16)+LN(1-D17)) -> 0.035587513 | F17: {=SUMPRODUCT($A$6^($K$1:$DT$1+1),K17:DT17,TRANSPOSE(D17:D130))} -> 0.73203095 | G17: {=SUMPRODUCT($A$6^($K$1:$DT$1),K17:DT17)} -> 9.2002705 | H17: =(1-$A$4/$A$9*F17)/$A$15 -> 8.7376738 | I17: =G17-(12-1)/2/12-(12^2-1)/12/12^2*(E17+LN(1+$A$4)) -> 8.7365461 | K17: 1 | L17: {=IFERROR(K17*(1-INDEX($D17:$D$71,L$1)),0)} -> 0.96321667 | M17: {=IFERROR(L17*(1-INDEX($D17:$D$71,M$1)),0)} -> 0.92384358 | N17: {=IFERROR(M17*(1-INDEX($D17:$D$71,N$1)),0)} -> 0.88183641 | O17: {=IFERROR(N17*(1-INDEX($D17:$D$71,O$1)),0)} -> 0.83719197 | P17: {=IFERROR(O17*(1-INDEX($D17:$D$71,P$1)),0)} -> 0.78995202 | Q17: {=IFERROR(P17*(1-INDEX($D17:$D$71,Q$1)),0)} -> 0.74021928 | R17: {=IFERROR(Q17*(1-INDEX($D17:$D$71,R$1)),0)} -> 0.68816952 | S17: {=IFERROR(R17*(1-INDEX($D17:$D$71,S$1)),0)} -> 0.63407252 | ... DX17: {=IFERROR(DW17*(1-INDEX($D17:$D$71,DX$1)),0)} -> 0 | DZ17: 79 years | EA17: 0.03599 | EB17: 0.03698 | EC17: 0.03651 | ED17: 0.0379 | EE17: 0.03594 | EF17: =AVERAGE(EC17:EE17) -> 0.036783333 | EG17: =ED17/EC17-1 -> 0.038071761 | EH17: =EE17/ED17-1 -> -0.05171504
C18: 80 | D18: =EF18 -> 0.040876667 | E18: =-1/2*(LN(1-D17)+LN(1-D18)) -> 0.039606254 | F18: {=SUMPRODUCT($A$6^($K$1:$DT$1+1),K18:DT18,TRANSPOSE(D18:D131))} -> 0.74459732 | G18: {=SUMPRODUCT($A$6^($K$1:$DT$1),K18:DT18)} -> 8.7688253 | H18: =(1-$A$4/$A$9*F18)/$A$15 -> 8.3061974 | I18: =G18-(12-1)/2/12-(12^2-1)/12/12^2*(E18+LN(1+$A$4)) -> 8.3047682 | K18: 1 | L18: {=IFERROR(K18*(1-INDEX($D18:$D$71,L$1)),0)} -> 0.95912333 | M18: {=IFERROR(L18*(1-INDEX($D18:$D$71,M$1)),0)} -> 0.915512 | N18: {=IFERROR(M18*(1-INDEX($D18:$D$71,N$1)),0)} -> 0.86916267 | O18: {=IFERROR(N18*(1-INDEX($D18:$D$71,O$1)),0)} -> 0.82011872 | P18: {=IFERROR(O18*(1-INDEX($D18:$D$71,P$1)),0)} -> 0.76848678 | Q18: {=IFERROR(P18*(1-INDEX($D18:$D$71,Q$1)),0)} -> 0.71444935 | R18: {=IFERROR(Q18*(1-INDEX($D18:$D$71,R$1)),0)} -> 0.65828649 | S18: {=IFERROR(R18*(1-INDEX($D18:$D$71,S$1)),0)} -> 0.60037264 | ... DX18: {=IFERROR(DW18*(1-INDEX($D18:$D$71,DX$1)),0)} -> 0 | DZ18: 80 years | EA18: 0.04003 | EB18: 0.04116 | EC18: 0.04051 | ED18: 0.04216 | EE18: 0.03996 | EF18: =AVERAGE(EC18:EE18) -> 0.040876667 | EG18: =ED18/EC18-1 -> 0.040730684 | EH18: =EE18/ED18-1 -> -0.052182163
C19: 81 | D19: =EF19 -> 0.04547 | E19: =-1/2*(LN(1-D18)+LN(1-D19)) -> 0.044135906 | F19: {=SUMPRODUCT($A$6^($K$1:$DT$1+1),K19:DT19,TRANSPOSE(D19:D132))} -> 0.75700231 | G19: {=SUMPRODUCT($A$6^($K$1:$DT$1),K19:DT19)} -> 8.3429208 | H19: =(1-$A$4/$A$9*F19)/$A$15 -> 7.8802621 | I19: =G19-(12-1)/2/12-(12^2-1)/12/12^2*(E19+LN(1+$A$4)) -> 7.8784889 | K19: 1 | L19: {=IFERROR(K19*(1-INDEX($D19:$D$71,L$1)),0)} -> 0.95453 | M19: {=IFERROR(L19*(1-INDEX($D19:$D$71,M$1)),0)} -> 0.90620533 | N19: {=IFERROR(M19*(1-INDEX($D19:$D$71,N$1)),0)} -> 0.85507118 | O19: {=IFERROR(N19*(1-INDEX($D19:$D$71,O$1)),0)} -> 0.80123875 | P19: {=IFERROR(O19*(1-INDEX($D19:$D$71,P$1)),0)} -> 0.74489831 | Q19: {=IFERROR(P19*(1-INDEX($D19:$D$71,Q$1)),0)} -> 0.68634186 | R19: {=IFERROR(Q19*(1-INDEX($D19:$D$71,R$1)),0)} -> 0.62595979 | S19: {=IFERROR(R19*(1-INDEX($D19:$D$71,S$1)),0)} -> 0.56426936 | ... DX19: {=IFERROR(DW19*(1-INDEX($D19:$D$71,DX$1)),0)} -> 0 | DZ19: 81 years | EA19: 0.04456 | EB19: 0.04585 | EC19: 0.04499 | ED19: 0.04695 | EE19: 0.04447 | EF19: =AVERAGE(EC19:EE19) -> 0.04547 | EG19: =ED19/EC19-1 -> 0.043565237 | EH19: =EE19/ED19-1 -> -0.052822151
C20: 82 | D20: =EF20 -> 0.050626667 | E20: =-1/2*(LN(1-D19)+LN(1-D20)) -> 0.049244684 | F20: {=SUMPRODUCT($A$6^($K$1:$DT$1+1),K20:DT20,TRANSPOSE(D20:D133))} -> 0.76921875 | G20: {=SUMPRODUCT($A$6^($K$1:$DT$1),K20:DT20)} -> 7.9234895 | H20: =(1-$A$4/$A$9*F20)/$A$15 -> 7.4608005 | I20: =G20-(12-1)/2/12-(12^2-1)/12/12^2*(E20+LN(1+$A$4)) -> 7.4586348 | K20: 1 | L20: {=IFERROR(K20*(1-INDEX($D20:$D$71,L$1)),0)} -> 0.94937333 | M20: {=IFERROR(L20*(1-INDEX($D20:$D$71,M$1)),0)} -> 0.89580336 | N20: {=IFERROR(M20*(1-INDEX($D20:$D$71,N$1)),0)} -> 0.83940657 | O20: {=IFERROR(N20*(1-INDEX($D20:$D$71,O$1)),0)} -> 0.7803823 | P20: {=IFERROR(O20*(1-INDEX($D20:$D$71,P$1)),0)} -> 0.71903644 | Q20: {=IFERROR(P20*(1-INDEX($D20:$D$71,Q$1)),0)} -> 0.65577801 | R20: {=IFERROR(Q20*(1-INDEX($D20:$D$71,R$1)),0)} -> 0.5911489 | S20: {=IFERROR(R20*(1-INDEX($D20:$D$71,S$1)),0)} -> 0.52581513 | ... DX20: {=IFERROR(DW20*(1-INDEX($D20:$D$71,DX$1)),0)} -> 0 | DZ20: 82 years | EA20: 0.04964 | EB20: 0.05114 | EC20: 0.05001 | ED20: 0.05233 | EE20: 0.04954 | EF20: =AVERAGE(EC20:EE20) -> 0.050626667 | EG20: =ED20/EC20-1 -> 0.046390722 | EH20: =EE20/ED20-1 -> -0.053315498
C21: 83 | D21: =EF21 -> 0.056426667 | E21: =-1/2*(LN(1-D20)+LN(1-D21)) -> 0.055017177 | F21: {=SUMPRODUCT($A$6^($K$1:$DT$1+1),K21:DT21,TRANSPOSE(D21:D134))} -> 0.78121917 | G21: {=SUMPRODUCT($A$6^($K$1:$DT$1),K21:DT21)} -> 7.5114752 | H21: =(1-$A$4/$A$9*F21)/$A$15 -> 7.0487563 | I21: =G21-(12-1)/2/12-(12^2-1)/12/12^2*(E21+LN(1+$A$4)) -> 7.0461428 | K21: 1 | L21: {=IFERROR(K21*(1-INDEX($D21:$D$71,L$1)),0)} -> 0.94357333 | M21: {=IFERROR(L21*(1-INDEX($D21:$D$71,M$1)),0)} -> 0.8841691 | N21: {=IFERROR(M21*(1-INDEX($D21:$D$71,N$1)),0)} -> 0.82199728 | O21: {=IFERROR(N21*(1-INDEX($D21:$D$71,O$1)),0)} -> 0.75738007 | P21: {=IFERROR(O21*(1-INDEX($D21:$D$71,P$1)),0)} -> 0.6907483 | Q21: {=IFERROR(P21*(1-INDEX($D21:$D$71,Q$1)),0)} -> 0.62267275 | R21: {=IFERROR(Q21*(1-INDEX($D21:$D$71,R$1)),0)} -> 0.55385496 | S21: {=IFERROR(R21*(1-INDEX($D21:$D$71,S$1)),0)} -> 0.48514371 | ... DX21: {=IFERROR(DW21*(1-INDEX($D21:$D$71,DX$1)),0)} -> 0 | DZ21: 83 years | EA21: 0.05535 | EB21: 0.0571 | EC21: 0.05564 | ED21: 0.05839 | EE21: 0.05525 | EF21: =AVERAGE(EC21:EE21) -> 0.056426667 | EG21: =ED21/EC21-1 -> 0.049424874 | EH21: =EE21/ED21-1 -> -0.053776332
C22: 84 | D22: =EF22 -> 0.062956667 | E22: =-1/2*(LN(1-D21)+LN(1-D22)) -> 0.061553472 | F22: {=SUMPRODUCT($A$6^($K$1:$DT$1+1),K22:DT22,TRANSPOSE(D22:D135))} -> 0.79297396 | G22: {=SUMPRODUCT($A$6^($K$1:$DT$1),K22:DT22)} -> 7.1078942 | H22: =(1-$A$4/$A$9*F22)/$A$15 -> 6.6451462 | I22: =G22-(12-1)/2/12-(12^2-1)/12/12^2*(E22+LN(1+$A$4)) -> 6.6420209 | K22: 1 | L22: {=IFERROR(K22*(1-INDEX($D22:$D$71,L$1)),0)} -> 0.93704333 | M22: {=IFERROR(L22*(1-INDEX($D22:$D$71,M$1)),0)} -> 0.87115357 | N22: {=IFERROR(M22*(1-INDEX($D22:$D$71,N$1)),0)} -> 0.80267219 | O22: {=IFERROR(N22*(1-INDEX($D22:$D$71,O$1)),0)} -> 0.73205576 | P22: {=IFERROR(O22*(1-INDEX($D22:$D$71,P$1)),0)} -> 0.65990923 | Q22: {=IFERROR(P22*(1-INDEX($D22:$D$71,Q$1)),0)} -> 0.58697606 | R22: {=IFERROR(Q22*(1-INDEX($D22:$D$71,R$1)),0)} -> 0.51415581 | S22: {=IFERROR(R22*(1-INDEX($D22:$D$71,S$1)),0)} -> 0.44267616 | ... DX22: {=IFERROR(DW22*(1-INDEX($D22:$D$71,DX$1)),0)} -> 0 | DZ22: 84 years | EA22: 0.06176 | EB22: 0.06382 | EC22: 0.06196 | ED22: 0.06523 | EE22: 0.06168 | EF22: =AVERAGE(EC22:EE22) -> 0.062956667 | EG22: =ED22/EC22-1 -> 0.052775985 | EH22: =EE22/ED22-1 -> -0.054422812
C23: 85 | D23: =EF23 -> 0.070316667 | E23: =-1/2*(LN(1-D22)+LN(1-D23)) -> 0.068968502 | F23: {=SUMPRODUCT($A$6^($K$1:$DT$1+1),K23:DT23,TRANSPOSE(D23:D136))} -> 0.80445213 | G23: {=SUMPRODUCT($A$6^($K$1:$DT$1),K23:DT23)} -> 6.7138101 | H23: =(1-$A$4/$A$9*F23)/$A$15 -> 6.2510336 | I23: =G23-(12-1)/2/12-(12^2-1)/12/12^2*(E23+LN(1+$A$4)) -> 6.2473232 | K23: 1 | L23: {=IFERROR(K23*(1-INDEX($D23:$D$71,L$1)),0)} -> 0.92968333 | M23: {=IFERROR(L23*(1-INDEX($D23:$D$71,M$1)),0)} -> 0.85660093 | N23: {=IFERROR(M23*(1-INDEX($D23:$D$71,N$1)),0)} -> 0.78124003 | O23: {=IFERROR(N23*(1-INDEX($D23:$D$71,O$1)),0)} -> 0.70424622 | P23: {=IFERROR(O23*(1-INDEX($D23:$D$71,P$1)),0)} -> 0.62641293 | Q23: {=IFERROR(P23*(1-INDEX($D23:$D$71,Q$1)),0)} -> 0.54870014 | R23: {=IFERROR(Q23*(1-INDEX($D23:$D$71,R$1)),0)} -> 0.47241802 | S23: {=IFERROR(R23*(1-INDEX($D23:$D$71,S$1)),0)} -> 0.39914126 | ... DX23: {=IFERROR(DW23*(1-INDEX($D23:$D$71,DX$1)),0)} -> 0 | DZ23: 85 years | EA23: 0.06896 | EB23: 0.0714 | EC23: 0.06907 | ED23: 0.07294 | EE23: 0.06894 | EF23: =AVERAGE(EC23:EE23) -> 0.070316667 | EG23: =ED23/EC23-1 -> 0.056030114 | EH23: =EE23/ED23-1 -> -0.054839594
C24: 86 | D24: =EF24 -> 0.07861 | E24: =-1/2*(LN(1-D23)+LN(1-D24)) -> 0.077391566 | F24: {=SUMPRODUCT($A$6^($K$1:$DT$1+1),K24:DT24,TRANSPOSE(D24:D137))} -> 0.81562076 | G24: {=SUMPRODUCT($A$6^($K$1:$DT$1),K24:DT24)} -> 6.3303538 | H24: =(1-$A$4/$A$9*F24)/$A$15 -> 5.8675496 | I24: =G24-(12-1)/2/12-(12^2-1)/12/12^2*(E24+LN(1+$A$4)) -> 5.8631698 | K24: 1 | L24: {=IFERROR(K24*(1-INDEX($D24:$D$71,L$1)),0)} -> 0.92139 | M24: {=IFERROR(L24*(1-INDEX($D24:$D$71,M$1)),0)} -> 0.84032918 | N24: {=IFERROR(M24*(1-INDEX($D24:$D$71,N$1)),0)} -> 0.75751194 | O24: {=IFERROR(N24*(1-INDEX($D24:$D$71,O$1)),0)} -> 0.67379172 | P24: {=IFERROR(O24*(1-INDEX($D24:$D$71,P$1)),0)} -> 0.59020112 | Q24: {=IFERROR(P24*(1-INDEX($D24:$D$71,Q$1)),0)} -> 0.50814939 | R24: {=IFERROR(Q24*(1-INDEX($D24:$D$71,R$1)),0)} -> 0.42933034 | S24: {=IFERROR(R24*(1-INDEX($D24:$D$71,S$1)),0)} -> 0.35535958 | ... DX24: {=IFERROR(DW24*(1-INDEX($D24:$D$71,DX$1)),0)} -> 0 | DZ24: 86 years | EA24: 0.07708 | EB24: 0.07998 | EC24: 0.07706 | ED24: 0.08164 | EE24: 0.07713 | EF24: =AVERAGE(EC24:EE24) -> 0.07861 | EG24: =ED24/EC24-1 -> 0.059434207 | EH24: =EE24/ED24-1 -> -0.055242528
C25: 87 | D25: =EF25 -> 0.087976667 | E25: =-1/2*(LN(1-D24)+LN(1-D25)) -> 0.086980792 | F25: {=SUMPRODUCT($A$6^($K$1:$DT$1+1),K25:DT25,TRANSPOSE(D25:D138))} -> 0.82644633 | G25: {=SUMPRODUCT($A$6^($K$1:$DT$1),K25:DT25)} -> 5.9586759 | H25: =(1-$A$4/$A$9*F25)/$A$15 -> 5.4958448 | I25: =G25-(12-1)/2/12-(12^2-1)/12/12^2*(E25+LN(1+$A$4)) -> 5.4906984 | K25: 1 | L25: {=IFERROR(K25*(1-INDEX($D25:$D$71,L$1)),0)} -> 0.91202333 | M25: {=IFERROR(L25*(1-INDEX($D25:$D$71,M$1)),0)} -> 0.82214039 | N25: {=IFERROR(M25*(1-INDEX($D25:$D$71,N$1)),0)} -> 0.73127744 | O25: {=IFERROR(N25*(1-INDEX($D25:$D$71,O$1)),0)} -> 0.64055516 | P25: {=IFERROR(O25*(1-INDEX($D25:$D$71,P$1)),0)} -> 0.55150305 | Q25: {=IFERROR(P25*(1-INDEX($D25:$D$71,Q$1)),0)} -> 0.46595941 | R25: {=IFERROR(Q25*(1-INDEX($D25:$D$71,R$1)),0)} -> 0.38567771 | S25: {=IFERROR(R25*(1-INDEX($D25:$D$71,S$1)),0)} -> 0.31219068 | ... DX25: {=IFERROR(DW25*(1-INDEX($D25:$D$71,DX$1)),0)} -> 0 | DZ25: 87 years | EA25: 0.08621 | EB25: 0.08967 | EC25: 0.08606 | ED25: 0.09148 | EE25: 0.08639 | EF25: =AVERAGE(EC25:EE25) -> 0.087976667 | EG25: =ED25/EC25-1 -> 0.062979317 | EH25: =EE25/ED25-1 -> -0.055640577
C26: 88 | D26: =EF26 -> 0.098553333 | E26: =-1/2*(LN(1-D25)+LN(1-D26)) -> 0.097922052 | F26: {=SUMPRODUCT($A$6^($K$1:$DT$1+1),K26:DT26,TRANSPOSE(D26:D139))} -> 0.83688983 | G26: {=SUMPRODUCT($A$6^($K$1:$DT$1),K26:DT26)} -> 5.6001157 | H26: =(1-$A$4/$A$9*F26)/$A$15 -> 5.1372587 | I26: =G26-(12-1)/2/12-(12^2-1)/12/12^2*(E26+LN(1+$A$4)) -> 5.1312328 | K26: 1 | L26: {=IFERROR(K26*(1-INDEX($D26:$D$71,L$1)),0)} -> 0.90144667 | M26: {=IFERROR(L26*(1-INDEX($D26:$D$71,M$1)),0)} -> 0.80181878 | N26: {=IFERROR(M26*(1-INDEX($D26:$D$71,N$1)),0)} -> 0.70234514 | O26: {=IFERROR(N26*(1-INDEX($D26:$D$71,O$1)),0)} -> 0.60470278 | P26: {=IFERROR(O26*(1-INDEX($D26:$D$71,P$1)),0)} -> 0.51090733 | Q26: {=IFERROR(P26*(1-INDEX($D26:$D$71,Q$1)),0)} -> 0.4228814 | R26: {=IFERROR(Q26*(1-INDEX($D26:$D$71,R$1)),0)} -> 0.34230558 | S26: {=IFERROR(R26*(1-INDEX($D26:$D$71,S$1)),0)} -> 0.26972767 | ... DX26: {=IFERROR(DW26*(1-INDEX($D26:$D$71,DX$1)),0)} -> 0 | DZ26: 88 years | EA26: 0.09651 | EB26: 0.10065 | EC26: 0.0962 | ED26: 0.10261 | EE26: 0.09685 | EF26: =AVERAGE(EC26:EE26) -> 0.098553333 | EG26: =ED26/EC26-1 -> 0.066632017 | EH26: =EE26/ED26-1 -> -0.05613488
C27: 89 | D27: =EF27 -> 0.11052 | E27: =-1/2*(LN(1-D26)+LN(1-D27)) -> 0.11043633 | F27: {=SUMPRODUCT($A$6^($K$1:$DT$1+1),K27:DT27,TRANSPOSE(D27:D140))} -> 0.84690889 | G27: {=SUMPRODUCT($A$6^($K$1:$DT$1),K27:DT27)} -> 5.2561282 | H27: =(1-$A$4/$A$9*F27)/$A$15 -> 4.7932463 | I27: =G27-(12-1)/2/12-(12^2-1)/12/12^2*(E27+LN(1+$A$4)) -> 4.7862096 | K27: 1 | L27: {=IFERROR(K27*(1-INDEX($D27:$D$71,L$1)),0)} -> 0.88948 | M27: {=IFERROR(L27*(1-INDEX($D27:$D$71,M$1)),0)} -> 0.77913111 | N27: {=IFERROR(M27*(1-INDEX($D27:$D$71,N$1)),0)} -> 0.67081371 | O27: {=IFERROR(N27*(1-INDEX($D27:$D$71,O$1)),0)} -> 0.56676379 | P27: {=IFERROR(O27*(1-INDEX($D27:$D$71,P$1)),0)} -> 0.46911417 | Q27: {=IFERROR(P27*(1-INDEX($D27:$D$71,Q$1)),0)} -> 0.37972916 | R27: {=IFERROR(Q27*(1-INDEX($D27:$D$71,R$1)),0)} -> 0.29921645 | S27: {=IFERROR(R27*(1-INDEX($D27:$D$71,S$1)),0)} -> 0.22972941 | ... DX27: {=IFERROR(DW27*(1-INDEX($D27:$D$71,DX$1)),0)} -> 0 | DZ27: 89 years | EA27: 0.10812 | EB27: 0.11309 | EC27: 0.10764 | ED27: 0.11521 | EE27: 0.10871 | EF27: =AVERAGE(EC27:EE27) -> 0.11052 | EG27: =ED27/EC27-1 -> 0.070327016 | EH27: =EE27/ED27-1 -> -0.056418714
... C48: 110 | D48: =EF48 -> 1 | E48: =-1/2*(LN(1-D47)+LN(1-D48)) -> #NUM! | F48: {=SUMPRODUCT($A$6^($K$1:$DT$1+1),K48:DT48,TRANSPOSE(D48:D161))} -> 0.97087379 | G48: {=SUMPRODUCT($A$6^($K$1:$DT$1),K48:DT48)} -> 1 | H48: =(1-$A$4/$A$9*F48)/$A$15 -> 0.53681035 | I48: =G48-(12-1)/2/12-(12^2-1)/12/12^2*(E48+LN(1+$A$4)) -> #NUM! | K48: 1 | L48: {=IFERROR(K48*(1-INDEX($D48:$D$71,L$1)),0)} -> 0 | M48: {=IFERROR(L48*(1-INDEX($D48:$D$71,M$1)),0)} -> 0 | N48: {=IFERROR(M48*(1-INDEX($D48:$D$71,N$1)),0)} -> 0 | O48: {=IFERROR(N48*(1-INDEX($D48:$D$71,O$1)),0)} -> 0 | P48: {=IFERROR(O48*(1-INDEX($D48:$D$71,P$1)),0)} -> 0 | Q48: {=IFERROR(P48*(1-INDEX($D48:$D$71,Q$1)),0)} -> 0 | R48: {=IFERROR(Q48*(1-INDEX($D48:$D$71,R$1)),0)} -> 0 | S48: {=IFERROR(R48*(1-INDEX($D48:$D$71,S$1)),0)} -> 0 | ... DX48: {=IFERROR(DW48*(1-INDEX($D48:$D$71,DX$1)),0)} -> 0 | DZ48: 110 years and over | EA48: 1 | EB48: 1 | EC48: 1 | ED48: 1 | EE48: 1 | EF48: =AVERAGE(EC48:EE48) -> 1 | EG48: =ED48/EC48-1 -> 0 | EH48: =EE48/ED48-1 -> 0
C49: 111 | D49: =EF49 -> 0 | E49: =-1/2*(LN(1-D48)+LN(1-D49)) -> #NUM! | F49: {=SUMPRODUCT($A$6^($K$1:$DT$1+1),K49:DT49,TRANSPOSE(D49:D162))} -> 0 | G49: {=SUMPRODUCT($A$6^($K$1:$DT$1),K49:DT49)} -> 17.443608 | H49: =(1-$A$4/$A$9*F49)/$A$15 -> 33.872554 | I49: =G49-(12-1)/2/12-(12^2-1)/12/12^2*(E49+LN(1+$A$4)) -> #NUM! | K49: 1 | L49: {=IFERROR(K49*(1-INDEX($D49:$D$71,L$1)),0)} -> 1 | M49: {=IFERROR(L49*(1-INDEX($D49:$D$71,M$1)),0)} -> 1 | N49: {=IFERROR(M49*(1-INDEX($D49:$D$71,N$1)),0)} -> 1 | O49: {=IFERROR(N49*(1-INDEX($D49:$D$71,O$1)),0)} -> 1 | P49: {=IFERROR(O49*(1-INDEX($D49:$D$71,P$1)),0)} -> 1 | Q49: {=IFERROR(P49*(1-INDEX($D49:$D$71,Q$1)),0)} -> 1 | R49: {=IFERROR(Q49*(1-INDEX($D49:$D$71,R$1)),0)} -> 1 | S49: {=IFERROR(R49*(1-INDEX($D49:$D$71,S$1)),0)} -> 1 | ... DX49: {=IFERROR(DW49*(1-INDEX($D49:$D$71,DX$1)),0)} -> 0
C50: 112 | D50: =EF50 -> 0 | E50: =-1/2*(LN(1-D49)+LN(1-D50)) -> 0 | F50: {=SUMPRODUCT($A$6^($K$1:$DT$1+1),K50:DT50,TRANSPOSE(D50:D163))} -> 0 | G50: {=SUMPRODUCT($A$6^($K$1:$DT$1),K50:DT50)} -> 16.936917 | H50: =(1-$A$4/$A$9*F50)/$A$15 -> 33.872554 | I50: =G50-(12-1)/2/12-(12^2-1)/12/12^2*(E50+LN(1+$A$4)) -> 16.476137 | K50: 1 | L50: {=IFERROR(K50*(1-INDEX($D50:$D$71,L$1)),0)} -> 1 | M50: {=IFERROR(L50*(1-INDEX($D50:$D$71,M$1)),0)} -> 1 | N50: {=IFERROR(M50*(1-INDEX($D50:$D$71,N$1)),0)} -> 1 | O50: {=IFERROR(N50*(1-INDEX($D50:$D$71,O$1)),0)} -> 1 | P50: {=IFERROR(O50*(1-INDEX($D50:$D$71,P$1)),0)} -> 1 | Q50: {=IFERROR(P50*(1-INDEX($D50:$D$71,Q$1)),0)} -> 1 | R50: {=IFERROR(Q50*(1-INDEX($D50:$D$71,R$1)),0)} -> 1 | S50: {=IFERROR(R50*(1-INDEX($D50:$D$71,S$1)),0)} -> 1 | ... DX50: {=IFERROR(DW50*(1-INDEX($D50:$D$71,DX$1)),0)} -> 0
C51: 113 | D51: =EF51 -> 0 | E51: =-1/2*(LN(1-D50)+LN(1-D51)) -> 0 | F51: {=SUMPRODUCT($A$6^($K$1:$DT$1+1),K51:DT51,TRANSPOSE(D51:D164))} -> 0 | G51: {=SUMPRODUCT($A$6^($K$1:$DT$1),K51:DT51)} -> 16.415024 | H51: =(1-$A$4/$A$9*F51)/$A$15 -> 33.872554 | I51: =G51-(12-1)/2/12-(12^2-1)/12/12^2*(E51+LN(1+$A$4)) -> 15.954245 | K51: 1 | L51: {=IFERROR(K51*(1-INDEX($D51:$D$71,L$1)),0)} -> 1 | M51: {=IFERROR(L51*(1-INDEX($D51:$D$71,M$1)),0)} -> 1 | N51: {=IFERROR(M51*(1-INDEX($D51:$D$71,N$1)),0)} -> 1 | O51: {=IFERROR(N51*(1-INDEX($D51:$D$71,O$1)),0)} -> 1 | P51: {=IFERROR(O51*(1-INDEX($D51:$D$71,P$1)),0)} -> 1 | Q51: {=IFERROR(P51*(1-INDEX($D51:$D$71,Q$1)),0)} -> 1 | R51: {=IFERROR(Q51*(1-INDEX($D51:$D$71,R$1)),0)} -> 1 | S51: {=IFERROR(R51*(1-INDEX($D51:$D$71,S$1)),0)} -> 1 | ... DX51: {=IFERROR(DW51*(1-INDEX($D51:$D$71,DX$1)),0)} -> 0
C52: 114 | D52: =EF52 -> 0 | E52: =-1/2*(LN(1-D51)+LN(1-D52)) -> 0 | F52: {=SUMPRODUCT($A$6^($K$1:$DT$1+1),K52:DT52,TRANSPOSE(D52:D165))} -> 0 | G52: {=SUMPRODUCT($A$6^($K$1:$DT$1),K52:DT52)} -> 15.877475 | H52: =(1-$A$4/$A$9*F52)/$A$15 -> 33.872554 | I52: =G52-(12-1)/2/12-(12^2-1)/12/12^2*(E52+LN(1+$A$4)) -> 15.416695 | K52: 1 | L52: {=IFERROR(K52*(1-INDEX($D52:$D$71,L$1)),0)} -> 1 | M52: {=IFERROR(L52*(1-INDEX($D52:$D$71,M$1)),0)} -> 1 | N52: {=IFERROR(M52*(1-INDEX($D52:$D$71,N$1)),0)} -> 1 | O52: {=IFERROR(N52*(1-INDEX($D52:$D$71,O$1)),0)} -> 1 | P52: {=IFERROR(O52*(1-INDEX($D52:$D$71,P$1)),0)} -> 1 | Q52: {=IFERROR(P52*(1-INDEX($D52:$D$71,Q$1)),0)} -> 1 | R52: {=IFERROR(Q52*(1-INDEX($D52:$D$71,R$1)),0)} -> 1 | S52: {=IFERROR(R52*(1-INDEX($D52:$D$71,S$1)),0)} -> 1 | ... DX52: {=IFERROR(DW52*(1-INDEX($D52:$D$71,DX$1)),0)} -> 0
C53: 115 | D53: =EF53 -> 0 | E53: =-1/2*(LN(1-D52)+LN(1-D53)) -> 0 | F53: {=SUMPRODUCT($A$6^($K$1:$DT$1+1),K53:DT53,TRANSPOSE(D53:D166))} -> 0 | G53: {=SUMPRODUCT($A$6^($K$1:$DT$1),K53:DT53)} -> 15.323799 | H53: =(1-$A$4/$A$9*F53)/$A$15 -> 33.872554 | I53: =G53-(12-1)/2/12-(12^2-1)/12/12^2*(E53+LN(1+$A$4)) -> 14.86302 | K53: 1 | L53: {=IFERROR(K53*(1-INDEX($D53:$D$71,L$1)),0)} -> 1 | M53: {=IFERROR(L53*(1-INDEX($D53:$D$71,M$1)),0)} -> 1 | N53: {=IFERROR(M53*(1-INDEX($D53:$D$71,N$1)),0)} -> 1 | O53: {=IFERROR(N53*(1-INDEX($D53:$D$71,O$1)),0)} -> 1 | P53: {=IFERROR(O53*(1-INDEX($D53:$D$71,P$1)),0)} -> 1 | Q53: {=IFERROR(P53*(1-INDEX($D53:$D$71,Q$1)),0)} -> 1 | R53: {=IFERROR(Q53*(1-INDEX($D53:$D$71,R$1)),0)} -> 1 | S53: {=IFERROR(R53*(1-INDEX($D53:$D$71,S$1)),0)} -> 1 | ... DX53: {=IFERROR(DW53*(1-INDEX($D53:$D$71,DX$1)),0)} -> 0
C54: 116 | D54: =EF54 -> 0 | E54: =-1/2*(LN(1-D53)+LN(1-D54)) -> 0 | F54: {=SUMPRODUCT($A$6^($K$1:$DT$1+1),K54:DT54,TRANSPOSE(D54:D167))} -> 0 | G54: {=SUMPRODUCT($A$6^($K$1:$DT$1),K54:DT54)} -> 14.753513 | H54: =(1-$A$4/$A$9*F54)/$A$15 -> 33.872554 | I54: =G54-(12-1)/2/12-(12^2-1)/12/12^2*(E54+LN(1+$A$4)) -> 14.292734 | K54: 1 | L54: {=IFERROR(K54*(1-INDEX($D54:$D$71,L$1)),0)} -> 1 | M54: {=IFERROR(L54*(1-INDEX($D54:$D$71,M$1)),0)} -> 1 | N54: {=IFERROR(M54*(1-INDEX($D54:$D$71,N$1)),0)} -> 1 | O54: {=IFERROR(N54*(1-INDEX($D54:$D$71,O$1)),0)} -> 1 | P54: {=IFERROR(O54*(1-INDEX($D54:$D$71,P$1)),0)} -> 1 | Q54: {=IFERROR(P54*(1-INDEX($D54:$D$71,Q$1)),0)} -> 1 | R54: {=IFERROR(Q54*(1-INDEX($D54:$D$71,R$1)),0)} -> 1 | S54: {=IFERROR(R54*(1-INDEX($D54:$D$71,S$1)),0)} -> 1 | ... DX54: {=IFERROR(DW54*(1-INDEX($D54:$D$71,DX$1)),0)} -> 0
C55: 117 | D55: =EF55 -> 0 | E55: =-1/2*(LN(1-D54)+LN(1-D55)) -> 0 | F55: {=SUMPRODUCT($A$6^($K$1:$DT$1+1),K55:DT55,TRANSPOSE(D55:D168))} -> 0 | G55: {=SUMPRODUCT($A$6^($K$1:$DT$1),K55:DT55)} -> 14.166118 | H55: =(1-$A$4/$A$9*F55)/$A$15 -> 33.872554 | I55: =G55-(12-1)/2/12-(12^2-1)/12/12^2*(E55+LN(1+$A$4)) -> 13.705339 | K55: 1 | L55: {=IFERROR(K55*(1-INDEX($D55:$D$71,L$1)),0)} -> 1 | M55: {=IFERROR(L55*(1-INDEX($D55:$D$71,M$1)),0)} -> 1 | N55: {=IFERROR(M55*(1-INDEX($D55:$D$71,N$1)),0)} -> 1 | O55: {=IFERROR(N55*(1-INDEX($D55:$D$71,O$1)),0)} -> 1 | P55: {=IFERROR(O55*(1-INDEX($D55:$D$71,P$1)),0)} -> 1 | Q55: {=IFERROR(P55*(1-INDEX($D55:$D$71,Q$1)),0)} -> 1 | R55: {=IFERROR(Q55*(1-INDEX($D55:$D$71,R$1)),0)} -> 1 | S55: {=IFERROR(R55*(1-INDEX($D55:$D$71,S$1)),0)} -> 1 | ... DX55: {=IFERROR(DW55*(1-INDEX($D55:$D$71,DX$1)),0)} -> 0
C56: 118 | D56: =EF56 -> 0 | E56: =-1/2*(LN(1-D55)+LN(1-D56)) -> 0 | F56: {=SUMPRODUCT($A$6^($K$1:$DT$1+1),K56:DT56,TRANSPOSE(D56:D169))} -> 0 | G56: {=SUMPRODUCT($A$6^($K$1:$DT$1),K56:DT56)} -> 13.561102 | H56: =(1-$A$4/$A$9*F56)/$A$15 -> 33.872554 | I56: =G56-(12-1)/2/12-(12^2-1)/12/12^2*(E56+LN(1+$A$4)) -> 13.100323 | K56: 1 | L56: {=IFERROR(K56*(1-INDEX($D56:$D$71,L$1)),0)} -> 1 | M56: {=IFERROR(L56*(1-INDEX($D56:$D$71,M$1)),0)} -> 1 | N56: {=IFERROR(M56*(1-INDEX($D56:$D$71,N$1)),0)} -> 1 | O56: {=IFERROR(N56*(1-INDEX($D56:$D$71,O$1)),0)} -> 1 | P56: {=IFERROR(O56*(1-INDEX($D56:$D$71,P$1)),0)} -> 1 | Q56: {=IFERROR(P56*(1-INDEX($D56:$D$71,Q$1)),0)} -> 1 | R56: {=IFERROR(Q56*(1-INDEX($D56:$D$71,R$1)),0)} -> 1 | S56: {=IFERROR(R56*(1-INDEX($D56:$D$71,S$1)),0)} -> 1 | ... DX56: {=IFERROR(DW56*(1-INDEX($D56:$D$71,DX$1)),0)} -> 0
C57: 119 | D57: =EF57 -> 0 | E57: =-1/2*(LN(1-D56)+LN(1-D57)) -> 0 | F57: {=SUMPRODUCT($A$6^($K$1:$DT$1+1),K57:DT57,TRANSPOSE(D57:D170))} -> 0 | G57: {=SUMPRODUCT($A$6^($K$1:$DT$1),K57:DT57)} -> 12.937935 | H57: =(1-$A$4/$A$9*F57)/$A$15 -> 33.872554 | I57: =G57-(12-1)/2/12-(12^2-1)/12/12^2*(E57+LN(1+$A$4)) -> 12.477156 | K57: 1 | L57: {=IFERROR(K57*(1-INDEX($D57:$D$71,L$1)),0)} -> 1 | M57: {=IFERROR(L57*(1-INDEX($D57:$D$71,M$1)),0)} -> 1 | N57: {=IFERROR(M57*(1-INDEX($D57:$D$71,N$1)),0)} -> 1 | O57: {=IFERROR(N57*(1-INDEX($D57:$D$71,O$1)),0)} -> 1 | P57: {=IFERROR(O57*(1-INDEX($D57:$D$71,P$1)),0)} -> 1 | Q57: {=IFERROR(P57*(1-INDEX($D57:$D$71,Q$1)),0)} -> 1 | R57: {=IFERROR(Q57*(1-INDEX($D57:$D$71,R$1)),0)} -> 1 | S57: {=IFERROR(R57*(1-INDEX($D57:$D$71,S$1)),0)} -> 1 | ... DX57: {=IFERROR(DW57*(1-INDEX($D57:$D$71,DX$1)),0)} -> 0
C58: 120 | D58: =EF58 -> 0 | E58: =-1/2*(LN(1-D57)+LN(1-D58)) -> 0 | F58: {=SUMPRODUCT($A$6^($K$1:$DT$1+1),K58:DT58,TRANSPOSE(D58:D171))} -> 0 | G58: {=SUMPRODUCT($A$6^($K$1:$DT$1),K58:DT58)} -> 12.296073 | H58: =(1-$A$4/$A$9*F58)/$A$15 -> 33.872554 | I58: =G58-(12-1)/2/12-(12^2-1)/12/12^2*(E58+LN(1+$A$4)) -> 11.835294 | K58: 1 | L58: {=IFERROR(K58*(1-INDEX($D58:$D$71,L$1)),0)} -> 1 | M58: {=IFERROR(L58*(1-INDEX($D58:$D$71,M$1)),0)} -> 1 | N58: {=IFERROR(M58*(1-INDEX($D58:$D$71,N$1)),0)} -> 1 | O58: {=IFERROR(N58*(1-INDEX($D58:$D$71,O$1)),0)} -> 1 | P58: {=IFERROR(O58*(1-INDEX($D58:$D$71,P$1)),0)} -> 1 | Q58: {=IFERROR(P58*(1-INDEX($D58:$D$71,Q$1)),0)} -> 1 | R58: {=IFERROR(Q58*(1-INDEX($D58:$D$71,R$1)),0)} -> 1 | S58: {=IFERROR(R58*(1-INDEX($D58:$D$71,S$1)),0)} -> 1 | ... DX58: {=IFERROR(DW58*(1-INDEX($D58:$D$71,DX$1)),0)} -> 0
C59: 121 | D59: =EF59 -> 0 | E59: =-1/2*(LN(1-D58)+LN(1-D59)) -> 0 | F59: {=SUMPRODUCT($A$6^($K$1:$DT$1+1),K59:DT59,TRANSPOSE(D59:D172))} -> 0 | G59: {=SUMPRODUCT($A$6^($K$1:$DT$1),K59:DT59)} -> 11.634955 | H59: =(1-$A$4/$A$9*F59)/$A$15 -> 33.872554 | I59: =G59-(12-1)/2/12-(12^2-1)/12/12^2*(E59+LN(1+$A$4)) -> 11.174176 | K59: 1 | L59: {=IFERROR(K59*(1-INDEX($D59:$D$71,L$1)),0)} -> 1 | M59: {=IFERROR(L59*(1-INDEX($D59:$D$71,M$1)),0)} -> 1 | N59: {=IFERROR(M59*(1-INDEX($D59:$D$71,N$1)),0)} -> 1 | O59: {=IFERROR(N59*(1-INDEX($D59:$D$71,O$1)),0)} -> 1 | P59: {=IFERROR(O59*(1-INDEX($D59:$D$71,P$1)),0)} -> 1 | Q59: {=IFERROR(P59*(1-INDEX($D59:$D$71,Q$1)),0)} -> 1 | R59: {=IFERROR(Q59*(1-INDEX($D59:$D$71,R$1)),0)} -> 1 | S59: {=IFERROR(R59*(1-INDEX($D59:$D$71,S$1)),0)} -> 1 | ... DX59: {=IFERROR(DW59*(1-INDEX($D59:$D$71,DX$1)),0)} -> 0
C60: 122 | D60: =EF60 -> 0 | E60: =-1/2*(LN(1-D59)+LN(1-D60)) -> 0 | F60: {=SUMPRODUCT($A$6^($K$1:$DT$1+1),K60:DT60,TRANSPOSE(D60:D173))} -> 0 | G60: {=SUMPRODUCT($A$6^($K$1:$DT$1),K60:DT60)} -> 10.954004 | H60: =(1-$A$4/$A$9*F60)/$A$15 -> 33.872554 | I60: =G60-(12-1)/2/12-(12^2-1)/12/12^2*(E60+LN(1+$A$4)) -> 10.493225 | K60: 1 | L60: {=IFERROR(K60*(1-INDEX($D60:$D$71,L$1)),0)} -> 1 | M60: {=IFERROR(L60*(1-INDEX($D60:$D$71,M$1)),0)} -> 1 | N60: {=IFERROR(M60*(1-INDEX($D60:$D$71,N$1)),0)} -> 1 | O60: {=IFERROR(N60*(1-INDEX($D60:$D$71,O$1)),0)} -> 1 | P60: {=IFERROR(O60*(1-INDEX($D60:$D$71,P$1)),0)} -> 1 | Q60: {=IFERROR(P60*(1-INDEX($D60:$D$71,Q$1)),0)} -> 1 | R60: {=IFERROR(Q60*(1-INDEX($D60:$D$71,R$1)),0)} -> 1 | S60: {=IFERROR(R60*(1-INDEX($D60:$D$71,S$1)),0)} -> 1 | ... DX60: {=IFERROR(DW60*(1-INDEX($D60:$D$71,DX$1)),0)} -> 0
... C71: 133 | D71: =EF71 -> 0 | E71: =-1/2*(LN(1-D70)+LN(1-D71)) -> 0 | F71: {=SUMPRODUCT($A$6^($K$1:$DT$1+1),K71:DT71,TRANSPOSE(D71:D184))} -> 0 | G71: {=SUMPRODUCT($A$6^($K$1:$DT$1),K71:DT71)} -> 1.9708738 | H71: =(1-$A$4/$A$9*F71)/$A$15 -> 33.872554 | I71: =G71-(12-1)/2/12-(12^2-1)/12/12^2*(E71+LN(1+$A$4)) -> 1.5100943 | K71: 1 | L71: {=IFERROR(K71*(1-INDEX($D71:$D$71,L$1)),0)} -> 1 | M71: {=IFERROR(L71*(1-INDEX($D71:$D$71,M$1)),0)} -> 0 | N71: {=IFERROR(M71*(1-INDEX($D71:$D$71,N$1)),0)} -> 0 | O71: {=IFERROR(N71*(1-INDEX($D71:$D$71,O$1)),0)} -> 0 | P71: {=IFERROR(O71*(1-INDEX($D71:$D$71,P$1)),0)} -> 0 | Q71: {=IFERROR(P71*(1-INDEX($D71:$D$71,Q$1)),0)} -> 0 | R71: {=IFERROR(Q71*(1-INDEX($D71:$D$71,R$1)),0)} -> 0 | S71: {=IFERROR(R71*(1-INDEX($D71:$D$71,S$1)),0)} -> 0 | ... DX71: {=IFERROR(DW71*(1-INDEX($D71:$D$71,DX$1)),0)} -> 0

Sheet Payments
B1: Qualified Age | C1: Income | D1: Residency | F1: B(65,0) | G1: Max Income | H1: 75 and above | K1: Interest | L1: i_12 | M1: d | N1: d_12 | DO1: mu_75 | DP1: A_75 | DQ1: a_75 | DR1: (UDD) | DS1: (WH3)
B2: =65+MAX(10-$D$2,0) -> 65 | C2: =Calculations!B3 -> 142609 | D2: =Calculations!D3 -> 15 | F2: =727.67*MAX(FLOOR(MIN($D$2,40),1),10)/40 -> 272.87625 | G2: =Calculations!B9 -> 142609 | H2: =Calculations!C9 -> 148179 | K2: =Calculations!B6 -> 0.03 | L2: =12*((1+K2)^(1/12)-1) -> 0.029595237 | M2: =1-1/(1+K2) -> 0.029126214 | N2: =(1-(1+K2)^(-1/12))*12 -> 0.029522427 | DO2: ='Life Table'!E13 -> 0.028389182 | DP2: ='Life Table'!F13 -> 0.70222735 | DQ2: ='Life Table'!G13 -> 10.223528 | DR2: ='Life Table'!H13 -> 9.7610048 | DS2: ='Life Table'!I13 -> 9.7603988
B3: k | C3: 0 | D3: 1 | E3: 2 | F3: 3 | G3: 4 | H3: 5 | I3: 6 | J3: 7 | K3: 8 | L3: 9 | M3: 10 | N3: 11 | O3: 12 | P3: 13 | Q3: 14 | R3: 15 | S3: 16 | T3: 17 | U3: 18 | V3: 19 | W3: 20 | X3: 21 | Y3: 22 | Z3: 23 | AA3: 24 | AB3: 25 | AC3: 26 | AD3: 27 | AE3: 28 | AF3: 29 | AG3: 30 | AH3: 31 | AI3: 32 | AJ3: 33 | AK3: 34 | AL3: 35 | AM3: 36 | AN3: 37 | AO3: 38 | AP3: 39 | AQ3: 40 | AR3: 41 | AS3: 42 | AT3: 43 | AU3: 44 | AV3: 45 | AW3: 46 | AX3: 47 | AY3: 48 | AZ3: 49 | BA3: 50 | BB3: 51 | BC3: 52 | BD3: 53 | BE3: 54 | BF3: 55 | BG3: 56 | BH3: 57 | BI3: 58 | BJ3: 59 | BK3: 60 | BL3: 61 | BM3: 62 | BN3: 63 | BO3: 64 | BP3: 65 | BQ3: 66 | BR3: 67 | BS3: 68 | BT3: 69 | BU3: 70 | BV3: 71 | BW3: 72 | BX3: 73 | BY3: 74 | BZ3: 75 | CA3: 76 | CB3: 77 | CC3: 78 | CD3: 79 | CE3: 80 | CF3: 81 | CG3: 82 | CH3: 83 | CI3: 84 | CJ3: 85 | CK3: 86 | CL3: 87 | CM3: 88 | CN3: 89 | CO3: 90 | CP3: 91 | CQ3: 92 | CR3: 93 | CS3: 94 | CT3: 95 | CU3: 96 | CV3: 97 | CW3: 98 | CX3: 99 | CY3: 100 | CZ3: 101 | DA3: 102 | DB3: 103 | DC3: 104 | DD3: 105 | DE3: 106 | DF3: 107 | DG3: 108 | DH3: 109 | DI3: 110 | DJ3: 111 | DK3: 112 | DL3: 113 | DM3: 114 | DN3: 115 | DO3: 116 | DP3: 117 | DQ3: 118 | DR3: 119 | DS3: 120
B4: k/12_p_65 | C4: {=INDEX('Life Table'!$L$3:$BF$71,1,1+FLOOR(C3/12,1))*(1-(C3/12-FLOOR(C3/12,1))*INDEX('Life Table'!$D$3:$D$71,1+FLOOR(C3/12,1)))} -> 1 | D4: {=INDEX('Life Table'!$L$3:$BF$71,1,1+FLOOR(D3/12,1))*(1-(D3/12-FLOOR(D3/12,1))*INDEX('Life Table'!$D$3:$D$71,1+FLOOR(D3/12,1)))} -> 0.9990535 | E4: {=INDEX('Life Table'!$L$3:$BF$71,1,1+FLOOR(E3/12,1))*(1-(E3/12-FLOOR(E3/12,1))*INDEX('Life Table'!$D$3:$D$71,1+FLOOR(E3/12,1)))} -> 0.998107 | F4: {=INDEX('Life Table'!$L$3:$BF$71,1,1+FLOOR(F3/12,1))*(1-(F3/12-FLOOR(F3/12,1))*INDEX('Life Table'!$D$3:$D$71,1+FLOOR(F3/12,1)))} -> 0.9971605 | G4: {=INDEX('Life Table'!$L$3:$BF$71,1,1+FLOOR(G3/12,1))*(1-(G3/12-FLOOR(G3/12,1))*INDEX('Life Table'!$D$3:$D$71,1+FLOOR(G3/12,1)))} -> 0.996214 | H4: {=INDEX('Life Table'!$L$3:$BF$71,1,1+FLOOR(H3/12,1))*(1-(H3/12-FLOOR(H3/12,1))*INDEX('Life Table'!$D$3:$D$71,1+FLOOR(H3/12,1)))} -> 0.9952675 | I4: {=INDEX('Life Table'!$L$3:$BF$71,1,1+FLOOR(I3/12,1))*(1-(I3/12-FLOOR(I3/12,1))*INDEX('Life Table'!$D$3:$D$71,1+FLOOR(I3/12,1)))} -> 0.994321 | J4: {=INDEX('Life Table'!$L$3:$BF$71,1,1+FLOOR(J3/12,1))*(1-(J3/12-FLOOR(J3/12,1))*INDEX('Life Table'!$D$3:$D$71,1+FLOOR(J3/12,1)))} -> 0.9933745 | ... DS4: {=INDEX('Life Table'!$L$3:$BF$71,1,1+FLOOR(DS3/12,1))*(1-(DS3/12-FLOOR(DS3/12,1))*INDEX('Life Table'!$D$3:$D$71,1+FLOOR(DS3/12,1)))} -> 0.83444024
B5: k/12_E_65 | C5: =C4/(1+$L$2/12)^C3 -> 1 | D5: =D4/(1+$L$2/12)^D3 -> 0.99659563 | E5: =E4/(1+$L$2/12)^E3 -> 0.99320195 | F5: =F4/(1+$L$2/12)^F3 -> 0.98981894 | G5: =G4/(1+$L$2/12)^G3 -> 0.98644657 | H5: =H4/(1+$L$2/12)^H3 -> 0.98308479 | I5: =I4/(1+$L$2/12)^I3 -> 0.97973359 | J5: =J4/(1+$L$2/12)^J3 -> 0.97639293 | ... DS5: =DS4/(1+$L$2/12)^DS3 -> 0.6209019
B6: Received Age | C6: 65 | D6: =$C$6+D3/12 -> 65.083333 | E6: =$C$6+E3/12 -> 65.166667 | F6: =$C$6+F3/12 -> 65.25 | G6: =$C$6+G3/12 -> 65.333333 | H6: =$C$6+H3/12 -> 65.416667 | I6: =$C$6+I3/12 -> 65.5 | J6: =$C$6+J3/12 -> 65.583333 | K6: =$C$6+K3/12 -> 65.666667 | ... DS6: =$C$6+DS3/12 -> 75
A7: u | B7: Deferred Age | DT7: PV
A8: 0 | B8: =65 -> 65 | C8: =$F$2*IF(C$6<$B8,0,1)*(1+0.072*MAX(MIN($B8,70)-$B$2,0))*IF(C$6>=75,1.1,1)*IF($B8<75,IF($C$2<=$G$2,1,0),IF($C$2<=$H$2,1,0))*IF(OR(C$6<$B$2,$B8<$B$2),0,1) -> 272.87625 | D8: =$F$2*IF(D$6<$B8,0,1)*(1+0.072*MAX(MIN($B8,70)-$B$2,0))*IF(D$6>=75,1.1,1)*IF($B8<75,IF($C$2<=$G$2,1,0),IF($C$2<=$H$2,1,0))*IF(OR(D$6<$B$2,$B8<$B$2),0,1) -> 272.87625 | E8: =$F$2*IF(E$6<$B8,0,1)*(1+0.072*MAX(MIN($B8,70)-$B$2,0))*IF(E$6>=75,1.1,1)*IF($B8<75,IF($C$2<=$G$2,1,0),IF($C$2<=$H$2,1,0))*IF(OR(E$6<$B$2,$B8<$B$2),0,1) -> 272.87625 | F8: =$F$2*IF(F$6<$B8,0,1)*(1+0.072*MAX(MIN($B8,70)-$B$2,0))*IF(F$6>=75,1.1,1)*IF($B8<75,IF($C$2<=$G$2,1,0),IF($C$2<=$H$2,1,0))*IF(OR(F$6<$B$2,$B8<$B$2),0,1) -> 272.87625 | G8: =$F$2*IF(G$6<$B8,0,1)*(1+0.072*MAX(MIN($B8,70)-$B$2,0))*IF(G$6>=75,1.1,1)*IF($B8<75,IF($C$2<=$G$2,1,0),IF($C$2<=$H$2,1,0))*IF(OR(G$6<$B$2,$B8<$B$2),0,1) -> 272.87625 | H8: =$F$2*IF(H$6<$B8,0,1)*(1+0.072*MAX(MIN($B8,70)-$B$2,0))*IF(H$6>=75,1.1,1)*IF($B8<75,IF($C$2<=$G$2,1,0),IF($C$2<=$H$2,1,0))*IF(OR(H$6<$B$2,$B8<$B$2),0,1) -> 272.87625 | I8: =$F$2*IF(I$6<$B8,0,1)*(1+0.072*MAX(MIN($B8,70)-$B$2,0))*IF(I$6>=75,1.1,1)*IF($B8<75,IF($C$2<=$G$2,1,0),IF($C$2<=$H$2,1,0))*IF(OR(I$6<$B$2,$B8<$B$2),0,1) -> 272.87625 | J8: =$F$2*IF(J$6<$B8,0,1)*(1+0.072*MAX(MIN($B8,70)-$B$2,0))*IF(J$6>=75,1.1,1)*IF($B8<75,IF($C$2<=$G$2,1,0),IF($C$2<=$H$2,1,0))*IF(OR(J$6<$B$2,$B8<$B$2),0,1) -> 272.87625 | ... DS8: =$F$2*IF(DS$6<$B8,0,1)*(1+0.072*MAX(MIN($B8,70)-$B$2,0))*IF(DS$6>=75,1.1,1)*IF($B8<75,IF($C$2<=$G$2,1,0),IF($C$2<=$H$2,1,0))*IF(OR(DS$6<$B$2,$B8<$B$2),0,1) -> 300.16388 | DT8: =SUMPRODUCT($C$5:$DR$5,C8:DR8)+DS8*12*$DR$2 -> 61623.917
A9: 1 | B9: =$B$8+A9/12 -> 65.083333 | C9: =$F$2*IF(C$6<$B9,0,1)*(1+0.072*MAX(MIN($B9,70)-$B$2,0))*IF(C$6>=75,1.1,1)*IF($B9<75,IF($C$2<=$G$2,1,0),IF($C$2<=$H$2,1,0))*IF(OR(C$6<$B$2,$B9<$B$2),0,1) -> 0 | D9: =$F$2*IF(D$6<$B9,0,1)*(1+0.072*MAX(MIN($B9,70)-$B$2,0))*IF(D$6>=75,1.1,1)*IF($B9<75,IF($C$2<=$G$2,1,0),IF($C$2<=$H$2,1,0))*IF(OR(D$6<$B$2,$B9<$B$2),0,1) -> 274.51351 | E9: =$F$2*IF(E$6<$B9,0,1)*(1+0.072*MAX(MIN($B9,70)-$B$2,0))*IF(E$6>=75,1.1,1)*IF($B9<75,IF($C$2<=$G$2,1,0),IF($C$2<=$H$2,1,0))*IF(OR(E$6<$B$2,$B9<$B$2),0,1) -> 274.51351 | F9: =$F$2*IF(F$6<$B9,0,1)*(1+0.072*MAX(MIN($B9,70)-$B$2,0))*IF(F$6>=75,1.1,1)*IF($B9<75,IF($C$2<=$G$2,1,0),IF($C$2<=$H$2,1,0))*IF(OR(F$6<$B$2,$B9<$B$2),0,1) -> 274.51351 | G9: =$F$2*IF(G$6<$B9,0,1)*(1+0.072*MAX(MIN($B9,70)-$B$2,0))*IF(G$6>=75,1.1,1)*IF($B9<75,IF($C$2<=$G$2,1,0),IF($C$2<=$H$2,1,0))*IF(OR(G$6<$B$2,$B9<$B$2),0,1) -> 274.51351 | H9: =$F$2*IF(H$6<$B9,0,1)*(1+0.072*MAX(MIN($B9,70)-$B$2,0))*IF(H$6>=75,1.1,1)*IF($B9<75,IF($C$2<=$G$2,1,0),IF($C$2<=$H$2,1,0))*IF(OR(H$6<$B$2,$B9<$B$2),0,1) -> 274.51351 | I9: =$F$2*IF(I$6<$B9,0,1)*(1+0.072*MAX(MIN($B9,70)-$B$2,0))*IF(I$6>=75,1.1,1)*IF($B9<75,IF($C$2<=$G$2,1,0),IF($C$2<=$H$2,1,0))*IF(OR(I$6<$B$2,$B9<$B$2),0,1) -> 274.51351 | J9: =$F$2*IF(J$6<$B9,0,1)*(1+0.072*MAX(MIN($B9,70)-$B$2,0))*IF(J$6>=75,1.1,1)*IF($B9<75,IF($C$2<=$G$2,1,0),IF($C$2<=$H$2,1,0))*IF(OR(J$6<$B$2,$B9<$B$2),0,1) -> 274.51351 | ... DS9: =$F$2*IF(DS$6<$B9,0,1)*(1+0.072*MAX(MIN($B9,70)-$B$2,0))*IF(DS$6>=75,1.1,1)*IF($B9<75,IF($C$2<=$G$2,1,0),IF($C$2<=$H$2,1,0))*IF(OR(DS$6<$B$2,$B9<$B$2),0,1) -> 301.96486 | DT9: =SUMPRODUCT($C$5:$DR$5,C9:DR9)+DS9*12*$DR$2 -> 61719.147
A10: 2 | B10: =$B$8+A10/12 -> 65.166667 | C10: =$F$2*IF(C$6<$B10,0,1)*(1+0.072*MAX(MIN($B10,70)-$B$2,0))*IF(C$6>=75,1.1,1)*IF($B10<75,IF($C$2<=$G$2,1,0),IF($C$2<=$H$2,1,0))*IF(OR(C$6<$B$2,$B10<$B$2),0,1) -> 0 | D10: =$F$2*IF(D$6<$B10,0,1)*(1+0.072*MAX(MIN($B10,70)-$B$2,0))*IF(D$6>=75,1.1,1)*IF($B10<75,IF($C$2<=$G$2,1,0),IF($C$2<=$H$2,1,0))*IF(OR(D$6<$B$2,$B10<$B$2),0,1) -> 0 | E10: =$F$2*IF(E$6<$B10,0,1)*(1+0.072*MAX(MIN($B10,70)-$B$2,0))*IF(E$6>=75,1.1,1)*IF($B10<75,IF($C$2<=$G$2,1,0),IF($C$2<=$H$2,1,0))*IF(OR(E$6<$B$2,$B10<$B$2),0,1) -> 276.15077 | F10: =$F$2*IF(F$6<$B10,0,1)*(1+0.072*MAX(MIN($B10,70)-$B$2,0))*IF(F$6>=75,1.1,1)*IF($B10<75,IF($C$2<=$G$2,1,0),IF($C$2<=$H$2,1,0))*IF(OR(F$6<$B$2,$B10<$B$2),0,1) -> 276.15077 | G10: =$F$2*IF(G$6<$B10,0,1)*(1+0.072*MAX(MIN($B10,70)-$B$2,0))*IF(G$6>=75,1.1,1)*IF($B10<75,IF($C$2<=$G$2,1,0),IF($C$2<=$H$2,1,0))*IF(OR(G$6<$B$2,$B10<$B$2),0,1) -> 276.15077 | H10: =$F$2*IF(H$6<$B10,0,1)*(1+0.072*MAX(MIN($B10,70)-$B$2,0))*IF(H$6>=75,1.1,1)*IF($B10<75,IF($C$2<=$G$2,1,0),IF($C$2<=$H$2,1,0))*IF(OR(H$6<$B$2,$B10<$B$2),0,1) -> 276.15077 | I10: =$F$2*IF(I$6<$B10,0,1)*(1+0.072*MAX(MIN($B10,70)-$B$2,0))*IF(I$6>=75,1.1,1)*IF($B10<75,IF($C$2<=$G$2,1,0),IF($C$2<=$H$2,1,0))*IF(OR(I$6<$B$2,$B10<$B$2),0,1) -> 276.15077 | J10: =$F$2*IF(J$6<$B10,0,1)*(1+0.072*MAX(MIN($B10,70)-$B$2,0))*IF(J$6>=75,1.1,1)*IF($B10<75,IF($C$2<=$G$2,1,0),IF($C$2<=$H$2,1,0))*IF(OR(J$6<$B$2,$B10<$B$2),0,1) -> 276.15077 | ... DS10: =$F$2*IF(DS$6<$B10,0,1)*(1+0.072*MAX(MIN($B10,70)-$B$2,0))*IF(DS$6>=75,1.1,1)*IF($B10<75,IF($C$2<=$G$2,1,0),IF($C$2<=$H$2,1,0))*IF(OR(DS$6<$B$2,$B10<$B$2),0,1) -> 303.76584 | DT10: =SUMPRODUCT($C$5:$DR$5,C10:DR10)+DS10*12*$DR$2 -> 61812.043
A11: 3 | B11: =$B$8+A11/12 -> 65.25 | C11: =$F$2*IF(C$6<$B11,0,1)*(1+0.072*MAX(MIN($B11,70)-$B$2,0))*IF(C$6>=75,1.1,1)*IF($B11<75,IF($C$2<=$G$2,1,0),IF($C$2<=$H$2,1,0))*IF(OR(C$6<$B$2,$B11<$B$2),0,1) -> 0 | D11: =$F$2*IF(D$6<$B11,0,1)*(1+0.072*MAX(MIN($B11,70)-$B$2,0))*IF(D$6>=75,1.1,1)*IF($B11<75,IF($C$2<=$G$2,1,0),IF($C$2<=$H$2,1,0))*IF(OR(D$6<$B$2,$B11<$B$2),0,1) -> 0 | E11: =$F$2*IF(E$6<$B11,0,1)*(1+0.072*MAX(MIN($B11,70)-$B$2,0))*IF(E$6>=75,1.1,1)*IF($B11<75,IF($C$2<=$G$2,1,0),IF($C$2<=$H$2,1,0))*IF(OR(E$6<$B$2,$B11<$B$2),0,1) -> 0 | F11: =$F$2*IF(F$6<$B11,0,1)*(1+0.072*MAX(MIN($B11,70)-$B$2,0))*IF(F$6>=75,1.1,1)*IF($B11<75,IF($C$2<=$G$2,1,0),IF($C$2<=$H$2,1,0))*IF(OR(F$6<$B$2,$B11<$B$2),0,1) -> 277.78802 | G11: =$F$2*IF(G$6<$B11,0,1)*(1+0.072*MAX(MIN($B11,70)-$B$2,0))*IF(G$6>=75,1.1,1)*IF($B11<75,IF($C$2<=$G$2,1,0),IF($C$2<=$H$2,1,0))*IF(OR(G$6<$B$2,$B11<$B$2),0,1) -> 277.78802 | H11: =$F$2*IF(H$6<$B11,0,1)*(1+0.072*MAX(MIN($B11,70)-$B$2,0))*IF(H$6>=75,1.1,1)*IF($B11<75,IF($C$2<=$G$2,1,0),IF($C$2<=$H$2,1,0))*IF(OR(H$6<$B$2,$B11<$B$2),0,1) -> 277.78802 | I11: =$F$2*IF(I$6<$B11,0,1)*(1+0.072*MAX(MIN($B11,70)-$B$2,0))*IF(I$6>=75,1.1,1)*IF($B11<75,IF($C$2<=$G$2,1,0),IF($C$2<=$H$2,1,0))*IF(OR(I$6<$B$2,$B11<$B$2),0,1) -> 277.78802 | J11: =$F$2*IF(J$6<$B11,0,1)*(1+0.072*MAX(MIN($B11,70)-$B$2,0))*IF(J$6>=75,1.1,1)*IF($B11<75,IF($C$2<=$G$2,1,0),IF($C$2<=$H$2,1,0))*IF(OR(J$6<$B$2,$B11<$B$2),0,1) -> 277.78802 | ... DS11: =$F$2*IF(DS$6<$B11,0,1)*(1+0.072*MAX(MIN($B11,70)-$B$2,0))*IF(DS$6>=75,1.1,1)*IF($B11<75,IF($C$2<=$G$2,1,0),IF($C$2<=$H$2,1,0))*IF(OR(DS$6<$B$2,$B11<$B$2),0,1) -> 305.56682 | DT11: =SUMPRODUCT($C$5:$DR$5,C11:DR11)+DS11*12*$DR$2 -> 61902.617
A12: 4 | B12: =$B$8+A12/12 -> 65.333333 | C12: =$F$2*IF(C$6<$B12,0,1)*(1+0.072*MAX(MIN($B12,70)-$B$2,0))*IF(C$6>=75,1.1,1)*IF($B12<75,IF($C$2<=$G$2,1,0),IF($C$2<=$H$2,1,0))*IF(OR(C$6<$B$2,$B12<$B$2),0,1) -> 0 | D12: =$F$2*IF(D$6<$B12,0,1)*(1+0.072*MAX(MIN($B12,70)-$B$2,0))*IF(D$6>=75,1.1,1)*IF($B12<75,IF($C$2<=$G$2,1,0),IF($C$2<=$H$2,1,0))*IF(OR(D$6<$B$2,$B12<$B$2),0,1) -> 0 | E12: =$F$2*IF(E$6<$B12,0,1)*(1+0.072*MAX(MIN($B12,70)-$B$2,0))*IF(E$6>=75,1.1,1)*IF($B12<75,IF($C$2<=$G$2,1,0),IF($C$2<=$H$2,1,0))*IF(OR(E$6<$B$2,$B12<$B$2),0,1) -> 0 | F12: =$F$2*IF(F$6<$B12,0,1)*(1+0.072*MAX(MIN($B12,70)-$B$2,0))*IF(F$6>=75,1.1,1)*IF($B12<75,IF($C$2<=$G$2,1,0),IF($C$2<=$H$2,1,0))*IF(OR(F$6<$B$2,$B12<$B$2),0,1) -> 0 | G12: =$F$2*IF(G$6<$B12,0,1)*(1+0.072*MAX(MIN($B12,70)-$B$2,0))*IF(G$6>=75,1.1,1)*IF($B12<75,IF($C$2<=$G$2,1,0),IF($C$2<=$H$2,1,0))*IF(OR(G$6<$B$2,$B12<$B$2),0,1) -> 279.42528 | H12: =$F$2*IF(H$6<$B12,0,1)*(1+0.072*MAX(MIN($B12,70)-$B$2,0))*IF(H$6>=75,1.1,1)*IF($B12<75,IF($C$2<=$G$2,1,0),IF($C$2<=$H$2,1,0))*IF(OR(H$6<$B$2,$B12<$B$2),0,1) -> 279.42528 | I12: =$F$2*IF(I$6<$B12,0,1)*(1+0.072*MAX(MIN($B12,70)-$B$2,0))*IF(I$6>=75,1.1,1)*IF($B12<75,IF($C$2<=$G$2,1,0),IF($C$2<=$H$2,1,0))*IF(OR(I$6<$B$2,$B12<$B$2),0,1) -> 279.42528 | J12: =$F$2*IF(J$6<$B12,0,1)*(1+0.072*MAX(MIN($B12,70)-$B$2,0))*IF(J$6>=75,1.1,1)*IF($B12<75,IF($C$2<=$G$2,1,0),IF($C$2<=$H$2,1,0))*IF(OR(J$6<$B$2,$B12<$B$2),0,1) -> 279.42528 | ... DS12: =$F$2*IF(DS$6<$B12,0,1)*(1+0.072*MAX(MIN($B12,70)-$B$2,0))*IF(DS$6>=75,1.1,1)*IF($B12<75,IF($C$2<=$G$2,1,0),IF($C$2<=$H$2,1,0))*IF(OR(DS$6<$B$2,$B12<$B$2),0,1) -> 307.36781 | DT12: =SUMPRODUCT($C$5:$DR$5,C12:DR12)+DS12*12*$DR$2 -> 61990.885
A13: 5 | B13: =$B$8+A13/12 -> 65.416667 | C13: =$F$2*IF(C$6<$B13,0,1)*(1+0.072*MAX(MIN($B13,70)-$B$2,0))*IF(C$6>=75,1.1,1)*IF($B13<75,IF($C$2<=$G$2,1,0),IF($C$2<=$H$2,1,0))*IF(OR(C$6<$B$2,$B13<$B$2),0,1) -> 0 | D13: =$F$2*IF(D$6<$B13,0,1)*(1+0.072*MAX(MIN($B13,70)-$B$2,0))*IF(D$6>=75,1.1,1)*IF($B13<75,IF($C$2<=$G$2,1,0),IF($C$2<=$H$2,1,0))*IF(OR(D$6<$B$2,$B13<$B$2),0,1) -> 0 | E13: =$F$2*IF(E$6<$B13,0,1)*(1+0.072*MAX(MIN($B13,70)-$B$2,0))*IF(E$6>=75,1.1,1)*IF($B13<75,IF($C$2<=$G$2,1,0),IF($C$2<=$H$2,1,0))*IF(OR(E$6<$B$2,$B13<$B$2),0,1) -> 0 | F13: =$F$2*IF(F$6<$B13,0,1)*(1+0.072*MAX(MIN($B13,70)-$B$2,0))*IF(F$6>=75,1.1,1)*IF($B13<75,IF($C$2<=$G$2,1,0),IF($C$2<=$H$2,1,0))*IF(OR(F$6<$B$2,$B13<$B$2),0,1) -> 0 | G13: =$F$2*IF(G$6<$B13,0,1)*(1+0.072*MAX(MIN($B13,70)-$B$2,0))*IF(G$6>=75,1.1,1)*IF($B13<75,IF($C$2<=$G$2,1,0),IF($C$2<=$H$2,1,0))*IF(OR(G$6<$B$2,$B13<$B$2),0,1) -> 0 | H13: =$F$2*IF(H$6<$B13,0,1)*(1+0.072*MAX(MIN($B13,70)-$B$2,0))*IF(H$6>=75,1.1,1)*IF($B13<75,IF($C$2<=$G$2,1,0),IF($C$2<=$H$2,1,0))*IF(OR(H$6<$B$2,$B13<$B$2),0,1) -> 281.06254 | I13: =$F$2*IF(I$6<$B13,0,1)*(1+0.072*MAX(MIN($B13,70)-$B$2,0))*IF(I$6>=75,1.1,1)*IF($B13<75,IF($C$2<=$G$2,1,0),IF($C$2<=$H$2,1,0))*IF(OR(I$6<$B$2,$B13<$B$2),0,1) -> 281.06254 | J13: =$F$2*IF(J$6<$B13,0,1)*(1+0.072*MAX(MIN($B13,70)-$B$2,0))*IF(J$6>=75,1.1,1)*IF($B13<75,IF($C$2<=$G$2,1,0),IF($C$2<=$H$2,1,0))*IF(OR(J$6<$B$2,$B13<$B$2),0,1) -> 281.06254 | ... DS13: =$F$2*IF(DS$6<$B13,0,1)*(1+0.072*MAX(MIN($B13,70)-$B$2,0))*IF(DS$6>=75,1.1,1)*IF($B13<75,IF($C$2<=$G$2,1,0),IF($C$2<=$H$2,1,0))*IF(OR(DS$6<$B$2,$B13<$B$2),0,1) -> 309.16879 | DT13: =SUMPRODUCT($C$5:$DR$5,C13:DR13)+DS13*12*$DR$2 -> 62076.86
A14: 6 | B14: =$B$8+A14/12 -> 65.5 | C14: =$F$2*IF(C$6<$B14,0,1)*(1+0.072*MAX(MIN($B14,70)-$B$2,0))*IF(C$6>=75,1.1,1)*IF($B14<75,IF($C$2<=$G$2,1,0),IF($C$2<=$H$2,1,0))*IF(OR(C$6<$B$2,$B14<$B$2),0,1) -> 0 | D14: =$F$2*IF(D$6<$B14,0,1)*(1+0.072*MAX(MIN($B14,70)-$B$2,0))*IF(D$6>=75,1.1,1)*IF($B14<75,IF($C$2<=$G$2,1,0),IF($C$2<=$H$2,1,0))*IF(OR(D$6<$B$2,$B14<$B$2),0,1) -> 0 | E14: =$F$2*IF(E$6<$B14,0,1)*(1+0.072*MAX(MIN($B14,70)-$B$2,0))*IF(E$6>=75,1.1,1)*IF($B14<75,IF($C$2<=$G$2,1,0),IF($C$2<=$H$2,1,0))*IF(OR(E$6<$B$2,$B14<$B$2),0,1) -> 0 | F14: =$F$2*IF(F$6<$B14,0,1)*(1+0.072*MAX(MIN($B14,70)-$B$2,0))*IF(F$6>=75,1.1,1)*IF($B14<75,IF($C$2<=$G$2,1,0),IF($C$2<=$H$2,1,0))*IF(OR(F$6<$B$2,$B14<$B$2),0,1) -> 0 | G14: =$F$2*IF(G$6<$B14,0,1)*(1+0.072*MAX(MIN($B14,70)-$B$2,0))*IF(G$6>=75,1.1,1)*IF($B14<75,IF($C$2<=$G$2,1,0),IF($C$2<=$H$2,1,0))*IF(OR(G$6<$B$2,$B14<$B$2),0,1) -> 0 | H14: =$F$2*IF(H$6<$B14,0,1)*(1+0.072*MAX(MIN($B14,70)-$B$2,0))*IF(H$6>=75,1.1,1)*IF($B14<75,IF($C$2<=$G$2,1,0),IF($C$2<=$H$2,1,0))*IF(OR(H$6<$B$2,$B14<$B$2),0,1) -> 0 | I14: =$F$2*IF(I$6<$B14,0,1)*(1+0.072*MAX(MIN($B14,70)-$B$2,0))*IF(I$6>=75,1.1,1)*IF($B14<75,IF($C$2<=$G$2,1,0),IF($C$2<=$H$2,1,0))*IF(OR(I$6<$B$2,$B14<$B$2),0,1) -> 282.69979 | J14: =$F$2*IF(J$6<$B14,0,1)*(1+0.072*MAX(MIN($B14,70)-$B$2,0))*IF(J$6>=75,1.1,1)*IF($B14<75,IF($C$2<=$G$2,1,0),IF($C$2<=$H$2,1,0))*IF(OR(J$6<$B$2,$B14<$B$2),0,1) -> 282.69979 | ... DS14: =$F$2*IF(DS$6<$B14,0,1)*(1+0.072*MAX(MIN($B14,70)-$B$2,0))*IF(DS$6>=75,1.1,1)*IF($B14<75,IF($C$2<=$G$2,1,0),IF($C$2<=$H$2,1,0))*IF(OR(DS$6<$B$2,$B14<$B$2),0,1) -> 310.96977 | DT14: =SUMPRODUCT($C$5:$DR$5,C14:DR14)+DS14*12*$DR$2 -> 62160.555
A15: 7 | B15: =$B$8+A15/12 -> 65.583333 | C15: =$F$2*IF(C$6<$B15,0,1)*(1+0.072*MAX(MIN($B15,70)-$B$2,0))*IF(C$6>=75,1.1,1)*IF($B15<75,IF($C$2<=$G$2,1,0),IF($C$2<=$H$2,1,0))*IF(OR(C$6<$B$2,$B15<$B$2),0,1) -> 0 | D15: =$F$2*IF(D$6<$B15,0,1)*(1+0.072*MAX(MIN($B15,70)-$B$2,0))*IF(D$6>=75,1.1,1)*IF($B15<75,IF($C$2<=$G$2,1,0),IF($C$2<=$H$2,1,0))*IF(OR(D$6<$B$2,$B15<$B$2),0,1) -> 0 | E15: =$F$2*IF(E$6<$B15,0,1)*(1+0.072*MAX(MIN($B15,70)-$B$2,0))*IF(E$6>=75,1.1,1)*IF($B15<75,IF($C$2<=$G$2,1,0),IF($C$2<=$H$2,1,0))*IF(OR(E$6<$B$2,$B15<$B$2),0,1) -> 0 | F15: =$F$2*IF(F$6<$B15,0,1)*(1+0.072*MAX(MIN($B15,70)-$B$2,0))*IF(F$6>=75,1.1,1)*IF($B15<75,IF($C$2<=$G$2,1,0),IF($C$2<=$H$2,1,0))*IF(OR(F$6<$B$2,$B15<$B$2),0,1) -> 0 | G15: =$F$2*IF(G$6<$B15,0,1)*(1+0.072*MAX(MIN($B15,70)-$B$2,0))*IF(G$6>=75,1.1,1)*IF($B15<75,IF($C$2<=$G$2,1,0),IF($C$2<=$H$2,1,0))*IF(OR(G$6<$B$2,$B15<$B$2),0,1) -> 0 | H15: =$F$2*IF(H$6<$B15,0,1)*(1+0.072*MAX(MIN($B15,70)-$B$2,0))*IF(H$6>=75,1.1,1)*IF($B15<75,IF($C$2<=$G$2,1,0),IF($C$2<=$H$2,1,0))*IF(OR(H$6<$B$2,$B15<$B$2),0,1) -> 0 | I15: =$F$2*IF(I$6<$B15,0,1)*(1+0.072*MAX(MIN($B15,70)-$B$2,0))*IF(I$6>=75,1.1,1)*IF($B15<75,IF($C$2<=$G$2,1,0),IF($C$2<=$H$2,1,0))*IF(OR(I$6<$B$2,$B15<$B$2),0,1) -> 0 | J15: =$F$2*IF(J$6<$B15,0,1)*(1+0.072*MAX(MIN($B15,70)-$B$2,0))*IF(J$6>=75,1.1,1)*IF($B15<75,IF($C$2<=$G$2,1,0),IF($C$2<=$H$2,1,0))*IF(OR(J$6<$B$2,$B15<$B$2),0,1) -> 284.33705 | ... DS15: =$F$2*IF(DS$6<$B15,0,1)*(1+0.072*MAX(MIN($B15,70)-$B$2,0))*IF(DS$6>=75,1.1,1)*IF($B15<75,IF($C$2<=$G$2,1,0),IF($C$2<=$H$2,1,0))*IF(OR(DS$6<$B$2,$B15<$B$2),0,1) -> 312.77076 | DT15: =SUMPRODUCT($C$5:$DR$5,C15:DR15)+DS15*12*$DR$2 -> 62241.984
A16: 8 | B16: =$B$8+A16/12 -> 65.666667 | C16: =$F$2*IF(C$6<$B16,0,1)*(1+0.072*MAX(MIN($B16,70)-$B$2,0))*IF(C$6>=75,1.1,1)*IF($B16<75,IF($C$2<=$G$2,1,0),IF($C$2<=$H$2,1,0))*IF(OR(C$6<$B$2,$B16<$B$2),0,1) -> 0 | D16: =$F$2*IF(D$6<$B16,0,1)*(1+0.072*MAX(MIN($B16,70)-$B$2,0))*IF(D$6>=75,1.1,1)*IF($B16<75,IF($C$2<=$G$2,1,0),IF($C$2<=$H$2,1,0))*IF(OR(D$6<$B$2,$B16<$B$2),0,1) -> 0 | E16: =$F$2*IF(E$6<$B16,0,1)*(1+0.072*MAX(MIN($B16,70)-$B$2,0))*IF(E$6>=75,1.1,1)*IF($B16<75,IF($C$2<=$G$2,1,0),IF($C$2<=$H$2,1,0))*IF(OR(E$6<$B$2,$B16<$B$2),0,1) -> 0 | F16: =$F$2*IF(F$6<$B16,0,1)*(1+0.072*MAX(MIN($B16,70)-$B$2,0))*IF(F$6>=75,1.1,1)*IF($B16<75,IF($C$2<=$G$2,1,0),IF($C$2<=$H$2,1,0))*IF(OR(F$6<$B$2,$B16<$B$2),0,1) -> 0 | G16: =$F$2*IF(G$6<$B16,0,1)*(1+0.072*MAX(MIN($B16,70)-$B$2,0))*IF(G$6>=75,1.1,1)*IF($B16<75,IF($C$2<=$G$2,1,0),IF($C$2<=$H$2,1,0))*IF(OR(G$6<$B$2,$B16<$B$2),0,1) -> 0 | H16: =$F$2*IF(H$6<$B16,0,1)*(1+0.072*MAX(MIN($B16,70)-$B$2,0))*IF(H$6>=75,1.1,1)*IF($B16<75,IF($C$2<=$G$2,1,0),IF($C$2<=$H$2,1,0))*IF(OR(H$6<$B$2,$B16<$B$2),0,1) -> 0 | I16: =$F$2*IF(I$6<$B16,0,1)*(1+0.072*MAX(MIN($B16,70)-$B$2,0))*IF(I$6>=75,1.1,1)*IF($B16<75,IF($C$2<=$G$2,1,0),IF($C$2<=$H$2,1,0))*IF(OR(I$6<$B$2,$B16<$B$2),0,1) -> 0 | J16: =$F$2*IF(J$6<$B16,0,1)*(1+0.072*MAX(MIN($B16,70)-$B$2,0))*IF(J$6>=75,1.1,1)*IF($B16<75,IF($C$2<=$G$2,1,0),IF($C$2<=$H$2,1,0))*IF(OR(J$6<$B$2,$B16<$B$2),0,1) -> 0 | ... DS16: =$F$2*IF(DS$6<$B16,0,1)*(1+0.072*MAX(MIN($B16,70)-$B$2,0))*IF(DS$6>=75,1.1,1)*IF($B16<75,IF($C$2<=$G$2,1,0),IF($C$2<=$H$2,1,0))*IF(OR(DS$6<$B$2,$B16<$B$2),0,1) -> 314.57174 | DT16: =SUMPRODUCT($C$5:$DR$5,C16:DR16)+DS16*12*$DR$2 -> 62321.16
A17: 9 | B17: =$B$8+A17/12 -> 65.75 | C17: =$F$2*IF(C$6<$B17,0,1)*(1+0.072*MAX(MIN($B17,70)-$B$2,0))*IF(C$6>=75,1.1,1)*IF($B17<75,IF($C$2<=$G$2,1,0),IF($C$2<=$H$2,1,0))*IF(OR(C$6<$B$2,$B17<$B$2),0,1) -> 0 | D17: =$F$2*IF(D$6<$B17,0,1)*(1+0.072*MAX(MIN($B17,70)-$B$2,0))*IF(D$6>=75,1.1,1)*IF($B17<75,IF($C$2<=$G$2,1,0),IF($C$2<=$H$2,1,0))*IF(OR(D$6<$B$2,$B17<$B$2),0,1) -> 0 | E17: =$F$2*IF(E$6<$B17,0,1)*(1+0.072*MAX(MIN($B17,70)-$B$2,0))*IF(E$6>=75,1.1,1)*IF($B17<75,IF($C$2<=$G$2,1,0),IF($C$2<=$H$2,1,0))*IF(OR(E$6<$B$2,$B17<$B$2),0,1) -> 0 | F17: =$F$2*IF(F$6<$B17,0,1)*(1+0.072*MAX(MIN($B17,70)-$B$2,0))*IF(F$6>=75,1.1,1)*IF($B17<75,IF($C$2<=$G$2,1,0),IF($C$2<=$H$2,1,0))*IF(OR(F$6<$B$2,$B17<$B$2),0,1) -> 0 | G17: =$F$2*IF(G$6<$B17,0,1)*(1+0.072*MAX(MIN($B17,70)-$B$2,0))*IF(G$6>=75,1.1,1)*IF($B17<75,IF($C$2<=$G$2,1,0),IF($C$2<=$H$2,1,0))*IF(OR(G$6<$B$2,$B17<$B$2),0,1) -> 0 | H17: =$F$2*IF(H$6<$B17,0,1)*(1+0.072*MAX(MIN($B17,70)-$B$2,0))*IF(H$6>=75,1.1,1)*IF($B17<75,IF($C$2<=$G$2,1,0),IF($C$2<=$H$2,1,0))*IF(OR(H$6<$B$2,$B17<$B$2),0,1) -> 0 | I17: =$F$2*IF(I$6<$B17,0,1)*(1+0.072*MAX(MIN($B17,70)-$B$2,0))*IF(I$6>=75,1.1,1)*IF($B17<75,IF($C$2<=$G$2,1,0),IF($C$2<=$H$2,1,0))*IF(OR(I$6<$B$2,$B17<$B$2),0,1) -> 0 | J17: =$F$2*IF(J$6<$B17,0,1)*(1+0.072*MAX(MIN($B17,70)-$B$2,0))*IF(J$6>=75,1.1,1)*IF($B17<75,IF($C$2<=$G$2,1,0),IF($C$2<=$H$2,1,0))*IF(OR(J$6<$B$2,$B17<$B$2),0,1) -> 0 | ... DS17: =$F$2*IF(DS$6<$B17,0,1)*(1+0.072*MAX(MIN($B17,70)-$B$2,0))*IF(DS$6>=75,1.1,1)*IF($B17<75,IF($C$2<=$G$2,1,0),IF($C$2<=$H$2,1,0))*IF(OR(DS$6<$B$2,$B17<$B$2),0,1) -> 316.37272 | DT17: =SUMPRODUCT($C$5:$DR$5,C17:DR17)+DS17*12*$DR$2 -> 62398.096
A18: 10 | B18: =$B$8+A18/12 -> 65.833333 | C18: =$F$2*IF(C$6<$B18,0,1)*(1+0.072*MAX(MIN($B18,70)-$B$2,0))*IF(C$6>=75,1.1,1)*IF($B18<75,IF($C$2<=$G$2,1,0),IF($C$2<=$H$2,1,0))*IF(OR(C$6<$B$2,$B18<$B$2),0,1) -> 0 | D18: =$F$2*IF(D$6<$B18,0,1)*(1+0.072*MAX(MIN($B18,70)-$B$2,0))*IF(D$6>=75,1.1,1)*IF($B18<75,IF($C$2<=$G$2,1,0),IF($C$2<=$H$2,1,0))*IF(OR(D$6<$B$2,$B18<$B$2),0,1) -> 0 | E18: =$F$2*IF(E$6<$B18,0,1)*(1+0.072*MAX(MIN($B18,70)-$B$2,0))*IF(E$6>=75,1.1,1)*IF($B18<75,IF($C$2<=$G$2,1,0),IF($C$2<=$H$2,1,0))*IF(OR(E$6<$B$2,$B18<$B$2),0,1) -> 0 | F18: =$F$2*IF(F$6<$B18,0,1)*(1+0.072*MAX(MIN($B18,70)-$B$2,0))*IF(F$6>=75,1.1,1)*IF($B18<75,IF($C$2<=$G$2,1,0),IF($C$2<=$H$2,1,0))*IF(OR(F$6<$B$2,$B18<$B$2),0,1) -> 0 | G18: =$F$2*IF(G$6<$B18,0,1)*(1+0.072*MAX(MIN($B18,70)-$B$2,0))*IF(G$6>=75,1.1,1)*IF($B18<75,IF($C$2<=$G$2,1,0),IF($C$2<=$H$2,1,0))*IF(OR(G$6<$B$2,$B18<$B$2),0,1) -> 0 | H18: =$F$2*IF(H$6<$B18,0,1)*(1+0.072*MAX(MIN($B18,70)-$B$2,0))*IF(H$6>=75,1.1,1)*IF($B18<75,IF($C$2<=$G$2,1,0),IF($C$2<=$H$2,1,0))*IF(OR(H$6<$B$2,$B18<$B$2),0,1) -> 0 | I18: =$F$2*IF(I$6<$B18,0,1)*(1+0.072*MAX(MIN($B18,70)-$B$2,0))*IF(I$6>=75,1.1,1)*IF($B18<75,IF($C$2<=$G$2,1,0),IF($C$2<=$H$2,1,0))*IF(OR(I$6<$B$2,$B18<$B$2),0,1) -> 0 | J18: =$F$2*IF(J$6<$B18,0,1)*(1+0.072*MAX(MIN($B18,70)-$B$2,0))*IF(J$6>=75,1.1,1)*IF($B18<75,IF($C$2<=$G$2,1,0),IF($C$2<=$H$2,1,0))*IF(OR(J$6<$B$2,$B18<$B$2),0,1) -> 0 | ... DS18: =$F$2*IF(DS$6<$B18,0,1)*(1+0.072*MAX(MIN($B18,70)-$B$2,0))*IF(DS$6>=75,1.1,1)*IF($B18<75,IF($C$2<=$G$2,1,0),IF($C$2<=$H$2,1,0))*IF(OR(DS$6<$B$2,$B18<$B$2),0,1) -> 318.17371 | DT18: =SUMPRODUCT($C$5:$DR$5,C18:DR18)+DS18*12*$DR$2 -> 62472.806
A19: 11 | B19: =$B$8+A19/12 -> 65.916667 | C19: =$F$2*IF(C$6<$B19,0,1)*(1+0.072*MAX(MIN($B19,70)-$B$2,0))*IF(C$6>=75,1.1,1)*IF($B19<75,IF($C$2<=$G$2,1,0),IF($C$2<=$H$2,1,0))*IF(OR(C$6<$B$2,$B19<$B$2),0,1) -> 0 | D19: =$F$2*IF(D$6<$B19,0,1)*(1+0.072*MAX(MIN($B19,70)-$B$2,0))*IF(D$6>=75,1.1,1)*IF($B19<75,IF($C$2<=$G$2,1,0),IF($C$2<=$H$2,1,0))*IF(OR(D$6<$B$2,$B19<$B$2),0,1) -> 0 | E19: =$F$2*IF(E$6<$B19,0,1)*(1+0.072*MAX(MIN($B19,70)-$B$2,0))*IF(E$6>=75,1.1,1)*IF($B19<75,IF($C$2<=$G$2,1,0),IF($C$2<=$H$2,1,0))*IF(OR(E$6<$B$2,$B19<$B$2),0,1) -> 0 | F19: =$F$2*IF(F$6<$B19,0,1)*(1+0.072*MAX(MIN($B19,70)-$B$2,0))*IF(F$6>=75,1.1,1)*IF($B19<75,IF($C$2<=$G$2,1,0),IF($C$2<=$H$2,1,0))*IF(OR(F$6<$B$2,$B19<$B$2),0,1) -> 0 | G19: =$F$2*IF(G$6<$B19,0,1)*(1+0.072*MAX(MIN($B19,70)-$B$2,0))*IF(G$6>=75,1.1,1)*IF($B19<75,IF($C$2<=$G$2,1,0),IF($C$2<=$H$2,1,0))*IF(OR(G$6<$B$2,$B19<$B$2),0,1) -> 0 | H19: =$F$2*IF(H$6<$B19,0,1)*(1+0.072*MAX(MIN($B19,70)-$B$2,0))*IF(H$6>=75,1.1,1)*IF($B19<75,IF($C$2<=$G$2,1,0),IF($C$2<=$H$2,1,0))*IF(OR(H$6<$B$2,$B19<$B$2),0,1) -> 0 | I19: =$F$2*IF(I$6<$B19,0,1)*(1+0.072*MAX(MIN($B19,70)-$B$2,0))*IF(I$6>=75,1.1,1)*IF($B19<75,IF($C$2<=$G$2,1,0),IF($C$2<=$H$2,1,0))*IF(OR(I$6<$B$2,$B19<$B$2),0,1) -> 0 | J19: =$F$2*IF(J$6<$B19,0,1)*(1+0.072*MAX(MIN($B19,70)-$B$2,0))*IF(J$6>=75,1.1,1)*IF($B19<75,IF($C$2<=$G$2,1,0),IF($C$2<=$H$2,1,0))*IF(OR(J$6<$B$2,$B19<$B$2),0,1) -> 0 | ... DS19: =$F$2*IF(DS$6<$B19,0,1)*(1+0.072*MAX(MIN($B19,70)-$B$2,0))*IF(DS$6>=75,1.1,1)*IF($B19<75,IF($C$2<=$G$2,1,0),IF($C$2<=$H$2,1,0))*IF(OR(DS$6<$B$2,$B19<$B$2),0,1) -> 319.97469 | DT19: =SUMPRODUCT($C$5:$DR$5,C19:DR19)+DS19*12*$DR$2 -> 62545.304
A20: 12 | B20: =$B$8+A20/12 -> 66 | C20: =$F$2*IF(C$6<$B20,0,1)*(1+0.072*MAX(MIN($B20,70)-$B$2,0))*IF(C$6>=75,1.1,1)*IF($B20<75,IF($C$2<=$G$2,1,0),IF($C$2<=$H$2,1,0))*IF(OR(C$6<$B$2,$B20<$B$2),0,1) -> 0 | D20: =$F$2*IF(D$6<$B20,0,1)*(1+0.072*MAX(MIN($B20,70)-$B$2,0))*IF(D$6>=75,1.1,1)*IF($B20<75,IF($C$2<=$G$2,1,0),IF($C$2<=$H$2,1,0))*IF(OR(D$6<$B$2,$B20<$B$2),0,1) -> 0 | E20: =$F$2*IF(E$6<$B20,0,1)*(1+0.072*MAX(MIN($B20,70)-$B$2,0))*IF(E$6>=75,1.1,1)*IF($B20<75,IF($C$2<=$G$2,1,0),IF($C$2<=$H$2,1,0))*IF(OR(E$6<$B$2,$B20<$B$2),0,1) -> 0 | F20: =$F$2*IF(F$6<$B20,0,1)*(1+0.072*MAX(MIN($B20,70)-$B$2,0))*IF(F$6>=75,1.1,1)*IF($B20<75,IF($C$2<=$G$2,1,0),IF($C$2<=$H$2,1,0))*IF(OR(F$6<$B$2,$B20<$B$2),0,1) -> 0 | G20: =$F$2*IF(G$6<$B20,0,1)*(1+0.072*MAX(MIN($B20,70)-$B$2,0))*IF(G$6>=75,1.1,1)*IF($B20<75,IF($C$2<=$G$2,1,0),IF($C$2<=$H$2,1,0))*IF(OR(G$6<$B$2,$B20<$B$2),0,1) -> 0 | H20: =$F$2*IF(H$6<$B20,0,1)*(1+0.072*MAX(MIN($B20,70)-$B$2,0))*IF(H$6>=75,1.1,1)*IF($B20<75,IF($C$2<=$G$2,1,0),IF($C$2<=$H$2,1,0))*IF(OR(H$6<$B$2,$B20<$B$2),0,1) -> 0 | I20: =$F$2*IF(I$6<$B20,0,1)*(1+0.072*MAX(MIN($B20,70)-$B$2,0))*IF(I$6>=75,1.1,1)*IF($B20<75,IF($C$2<=$G$2,1,0),IF($C$2<=$H$2,1,0))*IF(OR(I$6<$B$2,$B20<$B$2),0,1) -> 0 | J20: =$F$2*IF(J$6<$B20,0,1)*(1+0.072*MAX(MIN($B20,70)-$B$2,0))*IF(J$6>=75,1.1,1)*IF($B20<75,IF($C$2<=$G$2,1,0),IF($C$2<=$H$2,1,0))*IF(OR(J$6<$B$2,$B20<$B$2),0,1) -> 0 | ... DS20: =$F$2*IF(DS$6<$B20,0,1)*(1+0.072*MAX(MIN($B20,70)-$B$2,0))*IF(DS$6>=75,1.1,1)*IF($B20<75,IF($C$2<=$G$2,1,0),IF($C$2<=$H$2,1,0))*IF(OR(DS$6<$B$2,$B20<$B$2),0,1) -> 321.77567 | DT20: =SUMPRODUCT($C$5:$DR$5,C20:DR20)+DS20*12*$DR$2 -> 62615.602
... A128: 120 | B128: =$B$8+A128/12 -> 75 | C128: =$F$2*IF(C$6<$B128,0,1)*(1+0.072*MAX(MIN($B128,70)-$B$2,0))*IF(C$6>=75,1.1,1)*IF($B128<75,IF($C$2<=$G$2,1,0),IF($C$2<=$H$2,1,0))*IF(OR(C$6<$B$2,$B128<$B$2),0,1) -> 0 | D128: =$F$2*IF(D$6<$B128,0,1)*(1+0.072*MAX(MIN($B128,70)-$B$2,0))*IF(D$6>=75,1.1,1)*IF($B128<75,IF($C$2<=$G$2,1,0),IF($C$2<=$H$2,1,0))*IF(OR(D$6<$B$2,$B128<$B$2),0,1) -> 0 | E128: =$F$2*IF(E$6<$B128,0,1)*(1+0.072*MAX(MIN($B128,70)-$B$2,0))*IF(E$6>=75,1.1,1)*IF($B128<75,IF($C$2<=$G$2,1,0),IF($C$2<=$H$2,1,0))*IF(OR(E$6<$B$2,$B128<$B$2),0,1) -> 0 | F128: =$F$2*IF(F$6<$B128,0,1)*(1+0.072*MAX(MIN($B128,70)-$B$2,0))*IF(F$6>=75,1.1,1)*IF($B128<75,IF($C$2<=$G$2,1,0),IF($C$2<=$H$2,1,0))*IF(OR(F$6<$B$2,$B128<$B$2),0,1) -> 0 | G128: =$F$2*IF(G$6<$B128,0,1)*(1+0.072*MAX(MIN($B128,70)-$B$2,0))*IF(G$6>=75,1.1,1)*IF($B128<75,IF($C$2<=$G$2,1,0),IF($C$2<=$H$2,1,0))*IF(OR(G$6<$B$2,$B128<$B$2),0,1) -> 0 | H128: =$F$2*IF(H$6<$B128,0,1)*(1+0.072*MAX(MIN($B128,70)-$B$2,0))*IF(H$6>=75,1.1,1)*IF($B128<75,IF($C$2<=$G$2,1,0),IF($C$2<=$H$2,1,0))*IF(OR(H$6<$B$2,$B128<$B$2),0,1) -> 0 | I128: =$F$2*IF(I$6<$B128,0,1)*(1+0.072*MAX(MIN($B128,70)-$B$2,0))*IF(I$6>=75,1.1,1)*IF($B128<75,IF($C$2<=$G$2,1,0),IF($C$2<=$H$2,1,0))*IF(OR(I$6<$B$2,$B128<$B$2),0,1) -> 0 | J128: =$F$2*IF(J$6<$B128,0,1)*(1+0.072*MAX(MIN($B128,70)-$B$2,0))*IF(J$6>=75,1.1,1)*IF($B128<75,IF($C$2<=$G$2,1,0),IF($C$2<=$H$2,1,0))*IF(OR(J$6<$B$2,$B128<$B$2),0,1) -> 0 | ... DS128: =$F$2*IF(DS$6<$B128,0,1)*(1+0.072*MAX(MIN($B128,70)-$B$2,0))*IF(DS$6>=75,1.1,1)*IF($B128<75,IF($C$2<=$G$2,1,0),IF($C$2<=$H$2,1,0))*IF(OR(DS$6<$B$2,$B128<$B$2),0,1) -> 408.22287 | DT128: =SUMPRODUCT($C$5:$DR$5,C128:DR128)+DS128*12*$DR$2 -> 47815.985

Sheet Payments (excl.)
B1: Qualified Age | C1: Residency | D1: B(65,0) | F1: min(B) | G1: Max Income | H1: 75 and above | DO1: mu_75 | DP1: A_75 | DQ1: a_75 | DR1: (UDD) | DS1: (WH3)
B2: =65+MAX(10-$C$2,0) -> 65 | C2: 14 | D2: =727.67*MAX(FLOOR(MIN($C$2,40),1),10)/40 -> 254.6845 | F2: 100000 | G2: 142609 | H2: 148179 | DO2: ='[1]Life Table'!E13 -> 0.028389182 | DP2: ='[1]Life Table'!F13 -> 0.70222735 | DQ2: ='[1]Life Table'!G13 -> 10.223528 | DR2: ='[1]Life Table'!H13 -> 9.7610048 | DS2: ='[1]Life Table'!I13 -> 9.7603988
A3: u | B3: Deferred Age | C3: Residency | D3: Deferral | DT3: PV
A4: 0 | B4: =B2 -> 65 | C4: =$D$2*1/FLOOR(MAX($C$2,10),1)*(FLOOR(MAX($C$2,10)+MIN((70-$B$2)*12,$A4)/12,1))*(1+0.072*(MIN((70-$B$2)*12,$A4)/12-FLOOR(MIN((70-$B$2)*12,$A4)/12,1)))*IF($B4>=75,1.1,1) -> 254.6845 | D4: =$D$2*(1+0.072*(MIN(70,$B4)-$B$2))*IF($B4>=75,1.1,1) -> 254.6845 | E4: =IF(C4>D4,$C$3,$D$3) -> Deferral | G4: New Finding | DT4: =SUMPRODUCT(#REF!,C4:DR4)+DS4*12*$DR$2 -> #REF!
A5: 1 | B5: =$B$4+A5/12 -> 65.083333 | C5: =$D$2*1/FLOOR(MAX($C$2,10),1)*(FLOOR(MAX($C$2,10)+MIN((70-$B$2)*12,$A5)/12,1))*(1+0.072*(MIN((70-$B$2)*12,$A5)/12-FLOOR(MIN((70-$B$2)*12,$A5)/12,1)))*IF($B5>=75,1.1,1) -> 256.21261 | D5: =$D$2*(1+0.072*(MIN(70,$B5)-$B$2))*IF($B5>=75,1.1,1) -> 256.21261 | E5: =IF(C5>D5,$C$3,$D$3) -> Deferral | G5: You'll find the calculations from gov follows like this: max(Redicency,Deferral) | DT5: =SUMPRODUCT(#REF!,C5:DR5)+DS5*12*$DR$2 -> #REF!
A6: 2 | B6: =$B$4+A6/12 -> 65.166667 | C6: =$D$2*1/FLOOR(MAX($C$2,10),1)*(FLOOR(MAX($C$2,10)+MIN((70-$B$2)*12,$A6)/12,1))*(1+0.072*(MIN((70-$B$2)*12,$A6)/12-FLOOR(MIN((70-$B$2)*12,$A6)/12,1)))*IF($B6>=75,1.1,1) -> 257.74071 | D6: =$D$2*(1+0.072*(MIN(70,$B6)-$B$2))*IF($B6>=75,1.1,1) -> 257.74071 | E6: =IF(C6>D6,$C$3,$D$3) -> Deferral | G6: However, this issue only appears when residency is less than 15 years. | DT6: =SUMPRODUCT(#REF!,C6:DR6)+DS6*12*$DR$2 -> #REF!
A7: 3 | B7: =$B$4+A7/12 -> 65.25 | C7: =$D$2*1/FLOOR(MAX($C$2,10),1)*(FLOOR(MAX($C$2,10)+MIN((70-$B$2)*12,$A7)/12,1))*(1+0.072*(MIN((70-$B$2)*12,$A7)/12-FLOOR(MIN((70-$B$2)*12,$A7)/12,1)))*IF($B7>=75,1.1,1) -> 259.26882 | D7: =$D$2*(1+0.072*(MIN(70,$B7)-$B$2))*IF($B7>=75,1.1,1) -> 259.26882 | E7: =IF(C7>D7,$C$3,$D$3) -> Deferral | G7: e.g. check the payments beyond 1-year deferral with residency less than 15. | DT7: =SUMPRODUCT(#REF!,C7:DR7)+DS7*12*$DR$2 -> #REF!
A8: 4 | B8: =$B$4+A8/12 -> 65.333333 | C8: =$D$2*1/FLOOR(MAX($C$2,10),1)*(FLOOR(MAX($C$2,10)+MIN((70-$B$2)*12,$A8)/12,1))*(1+0.072*(MIN((70-$B$2)*12,$A8)/12-FLOOR(MIN((70-$B$2)*12,$A8)/12,1)))*IF($B8>=75,1.1,1) -> 260.79693 | D8: =$D$2*(1+0.072*(MIN(70,$B8)-$B$2))*IF($B8>=75,1.1,1) -> 260.79693 | E8: =IF(C8>D8,$C$3,$D$3) -> Deferral | G8: Problem | DT8: =SUMPRODUCT(#REF!,C8:DR8)+DS8*12*$DR$2 -> #REF!
A9: 5 | B9: =$B$4+A9/12 -> 65.416667 | C9: =$D$2*1/FLOOR(MAX($C$2,10),1)*(FLOOR(MAX($C$2,10)+MIN((70-$B$2)*12,$A9)/12,1))*(1+0.072*(MIN((70-$B$2)*12,$A9)/12-FLOOR(MIN((70-$B$2)*12,$A9)/12,1)))*IF($B9>=75,1.1,1) -> 262.32504 | D9: =$D$2*(1+0.072*(MIN(70,$B9)-$B$2))*IF($B9>=75,1.1,1) -> 262.32504 | E9: =IF(C9>D9,$C$3,$D$3) -> Deferral | G9: This will also make some deferrals lower than previous month! | DT9: =SUMPRODUCT(#REF!,C9:DR9)+DS9*12*$DR$2 -> #REF!
A10: 6 | B10: =$B$4+A10/12 -> 65.5 | C10: =$D$2*1/FLOOR(MAX($C$2,10),1)*(FLOOR(MAX($C$2,10)+MIN((70-$B$2)*12,$A10)/12,1))*(1+0.072*(MIN((70-$B$2)*12,$A10)/12-FLOOR(MIN((70-$B$2)*12,$A10)/12,1)))*IF($B10>=75,1.1,1) -> 263.85314 | D10: =$D$2*(1+0.072*(MIN(70,$B10)-$B$2))*IF($B10>=75,1.1,1) -> 263.85314 | E10: =IF(C10>D10,$C$3,$D$3) -> Deferral | G10: But it only appears when residency is 14 years. | DT10: =SUMPRODUCT(#REF!,C10:DR10)+DS10*12*$DR$2 -> #REF!
A11: 7 | B11: =$B$4+A11/12 -> 65.583333 | C11: =$D$2*1/FLOOR(MAX($C$2,10),1)*(FLOOR(MAX($C$2,10)+MIN((70-$B$2)*12,$A11)/12,1))*(1+0.072*(MIN((70-$B$2)*12,$A11)/12-FLOOR(MIN((70-$B$2)*12,$A11)/12,1)))*IF($B11>=75,1.1,1) -> 265.38125 | D11: =$D$2*(1+0.072*(MIN(70,$B11)-$B$2))*IF($B11>=75,1.1,1) -> 265.38125 | E11: =IF(C11>D11,$C$3,$D$3) -> Deferral | G11: Reason | DT11: =SUMPRODUCT(#REF!,C11:DR11)+DS11*12*$DR$2 -> #REF!
A12: 8 | B12: =$B$4+A12/12 -> 65.666667 | C12: =$D$2*1/FLOOR(MAX($C$2,10),1)*(FLOOR(MAX($C$2,10)+MIN((70-$B$2)*12,$A12)/12,1))*(1+0.072*(MIN((70-$B$2)*12,$A12)/12-FLOOR(MIN((70-$B$2)*12,$A12)/12,1)))*IF($B12>=75,1.1,1) -> 266.90936 | D12: =$D$2*(1+0.072*(MIN(70,$B12)-$B$2))*IF($B12>=75,1.1,1) -> 266.90936 | E12: =IF(C12>D12,$C$3,$D$3) -> Deferral | G12: Residency only increases proportionally in discrete integers, | DT12: =SUMPRODUCT(#REF!,C12:DR12)+DS12*12*$DR$2 -> #REF!
A13: 9 | B13: =$B$4+A13/12 -> 65.75 | C13: =$D$2*1/FLOOR(MAX($C$2,10),1)*(FLOOR(MAX($C$2,10)+MIN((70-$B$2)*12,$A13)/12,1))*(1+0.072*(MIN((70-$B$2)*12,$A13)/12-FLOOR(MIN((70-$B$2)*12,$A13)/12,1)))*IF($B13>=75,1.1,1) -> 268.43746 | D13: =$D$2*(1+0.072*(MIN(70,$B13)-$B$2))*IF($B13>=75,1.1,1) -> 268.43746 | E13: =IF(C13>D13,$C$3,$D$3) -> Deferral | G13: then the 0.6% linear increase will be applied after the ratio change. | DT13: =SUMPRODUCT(#REF!,C13:DR13)+DS13*12*$DR$2 -> #REF!
A14: 10 | B14: =$B$4+A14/12 -> 65.833333 | C14: =$D$2*1/FLOOR(MAX($C$2,10),1)*(FLOOR(MAX($C$2,10)+MIN((70-$B$2)*12,$A14)/12,1))*(1+0.072*(MIN((70-$B$2)*12,$A14)/12-FLOOR(MIN((70-$B$2)*12,$A14)/12,1)))*IF($B14>=75,1.1,1) -> 269.96557 | D14: =$D$2*(1+0.072*(MIN(70,$B14)-$B$2))*IF($B14>=75,1.1,1) -> 269.96557 | E14: =IF(C14>D14,$C$3,$D$3) -> Deferral | G14: Therefore, some payments have such priorized ratio increase greater than the linear one. | DT14: =SUMPRODUCT(#REF!,C14:DR14)+DS14*12*$DR$2 -> #REF!
A15: 11 | B15: =$B$4+A15/12 -> 65.916667 | C15: =$D$2*1/FLOOR(MAX($C$2,10),1)*(FLOOR(MAX($C$2,10)+MIN((70-$B$2)*12,$A15)/12,1))*(1+0.072*(MIN((70-$B$2)*12,$A15)/12-FLOOR(MIN((70-$B$2)*12,$A15)/12,1)))*IF($B15>=75,1.1,1) -> 271.49368 | D15: =$D$2*(1+0.072*(MIN(70,$B15)-$B$2))*IF($B15>=75,1.1,1) -> 271.49368 | E15: =IF(C15>D15,$C$3,$D$3) -> Deferral | G15: Conclude | DT15: =SUMPRODUCT(#REF!,C15:DR15)+DS15*12*$DR$2 -> #REF!
A16: 12 | B16: =$B$4+A16/12 -> 66 | C16: =$D$2*1/FLOOR(MAX($C$2,10),1)*(FLOOR(MAX($C$2,10)+MIN((70-$B$2)*12,$A16)/12,1))*(1+0.072*(MIN((70-$B$2)*12,$A16)/12-FLOOR(MIN((70-$B$2)*12,$A16)/12,1)))*IF($B16>=75,1.1,1) -> 272.87625 | D16: =$D$2*(1+0.072*(MIN(70,$B16)-$B$2))*IF($B16>=75,1.1,1) -> 273.02178 | E16: =IF(C16>D16,$C$3,$D$3) -> Deferral | G16: I spoke to Cherie, this is too difficult to explain and only affect minority | DT16: =SUMPRODUCT(#REF!,C16:DR16)+DS16*12*$DR$2 -> #REF!
A17: 13 | B17: =$B$4+A17/12 -> 66.083333 | C17: =$D$2*1/FLOOR(MAX($C$2,10),1)*(FLOOR(MAX($C$2,10)+MIN((70-$B$2)*12,$A17)/12,1))*(1+0.072*(MIN((70-$B$2)*12,$A17)/12-FLOOR(MIN((70-$B$2)*12,$A17)/12,1)))*IF($B17>=75,1.1,1) -> 274.51351 | D17: =$D$2*(1+0.072*(MIN(70,$B17)-$B$2))*IF($B17>=75,1.1,1) -> 274.54989 | E17: =IF(C17>D17,$C$3,$D$3) -> Deferral | G17: So please discard this analysis… | DT17: =SUMPRODUCT(#REF!,C17:DR17)+DS17*12*$DR$2 -> #REF!
A18: 14 | B18: =$B$4+A18/12 -> 66.166667 | C18: =$D$2*1/FLOOR(MAX($C$2,10),1)*(FLOOR(MAX($C$2,10)+MIN((70-$B$2)*12,$A18)/12,1))*(1+0.072*(MIN((70-$B$2)*12,$A18)/12-FLOOR(MIN((70-$B$2)*12,$A18)/12,1)))*IF($B18>=75,1.1,1) -> 276.15076 | D18: =$D$2*(1+0.072*(MIN(70,$B18)-$B$2))*IF($B18>=75,1.1,1) -> 276.078 | E18: =IF(C18>D18,$C$3,$D$3) -> Residency | DT18: =SUMPRODUCT(#REF!,C18:DR18)+DS18*12*$DR$2 -> #REF!
A19: 15 | B19: =$B$4+A19/12 -> 66.25 | C19: =$D$2*1/FLOOR(MAX($C$2,10),1)*(FLOOR(MAX($C$2,10)+MIN((70-$B$2)*12,$A19)/12,1))*(1+0.072*(MIN((70-$B$2)*12,$A19)/12-FLOOR(MIN((70-$B$2)*12,$A19)/12,1)))*IF($B19>=75,1.1,1) -> 277.78802 | D19: =$D$2*(1+0.072*(MIN(70,$B19)-$B$2))*IF($B19>=75,1.1,1) -> 277.60611 | E19: =IF(C19>D19,$C$3,$D$3) -> Residency | DT19: =SUMPRODUCT(#REF!,C19:DR19)+DS19*12*$DR$2 -> #REF!
A20: 16 | B20: =$B$4+A20/12 -> 66.333333 | C20: =$D$2*1/FLOOR(MAX($C$2,10),1)*(FLOOR(MAX($C$2,10)+MIN((70-$B$2)*12,$A20)/12,1))*(1+0.072*(MIN((70-$B$2)*12,$A20)/12-FLOOR(MIN((70-$B$2)*12,$A20)/12,1)))*IF($B20>=75,1.1,1) -> 279.42528 | D20: =$D$2*(1+0.072*(MIN(70,$B20)-$B$2))*IF($B20>=75,1.1,1) -> 279.13421 | E20: =IF(C20>D20,$C$3,$D$3) -> Residency | DT20: =SUMPRODUCT(#REF!,C20:DR20)+DS20*12*$DR$2 -> #REF!
A21: 17 | B21: =$B$4+A21/12 -> 66.416667 | C21: =$D$2*1/FLOOR(MAX($C$2,10),1)*(FLOOR(MAX($C$2,10)+MIN((70-$B$2)*12,$A21)/12,1))*(1+0.072*(MIN((70-$B$2)*12,$A21)/12-FLOOR(MIN((70-$B$2)*12,$A21)/12,1)))*IF($B21>=75,1.1,1) -> 281.06254 | D21: =$D$2*(1+0.072*(MIN(70,$B21)-$B$2))*IF($B21>=75,1.1,1) -> 280.66232 | E21: =IF(C21>D21,$C$3,$D$3) -> Residency | DT21: =SUMPRODUCT(#REF!,C21:DR21)+DS21*12*$DR$2 -> #REF!
A22: 18 | B22: =$B$4+A22/12 -> 66.5 | C22: =$D$2*1/FLOOR(MAX($C$2,10),1)*(FLOOR(MAX($C$2,10)+MIN((70-$B$2)*12,$A22)/12,1))*(1+0.072*(MIN((70-$B$2)*12,$A22)/12-FLOOR(MIN((70-$B$2)*12,$A22)/12,1)))*IF($B22>=75,1.1,1) -> 282.69979 | D22: =$D$2*(1+0.072*(MIN(70,$B22)-$B$2))*IF($B22>=75,1.1,1) -> 282.19043 | E22: =IF(C22>D22,$C$3,$D$3) -> Residency | DT22: =SUMPRODUCT(#REF!,C22:DR22)+DS22*12*$DR$2 -> #REF!
A23: 19 | B23: =$B$4+A23/12 -> 66.583333 | C23: =$D$2*1/FLOOR(MAX($C$2,10),1)*(FLOOR(MAX($C$2,10)+MIN((70-$B$2)*12,$A23)/12,1))*(1+0.072*(MIN((70-$B$2)*12,$A23)/12-FLOOR(MIN((70-$B$2)*12,$A23)/12,1)))*IF($B23>=75,1.1,1) -> 284.33705 | D23: =$D$2*(1+0.072*(MIN(70,$B23)-$B$2))*IF($B23>=75,1.1,1) -> 283.71853 | E23: =IF(C23>D23,$C$3,$D$3) -> Residency | DT23: =SUMPRODUCT(#REF!,C23:DR23)+DS23*12*$DR$2 -> #REF!
A24: 20 | B24: =$B$4+A24/12 -> 66.666667 | C24: =$D$2*1/FLOOR(MAX($C$2,10),1)*(FLOOR(MAX($C$2,10)+MIN((70-$B$2)*12,$A24)/12,1))*(1+0.072*(MIN((70-$B$2)*12,$A24)/12-FLOOR(MIN((70-$B$2)*12,$A24)/12,1)))*IF($B24>=75,1.1,1) -> 285.97431 | D24: =$D$2*(1+0.072*(MIN(70,$B24)-$B$2))*IF($B24>=75,1.1,1) -> 285.24664 | E24: =IF(C24>D24,$C$3,$D$3) -> Residency | DT24: =SUMPRODUCT(#REF!,C24:DR24)+DS24*12*$DR$2 -> #REF!
A25: 21 | B25: =$B$4+A25/12 -> 66.75 | C25: =$D$2*1/FLOOR(MAX($C$2,10),1)*(FLOOR(MAX($C$2,10)+MIN((70-$B$2)*12,$A25)/12,1))*(1+0.072*(MIN((70-$B$2)*12,$A25)/12-FLOOR(MIN((70-$B$2)*12,$A25)/12,1)))*IF($B25>=75,1.1,1) -> 287.61157 | D25: =$D$2*(1+0.072*(MIN(70,$B25)-$B$2))*IF($B25>=75,1.1,1) -> 286.77475 | E25: =IF(C25>D25,$C$3,$D$3) -> Residency | DT25: =SUMPRODUCT(#REF!,C25:DR25)+DS25*12*$DR$2 -> #REF!
A26: 22 | B26: =$B$4+A26/12 -> 66.833333 | C26: =$D$2*1/FLOOR(MAX($C$2,10),1)*(FLOOR(MAX($C$2,10)+MIN((70-$B$2)*12,$A26)/12,1))*(1+0.072*(MIN((70-$B$2)*12,$A26)/12-FLOOR(MIN((70-$B$2)*12,$A26)/12,1)))*IF($B26>=75,1.1,1) -> 289.24883 | D26: =$D$2*(1+0.072*(MIN(70,$B26)-$B$2))*IF($B26>=75,1.1,1) -> 288.30285 | E26: =IF(C26>D26,$C$3,$D$3) -> Residency | DT26: =SUMPRODUCT(#REF!,C26:DR26)+DS26*12*$DR$2 -> #REF!
A27: 23 | B27: =$B$4+A27/12 -> 66.916667 | C27: =$D$2*1/FLOOR(MAX($C$2,10),1)*(FLOOR(MAX($C$2,10)+MIN((70-$B$2)*12,$A27)/12,1))*(1+0.072*(MIN((70-$B$2)*12,$A27)/12-FLOOR(MIN((70-$B$2)*12,$A27)/12,1)))*IF($B27>=75,1.1,1) -> 290.88608 | D27: =$D$2*(1+0.072*(MIN(70,$B27)-$B$2))*IF($B27>=75,1.1,1) -> 289.83096 | E27: =IF(C27>D27,$C$3,$D$3) -> Residency | DT27: =SUMPRODUCT(#REF!,C27:DR27)+DS27*12*$DR$2 -> #REF!
A28: 24 | B28: =$B$4+A28/12 -> 67 | C28: =$D$2*1/FLOOR(MAX($C$2,10),1)*(FLOOR(MAX($C$2,10)+MIN((70-$B$2)*12,$A28)/12,1))*(1+0.072*(MIN((70-$B$2)*12,$A28)/12-FLOOR(MIN((70-$B$2)*12,$A28)/12,1)))*IF($B28>=75,1.1,1) -> 291.068 | D28: =$D$2*(1+0.072*(MIN(70,$B28)-$B$2))*IF($B28>=75,1.1,1) -> 291.35907 | E28: =IF(C28>D28,$C$3,$D$3) -> Deferral | DT28: =SUMPRODUCT(#REF!,C28:DR28)+DS28*12*$DR$2 -> #REF!
A29: 25 | B29: =$B$4+A29/12 -> 67.083333 | C29: =$D$2*1/FLOOR(MAX($C$2,10),1)*(FLOOR(MAX($C$2,10)+MIN((70-$B$2)*12,$A29)/12,1))*(1+0.072*(MIN((70-$B$2)*12,$A29)/12-FLOOR(MIN((70-$B$2)*12,$A29)/12,1)))*IF($B29>=75,1.1,1) -> 292.81441 | D29: =$D$2*(1+0.072*(MIN(70,$B29)-$B$2))*IF($B29>=75,1.1,1) -> 292.88717 | E29: =IF(C29>D29,$C$3,$D$3) -> Deferral | DT29: =SUMPRODUCT(#REF!,C29:DR29)+DS29*12*$DR$2 -> #REF!
... A124: 120 | B124: =$B$4+A124/12 -> 75 | C124: =$D$2*1/FLOOR(MAX($C$2,10),1)*(FLOOR(MAX($C$2,10)+MIN((70-$B$2)*12,$A124)/12,1))*(1+0.072*(MIN((70-$B$2)*12,$A124)/12-FLOOR(MIN((70-$B$2)*12,$A124)/12,1)))*IF($B124>=75,1.1,1) -> 380.20758 | D124: =$D$2*(1+0.072*(MIN(70,$B124)-$B$2))*IF($B124>=75,1.1,1) -> 381.00801 | E124: =IF(C124>D124,$C$3,$D$3) -> Deferral | DT124: =SUMPRODUCT(#REF!,C124:DR124)+DS124*12*$DR$2 -> #REF!

Sheet Payments (Revised)
B1: Qualified Age | C1: Residency | D1: max B_65 | E1: Income | F1: Max Income | G1: 75 and above | DM1: mu_75 | DN1: A_75 | DO1: a_75 | DP1: (UDD) | DQ1: (WH3)
B2: =65+MAX(0,10-$C$2) -> 65 | C2: ='Cover Page'!B4 -> 15 | D2: 727.67 | E2: ='Cover Page'!B2 -> 142609 | F2: 142609 | G2: 148179 | DM2: ='[1]Life Table'!E13 -> 0.028389182 | DN2: ='[1]Life Table'!F13 -> 0.70222735 | DO2: ='[1]Life Table'!G13 -> 10.223528 | DP2: ='[1]Life Table'!H13 -> 9.7610048 | DQ2: ='[1]Life Table'!I13 -> 9.7603988
A3: u | B3: Deferred Age | C3: Residency | D3: Method | E3: Residency | F3: R >= 10? | G3: Income? | H3: resid ratio | I3: subdefer | J3: defer | DR3: PV
A4: 0 | B4: 65 | C4: =$D$2*MAX($H4*$I4,$J4)*$F4*$G4 -> 272.87625 | D4: =IF($H4*$I4>$J4,$H$3,$J$3) -> defer | E4: =$C$2+$A4/12 -> 15 | F4: =IF($C$2+$A4/12>=10,1,0) -> 1 | G4: =IF($B4<75,IF($E$2<=$F$2,1,0),IF($E$2<=$G$2,1,0)) -> 1 | H4: =1/40*MIN(MAX(FLOOR(FLOOR($C$2,1)+MIN($A4/12,5),1),10),40) -> 0.375 | I4: =(1+0.072*(MIN($A4/12,5)-FLOOR(MIN($A4/12,5),1))) -> 1 | J4: =MIN(FLOOR($C$2,1),40)/40*(1+0.072*MIN($A4/12,5)) -> 0.375 | DR4: =SUMPRODUCT(#REF!,C4:DP4)+DQ4*12*$DP$2 -> #REF!
A5: 1 | B5: =$B$4+A5/12 -> 65.083333 | C5: =$D$2*MAX($H5*$I5,$J5)*$F5*$G5 -> 274.51351 | D5: =IF($H5*$I5>$J5,$H$3,$J$3) -> defer | E5: =$C$2+$A5/12 -> 15.083333 | F5: =IF($C$2+$A5/12>=10,1,0) -> 1 | G5: =IF($B5<75,IF($E$2<=$F$2,1,0),IF($E$2<=$G$2,1,0)) -> 1 | H5: =1/40*MIN(MAX(FLOOR(FLOOR($C$2,1)+MIN($A5/12,5),1),10),40) -> 0.375 | I5: =(1+0.072*(MIN($A5/12,5)-FLOOR(MIN($A5/12,5),1))) -> 1.006 | J5: =MIN(FLOOR($C$2,1),40)/40*(1+0.072*MIN($A5/12,5)) -> 0.37725 | DR5: =SUMPRODUCT(#REF!,C5:DP5)+DQ5*12*$DP$2 -> #REF!
A6: 2 | B6: =$B$4+A6/12 -> 65.166667 | C6: =$D$2*MAX($H6*$I6,$J6)*$F6*$G6 -> 276.15076 | D6: =IF($H6*$I6>$J6,$H$3,$J$3) -> defer | E6: =$C$2+$A6/12 -> 15.166667 | F6: =IF($C$2+$A6/12>=10,1,0) -> 1 | G6: =IF($B6<75,IF($E$2<=$F$2,1,0),IF($E$2<=$G$2,1,0)) -> 1 | H6: =1/40*MIN(MAX(FLOOR(FLOOR($C$2,1)+MIN($A6/12,5),1),10),40) -> 0.375 | I6: =(1+0.072*(MIN($A6/12,5)-FLOOR(MIN($A6/12,5),1))) -> 1.012 | J6: =MIN(FLOOR($C$2,1),40)/40*(1+0.072*MIN($A6/12,5)) -> 0.3795 | DR6: =SUMPRODUCT(#REF!,C6:DP6)+DQ6*12*$DP$2 -> #REF!
A7: 3 | B7: =$B$4+A7/12 -> 65.25 | C7: =$D$2*MAX($H7*$I7,$J7)*$F7*$G7 -> 277.78802 | D7: =IF($H7*$I7>$J7,$H$3,$J$3) -> defer | E7: =$C$2+$A7/12 -> 15.25 | F7: =IF($C$2+$A7/12>=10,1,0) -> 1 | G7: =IF($B7<75,IF($E$2<=$F$2,1,0),IF($E$2<=$G$2,1,0)) -> 1 | H7: =1/40*MIN(MAX(FLOOR(FLOOR($C$2,1)+MIN($A7/12,5),1),10),40) -> 0.375 | I7: =(1+0.072*(MIN($A7/12,5)-FLOOR(MIN($A7/12,5),1))) -> 1.018 | J7: =MIN(FLOOR($C$2,1),40)/40*(1+0.072*MIN($A7/12,5)) -> 0.38175 | DR7: =SUMPRODUCT(#REF!,C7:DP7)+DQ7*12*$DP$2 -> #REF!
A8: 4 | B8: =$B$4+A8/12 -> 65.333333 | C8: =$D$2*MAX($H8*$I8,$J8)*$F8*$G8 -> 279.42528 | D8: =IF($H8*$I8>$J8,$H$3,$J$3) -> defer | E8: =$C$2+$A8/12 -> 15.333333 | F8: =IF($C$2+$A8/12>=10,1,0) -> 1 | G8: =IF($B8<75,IF($E$2<=$F$2,1,0),IF($E$2<=$G$2,1,0)) -> 1 | H8: =1/40*MIN(MAX(FLOOR(FLOOR($C$2,1)+MIN($A8/12,5),1),10),40) -> 0.375 | I8: =(1+0.072*(MIN($A8/12,5)-FLOOR(MIN($A8/12,5),1))) -> 1.024 | J8: =MIN(FLOOR($C$2,1),40)/40*(1+0.072*MIN($A8/12,5)) -> 0.384 | DR8: =SUMPRODUCT(#REF!,C8:DP8)+DQ8*12*$DP$2 -> #REF!
A9: 5 | B9: =$B$4+A9/12 -> 65.416667 | C9: =$D$2*MAX($H9*$I9,$J9)*$F9*$G9 -> 281.06254 | D9: =IF($H9*$I9>$J9,$H$3,$J$3) -> defer | E9: =$C$2+$A9/12 -> 15.416667 | F9: =IF($C$2+$A9/12>=10,1,0) -> 1 | G9: =IF($B9<75,IF($E$2<=$F$2,1,0),IF($E$2<=$G$2,1,0)) -> 1 | H9: =1/40*MIN(MAX(FLOOR(FLOOR($C$2,1)+MIN($A9/12,5),1),10),40) -> 0.375 | I9: =(1+0.072*(MIN($A9/12,5)-FLOOR(MIN($A9/12,5),1))) -> 1.03 | J9: =MIN(FLOOR($C$2,1),40)/40*(1+0.072*MIN($A9/12,5)) -> 0.38625 | DR9: =SUMPRODUCT(#REF!,C9:DP9)+DQ9*12*$DP$2 -> #REF!
A10: 6 | B10: =$B$4+A10/12 -> 65.5 | C10: =$D$2*MAX($H10*$I10,$J10)*$F10*$G10 -> 282.69979 | D10: =IF($H10*$I10>$J10,$H$3,$J$3) -> defer | E10: =$C$2+$A10/12 -> 15.5 | F10: =IF($C$2+$A10/12>=10,1,0) -> 1 | G10: =IF($B10<75,IF($E$2<=$F$2,1,0),IF($E$2<=$G$2,1,0)) -> 1 | H10: =1/40*MIN(MAX(FLOOR(FLOOR($C$2,1)+MIN($A10/12,5),1),10),40) -> 0.375 | I10: =(1+0.072*(MIN($A10/12,5)-FLOOR(MIN($A10/12,5),1))) -> 1.036 | J10: =MIN(FLOOR($C$2,1),40)/40*(1+0.072*MIN($A10/12,5)) -> 0.3885 | DR10: =SUMPRODUCT(#REF!,C10:DP10)+DQ10*12*$DP$2 -> #REF!
A11: 7 | B11: =$B$4+A11/12 -> 65.583333 | C11: =$D$2*MAX($H11*$I11,$J11)*$F11*$G11 -> 284.33705 | D11: =IF($H11*$I11>$J11,$H$3,$J$3) -> defer | E11: =$C$2+$A11/12 -> 15.583333 | F11: =IF($C$2+$A11/12>=10,1,0) -> 1 | G11: =IF($B11<75,IF($E$2<=$F$2,1,0),IF($E$2<=$G$2,1,0)) -> 1 | H11: =1/40*MIN(MAX(FLOOR(FLOOR($C$2,1)+MIN($A11/12,5),1),10),40) -> 0.375 | I11: =(1+0.072*(MIN($A11/12,5)-FLOOR(MIN($A11/12,5),1))) -> 1.042 | J11: =MIN(FLOOR($C$2,1),40)/40*(1+0.072*MIN($A11/12,5)) -> 0.39075 | DR11: =SUMPRODUCT(#REF!,C11:DP11)+DQ11*12*$DP$2 -> #REF!
A12: 8 | B12: =$B$4+A12/12 -> 65.666667 | C12: =$D$2*MAX($H12*$I12,$J12)*$F12*$G12 -> 285.97431 | D12: =IF($H12*$I12>$J12,$H$3,$J$3) -> defer | E12: =$C$2+$A12/12 -> 15.666667 | F12: =IF($C$2+$A12/12>=10,1,0) -> 1 | G12: =IF($B12<75,IF($E$2<=$F$2,1,0),IF($E$2<=$G$2,1,0)) -> 1 | H12: =1/40*MIN(MAX(FLOOR(FLOOR($C$2,1)+MIN($A12/12,5),1),10),40) -> 0.375 | I12: =(1+0.072*(MIN($A12/12,5)-FLOOR(MIN($A12/12,5),1))) -> 1.048 | J12: =MIN(FLOOR($C$2,1),40)/40*(1+0.072*MIN($A12/12,5)) -> 0.393 | DR12: =SUMPRODUCT(#REF!,C12:DP12)+DQ12*12*$DP$2 -> #REF!
A13: 9 | B13: =$B$4+A13/12 -> 65.75 | C13: =$D$2*MAX($H13*$I13,$J13)*$F13*$G13 -> 287.61157 | D13: =IF($H13*$I13>$J13,$H$3,$J$3) -> defer | E13: =$C$2+$A13/12 -> 15.75 | F13: =IF($C$2+$A13/12>=10,1,0) -> 1 | G13: =IF($B13<75,IF($E$2<=$F$2,1,0),IF($E$2<=$G$2,1,0)) -> 1 | H13: =1/40*MIN(MAX(FLOOR(FLOOR($C$2,1)+MIN($A13/12,5),1),10),40) -> 0.375 | I13: =(1+0.072*(MIN($A13/12,5)-FLOOR(MIN($A13/12,5),1))) -> 1.054 | J13: =MIN(FLOOR($C$2,1),40)/40*(1+0.072*MIN($A13/12,5)) -> 0.39525 | DR13: =SUMPRODUCT(#REF!,C13:DP13)+DQ13*12*$DP$2 -> #REF!
A14: 10 | B14: =$B$4+A14/12 -> 65.833333 | C14: =$D$2*MAX($H14*$I14,$J14)*$F14*$G14 -> 289.24883 | D14: =IF($H14*$I14>$J14,$H$3,$J$3) -> defer | E14: =$C$2+$A14/12 -> 15.833333 | F14: =IF($C$2+$A14/12>=10,1,0) -> 1 | G14: =IF($B14<75,IF($E$2<=$F$2,1,0),IF($E$2<=$G$2,1,0)) -> 1 | H14: =1/40*MIN(MAX(FLOOR(FLOOR($C$2,1)+MIN($A14/12,5),1),10),40) -> 0.375 | I14: =(1+0.072*(MIN($A14/12,5)-FLOOR(MIN($A14/12,5),1))) -> 1.06 | J14: =MIN(FLOOR($C$2,1),40)/40*(1+0.072*MIN($A14/12,5)) -> 0.3975 | DR14: =SUMPRODUCT(#REF!,C14:DP14)+DQ14*12*$DP$2 -> #REF!
A15: 11 | B15: =$B$4+A15/12 -> 65.916667 | C15: =$D$2*MAX($H15*$I15,$J15)*$F15*$G15 -> 290.88608 | D15: =IF($H15*$I15>$J15,$H$3,$J$3) -> defer | E15: =$C$2+$A15/12 -> 15.916667 | F15: =IF($C$2+$A15/12>=10,1,0) -> 1 | G15: =IF($B15<75,IF($E$2<=$F$2,1,0),IF($E$2<=$G$2,1,0)) -> 1 | H15: =1/40*MIN(MAX(FLOOR(FLOOR($C$2,1)+MIN($A15/12,5),1),10),40) -> 0.375 | I15: =(1+0.072*(MIN($A15/12,5)-FLOOR(MIN($A15/12,5),1))) -> 1.066 | J15: =MIN(FLOOR($C$2,1),40)/40*(1+0.072*MIN($A15/12,5)) -> 0.39975 | DR15: =SUMPRODUCT(#REF!,C15:DP15)+DQ15*12*$DP$2 -> #REF!
A16: 12 | B16: =$B$4+A16/12 -> 66 | C16: =$D$2*MAX($H16*$I16,$J16)*$F16*$G16 -> 292.52334 | D16: =IF($H16*$I16>$J16,$H$3,$J$3) -> defer | E16: =$C$2+$A16/12 -> 16 | F16: =IF($C$2+$A16/12>=10,1,0) -> 1 | G16: =IF($B16<75,IF($E$2<=$F$2,1,0),IF($E$2<=$G$2,1,0)) -> 1 | H16: =1/40*MIN(MAX(FLOOR(FLOOR($C$2,1)+MIN($A16/12,5),1),10),40) -> 0.4 | I16: =(1+0.072*(MIN($A16/12,5)-FLOOR(MIN($A16/12,5),1))) -> 1 | J16: =MIN(FLOOR($C$2,1),40)/40*(1+0.072*MIN($A16/12,5)) -> 0.402 | DR16: =SUMPRODUCT(#REF!,C16:DP16)+DQ16*12*$DP$2 -> #REF!
... A123: 119 | B123: =$B$4+A123/12 -> 74.916667 | C123: =$D$2*MAX($H123*$I123,$J123)*$F123*$G123 -> 371.1117 | D123: =IF($H123*$I123>$J123,$H$3,$J$3) -> defer | E123: =$C$2+$A123/12 -> 24.916667 | F123: =IF($C$2+$A123/12>=10,1,0) -> 1 | G123: =IF($B123<75,IF($E$2<=$F$2,1,0),IF($E$2<=$G$2,1,0)) -> 1 | H123: =1/40*MIN(MAX(FLOOR(FLOOR($C$2,1)+MIN($A123/12,5),1),10),40) -> 0.5 | I123: =(1+0.072*(MIN($A123/12,5)-FLOOR(MIN($A123/12,5),1))) -> 1 | J123: =MIN(FLOOR($C$2,1),40)/40*(1+0.072*MIN($A123/12,5)) -> 0.51 | DR123: =SUMPRODUCT(#REF!,C123:DP123)+DQ123*12*$DP$2 -> #REF!
A124: 120 | B124: =$B$4+A124/12 -> 75 | C124: =$D$2*MAX($H124*$I124,$J124)*$F124*$G124 -> 371.1117 | D124: =IF($H124*$I124>$J124,$H$3,$J$3) -> defer | E124: =$C$2+$A124/12 -> 25 | F124: =IF($C$2+$A124/12>=10,1,0) -> 1 | G124: =IF($B124<75,IF($E$2<=$F$2,1,0),IF($E$2<=$G$2,1,0)) -> 1 | H124: =1/40*MIN(MAX(FLOOR(FLOOR($C$2,1)+MIN($A124/12,5),1),10),40) -> 0.5 | I124: =(1+0.072*(MIN($A124/12,5)-FLOOR(MIN($A124/12,5),1))) -> 1 | J124: =MIN(FLOOR($C$2,1),40)/40*(1+0.072*MIN($A124/12,5)) -> 0.51 | L124: * 1.10 will be rewarded when k = 120 from the annuity table (not u) | DR124: =SUMPRODUCT(#REF!,C124:DP124)+DQ124*12*$DP$2 -> #REF!

Sheet Annuity (Revised)
D1: mu_75 | E1: A_75 | F1: a_75 | G1: (UDD) | H1: (WH3) | J1: Interest | K1: i_12 | L1: d | M1: d_12
D2: ='Life Table'!E13 -> 0.028389182 | E2: ='Life Table'!F13 -> 0.70222735 | F2: ='Life Table'!G13 -> 10.223528 | G2: ='Life Table'!H13 -> 9.7610048 | H2: ='Life Table'!I13 -> 9.7603988 | J2: =Calculations!B6 -> 0.03 | K2: =12*((1+J2)^(1/12)-1) -> 0.029595237 | L2: =1-1/(1+J2) -> 0.029126214 | M2: =(1-(1+J2)^(-1/12))*12 -> 0.029522427
B3: k | D3: 0 | E3: 1 | F3: 2 | G3: 3 | H3: 4 | I3: 5 | J3: 6 | K3: 7 | L3: 8 | M3: 9 | N3: 10 | O3: 11 | P3: 12 | Q3: 13 | R3: 14 | S3: 15 | T3: 16 | U3: 17 | V3: 18 | W3: 19 | X3: 20 | Y3: 21 | Z3: 22 | AA3: 23 | AB3: 24 | AC3: 25 | AD3: 26 | AE3: 27 | AF3: 28 | AG3: 29 | AH3: 30 | AI3: 31 | AJ3: 32 | AK3: 33 | AL3: 34 | AM3: 35 | AN3: 36 | AO3: 37 | AP3: 38 | AQ3: 39 | AR3: 40 | AS3: 41 | AT3: 42 | AU3: 43 | AV3: 44 | AW3: 45 | AX3: 46 | AY3: 47 | AZ3: 48 | BA3: 49 | BB3: 50 | BC3: 51 | BD3: 52 | BE3: 53 | BF3: 54 | BG3: 55 | BH3: 56 | BI3: 57 | BJ3: 58 | BK3: 59 | BL3: 60 | BM3: 61 | BN3: 62 | BO3: 63 | BP3: 64 | BQ3: 65 | BR3: 66 | BS3: 67 | BT3: 68 | BU3: 69 | BV3: 70 | BW3: 71 | BX3: 72 | BY3: 73 | BZ3: 74 | CA3: 75 | CB3: 76 | CC3: 77 | CD3: 78 | CE3: 79 | CF3: 80 | CG3: 81 | CH3: 82 | CI3: 83 | CJ3: 84 | CK3: 85 | CL3: 86 | CM3: 87 | CN3: 88 | CO3: 89 | CP3: 90 | CQ3: 91 | CR3: 92 | CS3: 93 | CT3: 94 | CU3: 95 | CV3: 96 | CW3: 97 | CX3: 98 | CY3: 99 | CZ3: 100 | DA3: 101 | DB3: 102 | DC3: 103 | DD3: 104 | DE3: 105 | DF3: 106 | DG3: 107 | DH3: 108 | DI3: 109 | DJ3: 110 | DK3: 111 | DL3: 112 | DM3: 113 | DN3: 114 | DO3: 115 | DP3: 116 | DQ3: 117 | DR3: 118 | DS3: 119 | DT3: 120
B4: k/12_p_65 | D4: {=INDEX('Life Table'!$L$3:$BF$71,1,1+FLOOR(D3/12,1))*(1-(D3/12-FLOOR(D3/12,1))*INDEX('Life Table'!$D$3:$D$71,1+FLOOR(D3/12,1)))} -> 1 | E4: {=INDEX('Life Table'!$L$3:$BF$71,1,1+FLOOR(E3/12,1))*(1-(E3/12-FLOOR(E3/12,1))*INDEX('Life Table'!$D$3:$D$71,1+FLOOR(E3/12,1)))} -> 0.9990535 | F4: {=INDEX('Life Table'!$L$3:$BF$71,1,1+FLOOR(F3/12,1))*(1-(F3/12-FLOOR(F3/12,1))*INDEX('Life Table'!$D$3:$D$71,1+FLOOR(F3/12,1)))} -> 0.998107 | G4: {=INDEX('Life Table'!$L$3:$BF$71,1,1+FLOOR(G3/12,1))*(1-(G3/12-FLOOR(G3/12,1))*INDEX('Life Table'!$D$3:$D$71,1+FLOOR(G3/12,1)))} -> 0.9971605 | H4: {=INDEX('Life Table'!$L$3:$BF$71,1,1+FLOOR(H3/12,1))*(1-(H3/12-FLOOR(H3/12,1))*INDEX('Life Table'!$D$3:$D$71,1+FLOOR(H3/12,1)))} -> 0.996214 | I4: {=INDEX('Life Table'!$L$3:$BF$71,1,1+FLOOR(I3/12,1))*(1-(I3/12-FLOOR(I3/12,1))*INDEX('Life Table'!$D$3:$D$71,1+FLOOR(I3/12,1)))} -> 0.9952675 | J4: {=INDEX('Life Table'!$L$3:$BF$71,1,1+FLOOR(J3/12,1))*(1-(J3/12-FLOOR(J3/12,1))*INDEX('Life Table'!$D$3:$D$71,1+FLOOR(J3/12,1)))} -> 0.994321 | K4: {=INDEX('Life Table'!$L$3:$BF$71,1,1+FLOOR(K3/12,1))*(1-(K3/12-FLOOR(K3/12,1))*INDEX('Life Table'!$D$3:$D$71,1+FLOOR(K3/12,1)))} -> 0.9933745 | ... DT4: {=INDEX('Life Table'!$L$3:$BF$71,1,1+FLOOR(DT3/12,1))*(1-(DT3/12-FLOOR(DT3/12,1))*INDEX('Life Table'!$D$3:$D$71,1+FLOOR(DT3/12,1)))} -> 0.83444024
B5: k/12_E_65 | D5: =D4/(1+$K$2/12)^D3 -> 1 | E5: =E4/(1+$K$2/12)^E3 -> 0.99659563 | F5: =F4/(1+$K$2/12)^F3 -> 0.99320195 | G5: =G4/(1+$K$2/12)^G3 -> 0.98981894 | H5: =H4/(1+$K$2/12)^H3 -> 0.98644657 | I5: =I4/(1+$K$2/12)^I3 -> 0.98308479 | J5: =J4/(1+$K$2/12)^J3 -> 0.97973359 | K5: =K4/(1+$K$2/12)^K3 -> 0.97639293 | ... DT5: =DT4/(1+$K$2/12)^DT3 -> 0.6209019
B6: Received Age | D6: 65 | E6: =$D$6+E3/12 -> 65.083333 | F6: =$D$6+F3/12 -> 65.166667 | G6: =$D$6+G3/12 -> 65.25 | H6: =$D$6+H3/12 -> 65.333333 | I6: =$D$6+I3/12 -> 65.416667 | J6: =$D$6+J3/12 -> 65.5 | K6: =$D$6+K3/12 -> 65.583333 | L6: =$D$6+L3/12 -> 65.666667 | ... DT6: =$D$6+DT3/12 -> 75
A7: u | B7: Deferred Age | C7: PV
A8: 0 | B8: =65 -> 65 | C8: =SUMPRODUCT($D$5:$DS$5,D8:DS8)+DT8*12*$G$2 -> 61623.917 | D8: ='Payments (Revised)'!$C4*IF(D$6<$B8,0,1)*IF(D$6>=75,1.1,1) -> 272.87625 | E8: ='Payments (Revised)'!$C4*IF(E$6<$B8,0,1)*IF(E$6>=75,1.1,1) -> 272.87625 | F8: ='Payments (Revised)'!$C4*IF(F$6<$B8,0,1)*IF(F$6>=75,1.1,1) -> 272.87625 | G8: ='Payments (Revised)'!$C4*IF(G$6<$B8,0,1)*IF(G$6>=75,1.1,1) -> 272.87625 | H8: ='Payments (Revised)'!$C4*IF(H$6<$B8,0,1)*IF(H$6>=75,1.1,1) -> 272.87625 | I8: ='Payments (Revised)'!$C4*IF(I$6<$B8,0,1)*IF(I$6>=75,1.1,1) -> 272.87625 | J8: ='Payments (Revised)'!$C4*IF(J$6<$B8,0,1)*IF(J$6>=75,1.1,1) -> 272.87625 | K8: ='Payments (Revised)'!$C4*IF(K$6<$B8,0,1)*IF(K$6>=75,1.1,1) -> 272.87625 | ... DT8: ='Payments (Revised)'!$C4*IF(DT$6<$B8,0,1)*IF(DT$6>=75,1.1,1) -> 300.16388
A9: 1 | B9: =$B$8+A9/12 -> 65.083333 | C9: =SUMPRODUCT($D$5:$DS$5,D9:DS9)+DT9*12*$G$2 -> 61719.147 | D9: ='Payments (Revised)'!$C5*IF(D$6<$B9,0,1)*IF(D$6>=75,1.1,1) -> 0 | E9: ='Payments (Revised)'!$C5*IF(E$6<$B9,0,1)*IF(E$6>=75,1.1,1) -> 274.51351 | F9: ='Payments (Revised)'!$C5*IF(F$6<$B9,0,1)*IF(F$6>=75,1.1,1) -> 274.51351 | G9: ='Payments (Revised)'!$C5*IF(G$6<$B9,0,1)*IF(G$6>=75,1.1,1) -> 274.51351 | H9: ='Payments (Revised)'!$C5*IF(H$6<$B9,0,1)*IF(H$6>=75,1.1,1) -> 274.51351 | I9: ='Payments (Revised)'!$C5*IF(I$6<$B9,0,1)*IF(I$6>=75,1.1,1) -> 274.51351 | J9: ='Payments (Revised)'!$C5*IF(J$6<$B9,0,1)*IF(J$6>=75,1.1,1) -> 274.51351 | K9: ='Payments (Revised)'!$C5*IF(K$6<$B9,0,1)*IF(K$6>=75,1.1,1) -> 274.51351 | ... DT9: ='Payments (Revised)'!$C5*IF(DT$6<$B9,0,1)*IF(DT$6>=75,1.1,1) -> 301.96486
A10: 2 | B10: =$B$8+A10/12 -> 65.166667 | C10: =SUMPRODUCT($D$5:$DS$5,D10:DS10)+DT10*12*$G$2 -> 61812.043 | D10: ='Payments (Revised)'!$C6*IF(D$6<$B10,0,1)*IF(D$6>=75,1.1,1) -> 0 | E10: ='Payments (Revised)'!$C6*IF(E$6<$B10,0,1)*IF(E$6>=75,1.1,1) -> 0 | F10: ='Payments (Revised)'!$C6*IF(F$6<$B10,0,1)*IF(F$6>=75,1.1,1) -> 276.15076 | G10: ='Payments (Revised)'!$C6*IF(G$6<$B10,0,1)*IF(G$6>=75,1.1,1) -> 276.15076 | H10: ='Payments (Revised)'!$C6*IF(H$6<$B10,0,1)*IF(H$6>=75,1.1,1) -> 276.15076 | I10: ='Payments (Revised)'!$C6*IF(I$6<$B10,0,1)*IF(I$6>=75,1.1,1) -> 276.15076 | J10: ='Payments (Revised)'!$C6*IF(J$6<$B10,0,1)*IF(J$6>=75,1.1,1) -> 276.15076 | K10: ='Payments (Revised)'!$C6*IF(K$6<$B10,0,1)*IF(K$6>=75,1.1,1) -> 276.15076 | ... DT10: ='Payments (Revised)'!$C6*IF(DT$6<$B10,0,1)*IF(DT$6>=75,1.1,1) -> 303.76584
A11: 3 | B11: =$B$8+A11/12 -> 65.25 | C11: =SUMPRODUCT($D$5:$DS$5,D11:DS11)+DT11*12*$G$2 -> 61902.617 | D11: ='Payments (Revised)'!$C7*IF(D$6<$B11,0,1)*IF(D$6>=75,1.1,1) -> 0 | E11: ='Payments (Revised)'!$C7*IF(E$6<$B11,0,1)*IF(E$6>=75,1.1,1) -> 0 | F11: ='Payments (Revised)'!$C7*IF(F$6<$B11,0,1)*IF(F$6>=75,1.1,1) -> 0 | G11: ='Payments (Revised)'!$C7*IF(G$6<$B11,0,1)*IF(G$6>=75,1.1,1) -> 277.78802 | H11: ='Payments (Revised)'!$C7*IF(H$6<$B11,0,1)*IF(H$6>=75,1.1,1) -> 277.78802 | I11: ='Payments (Revised)'!$C7*IF(I$6<$B11,0,1)*IF(I$6>=75,1.1,1) -> 277.78802 | J11: ='Payments (Revised)'!$C7*IF(J$6<$B11,0,1)*IF(J$6>=75,1.1,1) -> 277.78802 | K11: ='Payments (Revised)'!$C7*IF(K$6<$B11,0,1)*IF(K$6>=75,1.1,1) -> 277.78802 | ... DT11: ='Payments (Revised)'!$C7*IF(DT$6<$B11,0,1)*IF(DT$6>=75,1.1,1) -> 305.56682
A12: 4 | B12: =$B$8+A12/12 -> 65.333333 | C12: =SUMPRODUCT($D$5:$DS$5,D12:DS12)+DT12*12*$G$2 -> 61990.885 | D12: ='Payments (Revised)'!$C8*IF(D$6<$B12,0,1)*IF(D$6>=75,1.1,1) -> 0 | E12: ='Payments (Revised)'!$C8*IF(E$6<$B12,0,1)*IF(E$6>=75,1.1,1) -> 0 | F12: ='Payments (Revised)'!$C8*IF(F$6<$B12,0,1)*IF(F$6>=75,1.1,1) -> 0 | G12: ='Payments (Revised)'!$C8*IF(G$6<$B12,0,1)*IF(G$6>=75,1.1,1) -> 0 | H12: ='Payments (Revised)'!$C8*IF(H$6<$B12,0,1)*IF(H$6>=75,1.1,1) -> 279.42528 | I12: ='Payments (Revised)'!$C8*IF(I$6<$B12,0,1)*IF(I$6>=75,1.1,1) -> 279.42528 | J12: ='Payments (Revised)'!$C8*IF(J$6<$B12,0,1)*IF(J$6>=75,1.1,1) -> 279.42528 | K12: ='Payments (Revised)'!$C8*IF(K$6<$B12,0,1)*IF(K$6>=75,1.1,1) -> 279.42528 | ... DT12: ='Payments (Revised)'!$C8*IF(DT$6<$B12,0,1)*IF(DT$6>=75,1.1,1) -> 307.36781
A13: 5 | B13: =$B$8+A13/12 -> 65.416667 | C13: =SUMPRODUCT($D$5:$DS$5,D13:DS13)+DT13*12*$G$2 -> 62076.86 | D13: ='Payments (Revised)'!$C9*IF(D$6<$B13,0,1)*IF(D$6>=75,1.1,1) -> 0 | E13: ='Payments (Revised)'!$C9*IF(E$6<$B13,0,1)*IF(E$6>=75,1.1,1) -> 0 | F13: ='Payments (Revised)'!$C9*IF(F$6<$B13,0,1)*IF(F$6>=75,1.1,1) -> 0 | G13: ='Payments (Revised)'!$C9*IF(G$6<$B13,0,1)*IF(G$6>=75,1.1,1) -> 0 | H13: ='Payments (Revised)'!$C9*IF(H$6<$B13,0,1)*IF(H$6>=75,1.1,1) -> 0 | I13: ='Payments (Revised)'!$C9*IF(I$6<$B13,0,1)*IF(I$6>=75,1.1,1) -> 281.06254 | J13: ='Payments (Revised)'!$C9*IF(J$6<$B13,0,1)*IF(J$6>=75,1.1,1) -> 281.06254 | K13: ='Payments (Revised)'!$C9*IF(K$6<$B13,0,1)*IF(K$6>=75,1.1,1) -> 281.06254 | ... DT13: ='Payments (Revised)'!$C9*IF(DT$6<$B13,0,1)*IF(DT$6>=75,1.1,1) -> 309.16879
A14: 6 | B14: =$B$8+A14/12 -> 65.5 | C14: =SUMPRODUCT($D$5:$DS$5,D14:DS14)+DT14*12*$G$2 -> 62160.555 | D14: ='Payments (Revised)'!$C10*IF(D$6<$B14,0,1)*IF(D$6>=75,1.1,1) -> 0 | E14: ='Payments (Revised)'!$C10*IF(E$6<$B14,0,1)*IF(E$6>=75,1.1,1) -> 0 | F14: ='Payments (Revised)'!$C10*IF(F$6<$B14,0,1)*IF(F$6>=75,1.1,1) -> 0 | G14: ='Payments (Revised)'!$C10*IF(G$6<$B14,0,1)*IF(G$6>=75,1.1,1) -> 0 | H14: ='Payments (Revised)'!$C10*IF(H$6<$B14,0,1)*IF(H$6>=75,1.1,1) -> 0 | I14: ='Payments (Revised)'!$C10*IF(I$6<$B14,0,1)*IF(I$6>=75,1.1,1) -> 0 | J14: ='Payments (Revised)'!$C10*IF(J$6<$B14,0,1)*IF(J$6>=75,1.1,1) -> 282.69979 | K14: ='Payments (Revised)'!$C10*IF(K$6<$B14,0,1)*IF(K$6>=75,1.1,1) -> 282.69979 | ... DT14: ='Payments (Revised)'!$C10*IF(DT$6<$B14,0,1)*IF(DT$6>=75,1.1,1) -> 310.96977
A15: 7 | B15: =$B$8+A15/12 -> 65.583333 | C15: =SUMPRODUCT($D$5:$DS$5,D15:DS15)+DT15*12*$G$2 -> 62241.984 | D15: ='Payments (Revised)'!$C11*IF(D$6<$B15,0,1)*IF(D$6>=75,1.1,1) -> 0 | E15: ='Payments (Revised)'!$C11*IF(E$6<$B15,0,1)*IF(E$6>=75,1.1,1) -> 0 | F15: ='Payments (Revised)'!$C11*IF(F$6<$B15,0,1)*IF(F$6>=75,1.1,1) -> 0 | G15: ='Payments (Revised)'!$C11*IF(G$6<$B15,0,1)*IF(G$6>=75,1.1,1) -> 0 | H15: ='Payments (Revised)'!$C11*IF(H$6<$B15,0,1)*IF(H$6>=75,1.1,1) -> 0 | I15: ='Payments (Revised)'!$C11*IF(I$6<$B15,0,1)*IF(I$6>=75,1.1,1) -> 0 | J15: ='Payments (Revised)'!$C11*IF(J$6<$B15,0,1)*IF(J$6>=75,1.1,1) -> 0 | K15: ='Payments (Revised)'!$C11*IF(K$6<$B15,0,1)*IF(K$6>=75,1.1,1) -> 284.33705 | ... DT15: ='Payments (Revised)'!$C11*IF(DT$6<$B15,0,1)*IF(DT$6>=75,1.1,1) -> 312.77076
A16: 8 | B16: =$B$8+A16/12 -> 65.666667 | C16: =SUMPRODUCT($D$5:$DS$5,D16:DS16)+DT16*12*$G$2 -> 62321.16 | D16: ='Payments (Revised)'!$C12*IF(D$6<$B16,0,1)*IF(D$6>=75,1.1,1) -> 0 | E16: ='Payments (Revised)'!$C12*IF(E$6<$B16,0,1)*IF(E$6>=75,1.1,1) -> 0 | F16: ='Payments (Revised)'!$C12*IF(F$6<$B16,0,1)*IF(F$6>=75,1.1,1) -> 0 | G16: ='Payments (Revised)'!$C12*IF(G$6<$B16,0,1)*IF(G$6>=75,1.1,1) -> 0 | H16: ='Payments (Revised)'!$C12*IF(H$6<$B16,0,1)*IF(H$6>=75,1.1,1) -> 0 | I16: ='Payments (Revised)'!$C12*IF(I$6<$B16,0,1)*IF(I$6>=75,1.1,1) -> 0 | J16: ='Payments (Revised)'!$C12*IF(J$6<$B16,0,1)*IF(J$6>=75,1.1,1) -> 0 | K16: ='Payments (Revised)'!$C12*IF(K$6<$B16,0,1)*IF(K$6>=75,1.1,1) -> 0 | ... DT16: ='Payments (Revised)'!$C12*IF(DT$6<$B16,0,1)*IF(DT$6>=75,1.1,1) -> 314.57174
A17: 9 | B17: =$B$8+A17/12 -> 65.75 | C17: =SUMPRODUCT($D$5:$DS$5,D17:DS17)+DT17*12*$G$2 -> 62398.096 | D17: ='Payments (Revised)'!$C13*IF(D$6<$B17,0,1)*IF(D$6>=75,1.1,1) -> 0 | E17: ='Payments (Revised)'!$C13*IF(E$6<$B17,0,1)*IF(E$6>=75,1.1,1) -> 0 | F17: ='Payments (Revised)'!$C13*IF(F$6<$B17,0,1)*IF(F$6>=75,1.1,1) -> 0 | G17: ='Payments (Revised)'!$C13*IF(G$6<$B17,0,1)*IF(G$6>=75,1.1,1) -> 0 | H17: ='Payments (Revised)'!$C13*IF(H$6<$B17,0,1)*IF(H$6>=75,1.1,1) -> 0 | I17: ='Payments (Revised)'!$C13*IF(I$6<$B17,0,1)*IF(I$6>=75,1.1,1) -> 0 | J17: ='Payments (Revised)'!$C13*IF(J$6<$B17,0,1)*IF(J$6>=75,1.1,1) -> 0 | K17: ='Payments (Revised)'!$C13*IF(K$6<$B17,0,1)*IF(K$6>=75,1.1,1) -> 0 | ... DT17: ='Payments (Revised)'!$C13*IF(DT$6<$B17,0,1)*IF(DT$6>=75,1.1,1) -> 316.37272
A18: 10 | B18: =$B$8+A18/12 -> 65.833333 | C18: =SUMPRODUCT($D$5:$DS$5,D18:DS18)+DT18*12*$G$2 -> 62472.806 | D18: ='Payments (Revised)'!$C14*IF(D$6<$B18,0,1)*IF(D$6>=75,1.1,1) -> 0 | E18: ='Payments (Revised)'!$C14*IF(E$6<$B18,0,1)*IF(E$6>=75,1.1,1) -> 0 | F18: ='Payments (Revised)'!$C14*IF(F$6<$B18,0,1)*IF(F$6>=75,1.1,1) -> 0 | G18: ='Payments (Revised)'!$C14*IF(G$6<$B18,0,1)*IF(G$6>=75,1.1,1) -> 0 | H18: ='Payments (Revised)'!$C14*IF(H$6<$B18,0,1)*IF(H$6>=75,1.1,1) -> 0 | I18: ='Payments (Revised)'!$C14*IF(I$6<$B18,0,1)*IF(I$6>=75,1.1,1) -> 0 | J18: ='Payments (Revised)'!$C14*IF(J$6<$B18,0,1)*IF(J$6>=75,1.1,1) -> 0 | K18: ='Payments (Revised)'!$C14*IF(K$6<$B18,0,1)*IF(K$6>=75,1.1,1) -> 0 | ... DT18: ='Payments (Revised)'!$C14*IF(DT$6<$B18,0,1)*IF(DT$6>=75,1.1,1) -> 318.17371
A19: 11 | B19: =$B$8+A19/12 -> 65.916667 | C19: =SUMPRODUCT($D$5:$DS$5,D19:DS19)+DT19*12*$G$2 -> 62545.304 | D19: ='Payments (Revised)'!$C15*IF(D$6<$B19,0,1)*IF(D$6>=75,1.1,1) -> 0 | E19: ='Payments (Revised)'!$C15*IF(E$6<$B19,0,1)*IF(E$6>=75,1.1,1) -> 0 | F19: ='Payments (Revised)'!$C15*IF(F$6<$B19,0,1)*IF(F$6>=75,1.1,1) -> 0 | G19: ='Payments (Revised)'!$C15*IF(G$6<$B19,0,1)*IF(G$6>=75,1.1,1) -> 0 | H19: ='Payments (Revised)'!$C15*IF(H$6<$B19,0,1)*IF(H$6>=75,1.1,1) -> 0 | I19: ='Payments (Revised)'!$C15*IF(I$6<$B19,0,1)*IF(I$6>=75,1.1,1) -> 0 | J19: ='Payments (Revised)'!$C15*IF(J$6<$B19,0,1)*IF(J$6>=75,1.1,1) -> 0 | K19: ='Payments (Revised)'!$C15*IF(K$6<$B19,0,1)*IF(K$6>=75,1.1,1) -> 0 | ... DT19: ='Payments (Revised)'!$C15*IF(DT$6<$B19,0,1)*IF(DT$6>=75,1.1,1) -> 319.97469
A20: 12 | B20: =$B$8+A20/12 -> 66 | C20: =SUMPRODUCT($D$5:$DS$5,D20:DS20)+DT20*12*$G$2 -> 62615.602 | D20: ='Payments (Revised)'!$C16*IF(D$6<$B20,0,1)*IF(D$6>=75,1.1,1) -> 0 | E20: ='Payments (Revised)'!$C16*IF(E$6<$B20,0,1)*IF(E$6>=75,1.1,1) -> 0 | F20: ='Payments (Revised)'!$C16*IF(F$6<$B20,0,1)*IF(F$6>=75,1.1,1) -> 0 | G20: ='Payments (Revised)'!$C16*IF(G$6<$B20,0,1)*IF(G$6>=75,1.1,1) -> 0 | H20: ='Payments (Revised)'!$C16*IF(H$6<$B20,0,1)*IF(H$6>=75,1.1,1) -> 0 | I20: ='Payments (Revised)'!$C16*IF(I$6<$B20,0,1)*IF(I$6>=75,1.1,1) -> 0 | J20: ='Payments (Revised)'!$C16*IF(J$6<$B20,0,1)*IF(J$6>=75,1.1,1) -> 0 | K20: ='Payments (Revised)'!$C16*IF(K$6<$B20,0,1)*IF(K$6>=75,1.1,1) -> 0 | ... DT20: ='Payments (Revised)'!$C16*IF(DT$6<$B20,0,1)*IF(DT$6>=75,1.1,1) -> 321.77567
... A128: 120 | B128: =$B$8+A128/12 -> 75 | C128: =SUMPRODUCT($D$5:$DS$5,D128:DS128)+DT128*12*$G$2 -> 47815.985 | D128: ='Payments (Revised)'!$C124*IF(D$6<$B128,0,1)*IF(D$6>=75,1.1,1) -> 0 | E128: ='Payments (Revised)'!$C124*IF(E$6<$B128,0,1)*IF(E$6>=75,1.1,1) -> 0 | F128: ='Payments (Revised)'!$C124*IF(F$6<$B128,0,1)*IF(F$6>=75,1.1,1) -> 0 | G128: ='Payments (Revised)'!$C124*IF(G$6<$B128,0,1)*IF(G$6>=75,1.1,1) -> 0 | H128: ='Payments (Revised)'!$C124*IF(H$6<$B128,0,1)*IF(H$6>=75,1.1,1) -> 0 | I128: ='Payments (Revised)'!$C124*IF(I$6<$B128,0,1)*IF(I$6>=75,1.1,1) -> 0 | J128: ='Payments (Revised)'!$C124*IF(J$6<$B128,0,1)*IF(J$6>=75,1.1,1) -> 0 | K128: ='Payments (Revised)'!$C124*IF(K$6<$B128,0,1)*IF(K$6>=75,1.1,1) -> 0 | ... DT128: ='Payments (Revised)'!$C124*IF(DT$6<$B128,0,1)*IF(DT$6>=75,1.1,1) -> 408.22287

Sheet Life Table
A1: ='Cover Page'!B3 -> Male | C1: x | D1: q_x | E1: mu_x | F1: A_x | G1: a_x | H1: a(12)_x (UDD) | I1: a(12)_x (WH3) | K1: npx | L1: 0 | M1: 1 | N1: 2 | O1: 3 | P1: 4 | Q1: 5 | R1: 6 | S1: 7 | T1: 8 | U1: 9 | V1: 10 | W1: 11 | X1: 12 | Y1: 13 | Z1: 14 | AA1: 15 | AB1: 16 | AC1: 17 | AD1: 18 | AE1: 19 | AF1: 20 | AG1: 21 | AH1: 22 | AI1: 23 | AJ1: 24 | AK1: 25 | AL1: 26 | AM1: 27 | AN1: 28 | AO1: 29 | AP1: 30 | AQ1: 31 | AR1: 32 | AS1: 33 | AT1: 34 | AU1: 35 | AV1: 36 | AW1: 37 | AX1: 38 | AY1: 39 | AZ1: 40 | BA1: 41 | BB1: 42 | BC1: 43 | BD1: 44 | BE1: 45 | BF1: 46
C2: 64 | D2: {=_xlfn.IFS($A$1="Male",Data!O4,$A$1="Female",Data!W4,$A$1="Unspecified",Data!G4)} -> 0.010388 | L2: 1 | M2: {=IFERROR(L2*(1-INDEX($D2:$D$71,M$1)),0)} -> 0.989612 | N2: {=IFERROR(M2*(1-INDEX($D2:$D$71,N$1)),0)} -> 0.97837199 | O2: {=IFERROR(N2*(1-INDEX($D2:$D$71,O$1)),0)} -> 0.96620495 | P2: {=IFERROR(O2*(1-INDEX($D2:$D$71,P$1)),0)} -> 0.95303751 | Q2: {=IFERROR(P2*(1-INDEX($D2:$D$71,Q$1)),0)} -> 0.93879151 | R2: {=IFERROR(Q2*(1-INDEX($D2:$D$71,R$1)),0)} -> 0.92338218 | S2: {=IFERROR(R2*(1-INDEX($D2:$D$71,S$1)),0)} -> 0.90672068 | T2: {=IFERROR(S2*(1-INDEX($D2:$D$71,T$1)),0)} -> 0.88872046 | ... BF2: {=IFERROR(BE2*(1-INDEX($D2:$D$71,BF$1)),0)} -> 3.9471012e-05
A3: i | C3: 65 | D3: {=_xlfn.IFS($A$1="Male",Data!O5,$A$1="Female",Data!W5,$A$1="Unspecified",Data!G5)} -> 0.011358 | E3: =-1/2*(LN(1-D2)+LN(1-D3)) -> 0.010932663 | F3: {=SUMPRODUCT($A$6^(($L$1:$BD$1)+1),(L3:BD3),(TRANSPOSE(D3:D47)))} -> 0.57460207 | G3: {=SUMPRODUCT($A$6^($L$1:$BF$1),L3:BF3)} -> 14.604977 | H3: =(1-$A$4/$A$8*F3)/$A$12 -> 14.143123 | I3: =G3-(12-1)/2/12-(12^2-1)/12/12^2*(E3+LN(1+$A$4)) -> 14.143293 | L3: 1 | M3: {=IFERROR(L3*(1-INDEX($D3:$D$71,M$1)),0)} -> 0.988642 | N3: {=IFERROR(M3*(1-INDEX($D3:$D$71,N$1)),0)} -> 0.97634725 | O3: {=IFERROR(N3*(1-INDEX($D3:$D$71,O$1)),0)} -> 0.96304159 | P3: {=IFERROR(O3*(1-INDEX($D3:$D$71,P$1)),0)} -> 0.94864604 | Q3: {=IFERROR(P3*(1-INDEX($D3:$D$71,Q$1)),0)} -> 0.93307497 | R3: {=IFERROR(Q3*(1-INDEX($D3:$D$71,R$1)),0)} -> 0.91623856 | S3: {=IFERROR(R3*(1-INDEX($D3:$D$71,S$1)),0)} -> 0.89804939 | T3: {=IFERROR(S3*(1-INDEX($D3:$D$71,T$1)),0)} -> 0.87841444 | ... BF3: {=IFERROR(BE3*(1-INDEX($D3:$D$71,BF$1)),0)} -> 0
A4: =Payments!K2 -> 0.03 | C4: 66 | D4: {=_xlfn.IFS($A$1="Male",Data!O6,$A$1="Female",Data!W6,$A$1="Unspecified",Data!G6)} -> 0.012436 | E4: =-1/2*(LN(1-D3)+LN(1-D4)) -> 0.011968484 | F4: {=SUMPRODUCT($A$6^(($L$1:$BD$1)+1),(L4:BD4),(TRANSPOSE(D4:D48)))} -> 0.58716166 | G4: {=SUMPRODUCT($A$6^($L$1:$BF$1),L4:BF4)} -> 14.174116 | H4: =(1-$A$4/$A$8*F4)/$A$12 -> 13.711879 | I4: =G4-(12-1)/2/12-(12^2-1)/12/12^2*(E4+LN(1+$A$4)) -> 13.712346 | L4: 1 | M4: {=IFERROR(L4*(1-INDEX($D4:$D$71,M$1)),0)} -> 0.987564 | N4: {=IFERROR(M4*(1-INDEX($D4:$D$71,N$1)),0)} -> 0.97410548 | O4: {=IFERROR(N4*(1-INDEX($D4:$D$71,O$1)),0)} -> 0.95954455 | P4: {=IFERROR(O4*(1-INDEX($D4:$D$71,P$1)),0)} -> 0.94379458 | Q4: {=IFERROR(P4*(1-INDEX($D4:$D$71,Q$1)),0)} -> 0.92676476 | R4: {=IFERROR(Q4*(1-INDEX($D4:$D$71,R$1)),0)} -> 0.90836662 | S4: {=IFERROR(R4*(1-INDEX($D4:$D$71,S$1)),0)} -> 0.88850609 | T4: {=IFERROR(S4*(1-INDEX($D4:$D$71,T$1)),0)} -> 0.86708954 | ... BF4: {=IFERROR(BE4*(1-INDEX($D4:$D$71,BF$1)),0)} -> 0
A5: v | C5: 67 | D5: {=_xlfn.IFS($A$1="Male",Data!O7,$A$1="Female",Data!W7,$A$1="Unspecified",Data!G7)} -> 0.013628 | E5: =-1/2*(LN(1-D4)+LN(1-D5)) -> 0.013117844 | F5: {=SUMPRODUCT($A$6^(($L$1:$BD$1)+1),(L5:BD5),(TRANSPOSE(D5:D49)))} -> 0.59979962 | G5: {=SUMPRODUCT($A$6^($L$1:$BF$1),L5:BF5)} -> 13.740213 | H5: =(1-$A$4/$A$8*F5)/$A$12 -> 13.277945 | I5: =G5-(12-1)/2/12-(12^2-1)/12/12^2*(E5+LN(1+$A$4)) -> 13.278348 | L5: 1 | M5: {=IFERROR(L5*(1-INDEX($D5:$D$71,M$1)),0)} -> 0.986372 | N5: {=IFERROR(M5*(1-INDEX($D5:$D$71,N$1)),0)} -> 0.97162771 | O5: {=IFERROR(N5*(1-INDEX($D5:$D$71,O$1)),0)} -> 0.95567941 | P5: {=IFERROR(O5*(1-INDEX($D5:$D$71,P$1)),0)} -> 0.93843513 | Q5: {=IFERROR(P5*(1-INDEX($D5:$D$71,Q$1)),0)} -> 0.91980532 | R5: {=IFERROR(Q5*(1-INDEX($D5:$D$71,R$1)),0)} -> 0.8996947 | S5: {=IFERROR(R5*(1-INDEX($D5:$D$71,S$1)),0)} -> 0.87800846 | T5: {=IFERROR(S5*(1-INDEX($D5:$D$71,T$1)),0)} -> 0.85465519 | ... BF5: {=IFERROR(BE5*(1-INDEX($D5:$D$71,BF$1)),0)} -> 0
A6: =(1+A4)^-1 -> 0.97087379 | C6: 68 | D6: {=_xlfn.IFS($A$1="Male",Data!O8,$A$1="Female",Data!W8,$A$1="Unspecified",Data!G8)} -> 0.014948 | E6: =-1/2*(LN(1-D5)+LN(1-D6)) -> 0.01439128 | F6: {=SUMPRODUCT($A$6^(($L$1:$BD$1)+1),(L6:BD6),(TRANSPOSE(D6:D50)))} -> 0.61251294 | G6: {=SUMPRODUCT($A$6^($L$1:$BF$1),L6:BF6)} -> 13.303722 | H6: =(1-$A$4/$A$8*F6)/$A$12 -> 12.841422 | I6: =G6-(12-1)/2/12-(12^2-1)/12/12^2*(E6+LN(1+$A$4)) -> 12.841752 | L6: 1 | M6: {=IFERROR(L6*(1-INDEX($D6:$D$71,M$1)),0)} -> 0.985052 | N6: {=IFERROR(M6*(1-INDEX($D6:$D$71,N$1)),0)} -> 0.96888336 | O6: {=IFERROR(N6*(1-INDEX($D6:$D$71,O$1)),0)} -> 0.95140083 | P6: {=IFERROR(O6*(1-INDEX($D6:$D$71,P$1)),0)} -> 0.93251362 | Q6: {=IFERROR(P6*(1-INDEX($D6:$D$71,Q$1)),0)} -> 0.91212514 | R6: {=IFERROR(Q6*(1-INDEX($D6:$D$71,R$1)),0)} -> 0.89013927 | S6: {=IFERROR(R6*(1-INDEX($D6:$D$71,S$1)),0)} -> 0.86646335 | T6: {=IFERROR(S6*(1-INDEX($D6:$D$71,T$1)),0)} -> 0.84100666 | ... BF6: {=IFERROR(BE6*(1-INDEX($D6:$D$71,BF$1)),0)} -> 0
A7: i_12 | C7: 69 | D7: {=_xlfn.IFS($A$1="Male",Data!O9,$A$1="Female",Data!W9,$A$1="Unspecified",Data!G9)} -> 0.016414 | E7: =-1/2*(LN(1-D6)+LN(1-D7)) -> 0.015805525 | F7: {=SUMPRODUCT($A$6^(($L$1:$BD$1)+1),(L7:BD7),(TRANSPOSE(D7:D51)))} -> 0.62528712 | G7: {=SUMPRODUCT($A$6^($L$1:$BF$1),L7:BF7)} -> 12.865142 | H7: =(1-$A$4/$A$8*F7)/$A$12 -> 12.402811 | I7: =G7-(12-1)/2/12-(12^2-1)/12/12^2*(E7+LN(1+$A$4)) -> 12.403055 | L7: 1 | M7: {=IFERROR(L7*(1-INDEX($D7:$D$71,M$1)),0)} -> 0.983586 | N7: {=IFERROR(M7*(1-INDEX($D7:$D$71,N$1)),0)} -> 0.96583817 | O7: {=IFERROR(N7*(1-INDEX($D7:$D$71,O$1)),0)} -> 0.94666435 | P7: {=IFERROR(O7*(1-INDEX($D7:$D$71,P$1)),0)} -> 0.92596649 | Q7: {=IFERROR(P7*(1-INDEX($D7:$D$71,Q$1)),0)} -> 0.90364699 | R7: {=IFERROR(Q7*(1-INDEX($D7:$D$71,R$1)),0)} -> 0.87961179 | S7: {=IFERROR(R7*(1-INDEX($D7:$D$71,S$1)),0)} -> 0.85376879 | T7: {=IFERROR(S7*(1-INDEX($D7:$D$71,T$1)),0)} -> 0.82603155 | ... BF7: {=IFERROR(BE7*(1-INDEX($D7:$D$71,BF$1)),0)} -> 0
A8: =12*((1+A4)^(1/12)-1) -> 0.029595237 | C8: 70 | D8: {=_xlfn.IFS($A$1="Male",Data!O10,$A$1="Female",Data!W10,$A$1="Unspecified",Data!G10)} -> 0.018044 | E8: =-1/2*(LN(1-D7)+LN(1-D8)) -> 0.01737949 | F8: {=SUMPRODUCT($A$6^(($L$1:$BD$1)+1),(L8:BD8),(TRANSPOSE(D8:D52)))} -> 0.6381056 | G8: {=SUMPRODUCT($A$6^($L$1:$BF$1),L8:BF8)} -> 12.425041 | H8: =(1-$A$4/$A$8*F8)/$A$12 -> 11.962678 | I8: =G8-(12-1)/2/12-(12^2-1)/12/12^2*(E8+LN(1+$A$4)) -> 11.962823 | L8: 1 | M8: {=IFERROR(L8*(1-INDEX($D8:$D$71,M$1)),0)} -> 0.981956 | N8: {=IFERROR(M8*(1-INDEX($D8:$D$71,N$1)),0)} -> 0.96246221 | O8: {=IFERROR(N8*(1-INDEX($D8:$D$71,O$1)),0)} -> 0.94141894 | P8: {=IFERROR(O8*(1-INDEX($D8:$D$71,P$1)),0)} -> 0.91872697 | Q8: {=IFERROR(P8*(1-INDEX($D8:$D$71,Q$1)),0)} -> 0.89429067 | R8: {=IFERROR(Q8*(1-INDEX($D8:$D$71,R$1)),0)} -> 0.86801641 | S8: {=IFERROR(R8*(1-INDEX($D8:$D$71,S$1)),0)} -> 0.8398163 | T8: {=IFERROR(S8*(1-INDEX($D8:$D$71,T$1)),0)} -> 0.80961818 | ... BF8: {=IFERROR(BE8*(1-INDEX($D8:$D$71,BF$1)),0)} -> 0
A9: d | C9: 71 | D9: {=_xlfn.IFS($A$1="Male",Data!O11,$A$1="Female",Data!W11,$A$1="Unspecified",Data!G11)} -> 0.019852 | E9: =-1/2*(LN(1-D8)+LN(1-D9)) -> 0.019130238 | F9: {=SUMPRODUCT($A$6^(($L$1:$BD$1)+1),(L9:BD9),(TRANSPOSE(D9:D53)))} -> 0.65095052 | G9: {=SUMPRODUCT($A$6^($L$1:$BF$1),L9:BF9)} -> 11.984032 | H9: =(1-$A$4/$A$8*F9)/$A$12 -> 11.521637 | I9: =G9-(12-1)/2/12-(12^2-1)/12/12^2*(E9+LN(1+$A$4)) -> 11.52167 | L9: 1 | M9: {=IFERROR(L9*(1-INDEX($D9:$D$71,M$1)),0)} -> 0.980148 | N9: {=IFERROR(M9*(1-INDEX($D9:$D$71,N$1)),0)} -> 0.95871804 | O9: {=IFERROR(N9*(1-INDEX($D9:$D$71,O$1)),0)} -> 0.9356091 | P9: {=IFERROR(O9*(1-INDEX($D9:$D$71,P$1)),0)} -> 0.91072377 | Q9: {=IFERROR(P9*(1-INDEX($D9:$D$71,Q$1)),0)} -> 0.88396671 | R9: {=IFERROR(Q9*(1-INDEX($D9:$D$71,R$1)),0)} -> 0.8552484 | S9: {=IFERROR(R9*(1-INDEX($D9:$D$71,S$1)),0)} -> 0.82449538 | T9: {=IFERROR(S9*(1-INDEX($D9:$D$71,T$1)),0)} -> 0.79164748 | ... BF9: {=IFERROR(BE9*(1-INDEX($D9:$D$71,BF$1)),0)} -> 0
A10: =1-1/(1+A4) -> 0.029126214 | C10: 72 | D10: {=_xlfn.IFS($A$1="Male",Data!O12,$A$1="Female",Data!W12,$A$1="Unspecified",Data!G12)} -> 0.021864 | E10: =-1/2*(LN(1-D9)+LN(1-D10)) -> 0.021079129 | F10: {=SUMPRODUCT($A$6^(($L$1:$BD$1)+1),(L10:BD10),(TRANSPOSE(D10:D54)))} -> 0.66380489 | G10: {=SUMPRODUCT($A$6^($L$1:$BF$1),L10:BF10)} -> 11.542699 | H10: =(1-$A$4/$A$8*F10)/$A$12 -> 11.080272 | I10: =G10-(12-1)/2/12-(12^2-1)/12/12^2*(E10+LN(1+$A$4)) -> 11.080175 | L10: 1 | M10: {=IFERROR(L10*(1-INDEX($D10:$D$71,M$1)),0)} -> 0.978136 | N10: {=IFERROR(M10*(1-INDEX($D10:$D$71,N$1)),0)} -> 0.95455901 | O10: {=IFERROR(N10*(1-INDEX($D10:$D$71,O$1)),0)} -> 0.92916965 | P10: {=IFERROR(O10*(1-INDEX($D10:$D$71,P$1)),0)} -> 0.90187065 | Q10: {=IFERROR(P10*(1-INDEX($D10:$D$71,Q$1)),0)} -> 0.87257067 | R10: {=IFERROR(Q10*(1-INDEX($D10:$D$71,R$1)),0)} -> 0.84119478 | S10: {=IFERROR(R10*(1-INDEX($D10:$D$71,S$1)),0)} -> 0.80768158 | T10: {=IFERROR(S10*(1-INDEX($D10:$D$71,T$1)),0)} -> 0.77199497 | ... BF10: {=IFERROR(BE10*(1-INDEX($D10:$D$71,BF$1)),0)} -> 0
A11: d_12 | C11: 73 | D11: {=_xlfn.IFS($A$1="Male",Data!O13,$A$1="Female",Data!W13,$A$1="Unspecified",Data!G13)} -> 0.024104 | E11: =-1/2*(LN(1-D10)+LN(1-D11)) -> 0.023252907 | F11: {=SUMPRODUCT($A$6^(($L$1:$BD$1)+1),(L11:BD11),(TRANSPOSE(D11:D55)))} -> 0.67664929 | G11: {=SUMPRODUCT($A$6^($L$1:$BF$1),L11:BF11)} -> 11.101708 | H11: =(1-$A$4/$A$8*F11)/$A$12 -> 10.639248 | I11: =G11-(12-1)/2/12-(12^2-1)/12/12^2*(E11+LN(1+$A$4)) -> 10.639004 | L11: 1 | M11: {=IFERROR(L11*(1-INDEX($D11:$D$71,M$1)),0)} -> 0.975896 | N11: {=IFERROR(M11*(1-INDEX($D11:$D$71,N$1)),0)} -> 0.94993912 | O11: {=IFERROR(N11*(1-INDEX($D11:$D$71,O$1)),0)} -> 0.92202991 | P11: {=IFERROR(O11*(1-INDEX($D11:$D$71,P$1)),0)} -> 0.892075 | Q11: {=IFERROR(P11*(1-INDEX($D11:$D$71,Q$1)),0)} -> 0.85999777 | R11: {=IFERROR(Q11*(1-INDEX($D11:$D$71,R$1)),0)} -> 0.82573546 | S11: {=IFERROR(R11*(1-INDEX($D11:$D$71,S$1)),0)} -> 0.78925116 | T11: {=IFERROR(S11*(1-INDEX($D11:$D$71,T$1)),0)} -> 0.75053681 | ... BF11: {=IFERROR(BE11*(1-INDEX($D11:$D$71,BF$1)),0)} -> 0
A12: =(1-(1+A4)^(-1/12))*12 -> 0.029522427 | C12: 74 | D12: {=_xlfn.IFS($A$1="Male",Data!O14,$A$1="Female",Data!W14,$A$1="Unspecified",Data!G14)} -> 0.026598 | E12: =-1/2*(LN(1-D11)+LN(1-D12)) -> 0.025678691 | F12: {=SUMPRODUCT($A$6^(($L$1:$BD$1)+1),(L12:BD12),(TRANSPOSE(D12:D56)))} -> 0.6894636 | G12: {=SUMPRODUCT($A$6^($L$1:$BF$1),L12:BF12)} -> 10.66175 | H12: =(1-$A$4/$A$8*F12)/$A$12 -> 10.199259 | I12: =G12-(12-1)/2/12-(12^2-1)/12/12^2*(E12+LN(1+$A$4)) -> 10.198845 | L12: 1 | M12: {=IFERROR(L12*(1-INDEX($D12:$D$71,M$1)),0)} -> 0.973402 | N12: {=IFERROR(M12*(1-INDEX($D12:$D$71,N$1)),0)} -> 0.94480345 | O12: {=IFERROR(N12*(1-INDEX($D12:$D$71,O$1)),0)} -> 0.91410867 | P12: {=IFERROR(O12*(1-INDEX($D12:$D$71,P$1)),0)} -> 0.88123916 | Q12: {=IFERROR(P12*(1-INDEX($D12:$D$71,Q$1)),0)} -> 0.84613059 | R12: {=IFERROR(Q12*(1-INDEX($D12:$D$71,R$1)),0)} -> 0.80874515 | S12: {=IFERROR(R12*(1-INDEX($D12:$D$71,S$1)),0)} -> 0.76907459 | T12: {=IFERROR(S12*(1-INDEX($D12:$D$71,T$1)),0)} -> 0.72715233 | ... BF12: {=IFERROR(BE12*(1-INDEX($D12:$D$71,BF$1)),0)} -> 0
C13: 75 | D13: {=_xlfn.IFS($A$1="Male",Data!O15,$A$1="Female",Data!W15,$A$1="Unspecified",Data!G15)} -> 0.02938 | E13: =-1/2*(LN(1-D12)+LN(1-D13)) -> 0.028389182 | F13: {=SUMPRODUCT($A$6^(($L$1:$BD$1)+1),(L13:BD13),(TRANSPOSE(D13:D57)))} -> 0.70222735 | G13: {=SUMPRODUCT($A$6^($L$1:$BF$1),L13:BF13)} -> 10.223528 | H13: =(1-$A$4/$A$8*F13)/$A$12 -> 9.7610048 | I13: =G13-(12-1)/2/12-(12^2-1)/12/12^2*(E13+LN(1+$A$4)) -> 9.7603988 | L13: 1 | M13: {=IFERROR(L13*(1-INDEX($D13:$D$71,M$1)),0)} -> 0.97062 | N13: {=IFERROR(M13*(1-INDEX($D13:$D$71,N$1)),0)} -> 0.9390865 | O13: {=IFERROR(N13*(1-INDEX($D13:$D$71,O$1)),0)} -> 0.90531883 | P13: {=IFERROR(O13*(1-INDEX($D13:$D$71,P$1)),0)} -> 0.86925092 | Q13: {=IFERROR(P13*(1-INDEX($D13:$D$71,Q$1)),0)} -> 0.83084394 | R13: {=IFERROR(Q13*(1-INDEX($D13:$D$71,R$1)),0)} -> 0.79008938 | S13: {=IFERROR(R13*(1-INDEX($D13:$D$71,S$1)),0)} -> 0.74702161 | T13: {=IFERROR(S13*(1-INDEX($D13:$D$71,T$1)),0)} -> 0.7017282 | ... BF13: {=IFERROR(BE13*(1-INDEX($D13:$D$71,BF$1)),0)} -> 0
C14: 76 | D14: {=_xlfn.IFS($A$1="Male",Data!O16,$A$1="Female",Data!W16,$A$1="Unspecified",Data!G16)} -> 0.032488 | E14: =-1/2*(LN(1-D13)+LN(1-D14)) -> 0.031423844 | F14: {=SUMPRODUCT($A$6^(($L$1:$BD$1)+1),(L14:BD14),(TRANSPOSE(D14:D58)))} -> 0.71491848 | G14: {=SUMPRODUCT($A$6^($L$1:$BF$1),L14:BF14)} -> 9.7877989 | H14: =(1-$A$4/$A$8*F14)/$A$12 -> 9.3252447 | I14: =G14-(12-1)/2/12-(12^2-1)/12/12^2*(E14+LN(1+$A$4)) -> 9.324419 | L14: 1 | M14: {=IFERROR(L14*(1-INDEX($D14:$D$71,M$1)),0)} -> 0.967512 | N14: {=IFERROR(M14*(1-INDEX($D14:$D$71,N$1)),0)} -> 0.9327222 | O14: {=IFERROR(N14*(1-INDEX($D14:$D$71,O$1)),0)} -> 0.89556255 | P14: {=IFERROR(O14*(1-INDEX($D14:$D$71,P$1)),0)} -> 0.85599302 | Q14: {=IFERROR(P14*(1-INDEX($D14:$D$71,Q$1)),0)} -> 0.81400485 | R14: {=IFERROR(Q14*(1-INDEX($D14:$D$71,R$1)),0)} -> 0.76963344 | S14: {=IFERROR(R14*(1-INDEX($D14:$D$71,S$1)),0)} -> 0.72296903 | T14: {=IFERROR(S14*(1-INDEX($D14:$D$71,T$1)),0)} -> 0.67415705 | ... BF14: {=IFERROR(BE14*(1-INDEX($D14:$D$71,BF$1)),0)} -> 0
C15: 77 | D15: {=_xlfn.IFS($A$1="Male",Data!O17,$A$1="Female",Data!W17,$A$1="Unspecified",Data!G17)} -> 0.035958 | E15: =-1/2*(LN(1-D14)+LN(1-D15)) -> 0.034823934 | F15: {=SUMPRODUCT($A$6^(($L$1:$BD$1)+1),(L15:BD15),(TRANSPOSE(D15:D59)))} -> 0.72751349 | G15: {=SUMPRODUCT($A$6^($L$1:$BF$1),L15:BF15)} -> 9.3553701 | H15: =(1-$A$4/$A$8*F15)/$A$12 -> 8.8927847 | I15: =G15-(12-1)/2/12-(12^2-1)/12/12^2*(E15+LN(1+$A$4)) -> 8.8917088 | L15: 1 | M15: {=IFERROR(L15*(1-INDEX($D15:$D$71,M$1)),0)} -> 0.964042 | N15: {=IFERROR(M15*(1-INDEX($D15:$D$71,N$1)),0)} -> 0.92563457 | O15: {=IFERROR(N15*(1-INDEX($D15:$D$71,O$1)),0)} -> 0.88473633 | P15: {=IFERROR(O15*(1-INDEX($D15:$D$71,P$1)),0)} -> 0.84133824 | Q15: {=IFERROR(P15*(1-INDEX($D15:$D$71,Q$1)),0)} -> 0.7954769 | R15: {=IFERROR(Q15*(1-INDEX($D15:$D$71,R$1)),0)} -> 0.74724554 | S15: {=IFERROR(R15*(1-INDEX($D15:$D$71,S$1)),0)} -> 0.69679451 | T15: {=IFERROR(S15*(1-INDEX($D15:$D$71,T$1)),0)} -> 0.64436212 | ... BF15: {=IFERROR(BE15*(1-INDEX($D15:$D$71,BF$1)),0)} -> 0
C16: 78 | D16: {=_xlfn.IFS($A$1="Male",Data!O18,$A$1="Female",Data!W18,$A$1="Unspecified",Data!G18)} -> 0.03984 | E16: =-1/2*(LN(1-D15)+LN(1-D16)) -> 0.038637879 | F16: {=SUMPRODUCT($A$6^(($L$1:$BD$1)+1),(L16:BD16),(TRANSPOSE(D16:D60)))} -> 0.73998944 | G16: {=SUMPRODUCT($A$6^($L$1:$BF$1),L16:BF16)} -> 8.9270294 | H16: =(1-$A$4/$A$8*F16)/$A$12 -> 8.4644129 | I16: =G16-(12-1)/2/12-(12^2-1)/12/12^2*(E16+LN(1+$A$4)) -> 8.4630525 | L16: 1 | M16: {=IFERROR(L16*(1-INDEX($D16:$D$71,M$1)),0)} -> 0.96016 | N16: {=IFERROR(M16*(1-INDEX($D16:$D$71,N$1)),0)} -> 0.91773629 | O16: {=IFERROR(N16*(1-INDEX($D16:$D$71,O$1)),0)} -> 0.87271949 | P16: {=IFERROR(O16*(1-INDEX($D16:$D$71,P$1)),0)} -> 0.82514755 | Q16: {=IFERROR(P16*(1-INDEX($D16:$D$71,Q$1)),0)} -> 0.7751172 | R16: {=IFERROR(Q16*(1-INDEX($D16:$D$71,R$1)),0)} -> 0.72278439 | S16: {=IFERROR(R16*(1-INDEX($D16:$D$71,S$1)),0)} -> 0.66839631 | T16: {=IFERROR(S16*(1-INDEX($D16:$D$71,T$1)),0)} -> 0.61228043 | ... BF16: {=IFERROR(BE16*(1-INDEX($D16:$D$71,BF$1)),0)} -> 0
C17: 79 | D17: {=_xlfn.IFS($A$1="Male",Data!O19,$A$1="Female",Data!W19,$A$1="Unspecified",Data!G19)} -> 0.044184 | E17: =-1/2*(LN(1-D16)+LN(1-D17)) -> 0.042922597 | F17: {=SUMPRODUCT($A$6^(($L$1:$BD$1)+1),(L17:BD17),(TRANSPOSE(D17:D61)))} -> 0.75232161 | G17: {=SUMPRODUCT($A$6^($L$1:$BF$1),L17:BF17)} -> 8.5036247 | H17: =(1-$A$4/$A$8*F17)/$A$12 -> 8.0409776 | I17: =G17-(12-1)/2/12-(12^2-1)/12/12^2*(E17+LN(1+$A$4)) -> 8.0392932 | L17: 1 | M17: {=IFERROR(L17*(1-INDEX($D17:$D$71,M$1)),0)} -> 0.955816 | N17: {=IFERROR(M17*(1-INDEX($D17:$D$71,N$1)),0)} -> 0.90893131 | O17: {=IFERROR(N17*(1-INDEX($D17:$D$71,O$1)),0)} -> 0.85938547 | P17: {=IFERROR(O17*(1-INDEX($D17:$D$71,P$1)),0)} -> 0.80727921 | Q17: {=IFERROR(P17*(1-INDEX($D17:$D$71,Q$1)),0)} -> 0.75277494 | R17: {=IFERROR(Q17*(1-INDEX($D17:$D$71,R$1)),0)} -> 0.69613014 | S17: {=IFERROR(R17*(1-INDEX($D17:$D$71,S$1)),0)} -> 0.63768583 | T17: {=IFERROR(S17*(1-INDEX($D17:$D$71,T$1)),0)} -> 0.57789514 | ... BF17: {=IFERROR(BE17*(1-INDEX($D17:$D$71,BF$1)),0)} -> 0
C18: 80 | D18: {=_xlfn.IFS($A$1="Male",Data!O20,$A$1="Female",Data!W20,$A$1="Unspecified",Data!G20)} -> 0.049052 | E18: =-1/2*(LN(1-D17)+LN(1-D18)) -> 0.047742875 | F18: {=SUMPRODUCT($A$6^(($L$1:$BD$1)+1),(L18:BD18),(TRANSPOSE(D18:D62)))} -> 0.76448528 | G18: {=SUMPRODUCT($A$6^($L$1:$BF$1),L18:BF18)} -> 8.0860055 | H18: =(1-$A$4/$A$8*F18)/$A$12 -> 7.6233282 | I18: =G18-(12-1)/2/12-(12^2-1)/12/12^2*(E18+LN(1+$A$4)) -> 7.6212751 | L18: 1 | M18: {=IFERROR(L18*(1-INDEX($D18:$D$71,M$1)),0)} -> 0.950948 | N18: {=IFERROR(M18*(1-INDEX($D18:$D$71,N$1)),0)} -> 0.89911182 | O18: {=IFERROR(N18*(1-INDEX($D18:$D$71,O$1)),0)} -> 0.84459688 | P18: {=IFERROR(O18*(1-INDEX($D18:$D$71,P$1)),0)} -> 0.78757307 | Q18: {=IFERROR(P18*(1-INDEX($D18:$D$71,Q$1)),0)} -> 0.72830978 | R18: {=IFERROR(Q18*(1-INDEX($D18:$D$71,R$1)),0)} -> 0.6671638 | S18: {=IFERROR(R18*(1-INDEX($D18:$D$71,S$1)),0)} -> 0.60460919 | T18: {=IFERROR(S18*(1-INDEX($D18:$D$71,T$1)),0)} -> 0.54123526 | ... BF18: {=IFERROR(BE18*(1-INDEX($D18:$D$71,BF$1)),0)} -> 0
C19: 81 | D19: {=_xlfn.IFS($A$1="Male",Data!O21,$A$1="Female",Data!W21,$A$1="Unspecified",Data!G21)} -> 0.05451 | E19: =-1/2*(LN(1-D18)+LN(1-D19)) -> 0.053173932 | F19: {=SUMPRODUCT($A$6^(($L$1:$BD$1)+1),(L19:BD19),(TRANSPOSE(D19:D63)))} -> 0.77645448 | G19: {=SUMPRODUCT($A$6^($L$1:$BF$1),L19:BF19)} -> 7.6750628 | H19: =(1-$A$4/$A$8*F19)/$A$12 -> 7.2123558 | I19: =G19-(12-1)/2/12-(12^2-1)/12/12^2*(E19+LN(1+$A$4)) -> 7.209883 | L19: 1 | M19: {=IFERROR(L19*(1-INDEX($D19:$D$71,M$1)),0)} -> 0.94549 | N19: {=IFERROR(M19*(1-INDEX($D19:$D$71,N$1)),0)} -> 0.88816305 | O19: {=IFERROR(N19*(1-INDEX($D19:$D$71,O$1)),0)} -> 0.82819783 | P19: {=IFERROR(O19*(1-INDEX($D19:$D$71,P$1)),0)} -> 0.7658776 | Q19: {=IFERROR(P19*(1-INDEX($D19:$D$71,Q$1)),0)} -> 0.70157758 | R19: {=IFERROR(Q19*(1-INDEX($D19:$D$71,R$1)),0)} -> 0.63579627 | S19: {=IFERROR(R19*(1-INDEX($D19:$D$71,S$1)),0)} -> 0.56915337 | T19: {=IFERROR(S19*(1-INDEX($D19:$D$71,T$1)),0)} -> 0.5023951 | ... BF19: {=IFERROR(BE19*(1-INDEX($D19:$D$71,BF$1)),0)} -> 0
C20: 82 | D20: {=_xlfn.IFS($A$1="Male",Data!O22,$A$1="Female",Data!W22,$A$1="Unspecified",Data!G22)} -> 0.060632 | E20: =-1/2*(LN(1-D19)+LN(1-D20)) -> 0.059299969 | F20: {=SUMPRODUCT($A$6^(($L$1:$BD$1)+1),(L20:BD20),(TRANSPOSE(D20:D64)))} -> 0.78820306 | G20: {=SUMPRODUCT($A$6^($L$1:$BF$1),L20:BF20)} -> 7.2716948 | H20: =(1-$A$4/$A$8*F20)/$A$12 -> 6.8089586 | I20: =G20-(12-1)/2/12-(12^2-1)/12/12^2*(E20+LN(1+$A$4)) -> 6.806008 | L20: 1 | M20: {=IFERROR(L20*(1-INDEX($D20:$D$71,M$1)),0)} -> 0.939368 | N20: {=IFERROR(M20*(1-INDEX($D20:$D$71,N$1)),0)} -> 0.87594563 | O20: {=IFERROR(N20*(1-INDEX($D20:$D$71,O$1)),0)} -> 0.81003247 | P20: {=IFERROR(O20*(1-INDEX($D20:$D$71,P$1)),0)} -> 0.74202539 | Q20: {=IFERROR(P20*(1-INDEX($D20:$D$71,Q$1)),0)} -> 0.6724516 | R20: {=IFERROR(Q20*(1-INDEX($D20:$D$71,R$1)),0)} -> 0.60196657 | S20: {=IFERROR(R20*(1-INDEX($D20:$D$71,S$1)),0)} -> 0.5313595 | T20: {=IFERROR(S20*(1-INDEX($D20:$D$71,T$1)),0)} -> 0.4615463 | ... BF20: {=IFERROR(BE20*(1-INDEX($D20:$D$71,BF$1)),0)} -> 0
C21: 83 | D21: {=_xlfn.IFS($A$1="Male",Data!O23,$A$1="Female",Data!W23,$A$1="Unspecified",Data!G23)} -> 0.067516 | E21: =-1/2*(LN(1-D20)+LN(1-D21)) -> 0.066225628 | F21: {=SUMPRODUCT($A$6^(($L$1:$BD$1)+1),(L21:BD21),(TRANSPOSE(D21:D65)))} -> 0.79970486 | G21: {=SUMPRODUCT($A$6^($L$1:$BF$1),L21:BF21)} -> 6.8767997 | H21: =(1-$A$4/$A$8*F21)/$A$12 -> 6.414035 | I21: =G21-(12-1)/2/12-(12^2-1)/12/12^2*(E21+LN(1+$A$4)) -> 6.4105398 | L21: 1 | M21: {=IFERROR(L21*(1-INDEX($D21:$D$71,M$1)),0)} -> 0.932484 | N21: {=IFERROR(M21*(1-INDEX($D21:$D$71,N$1)),0)} -> 0.86231644 | O21: {=IFERROR(N21*(1-INDEX($D21:$D$71,O$1)),0)} -> 0.7899198 | P21: {=IFERROR(O21*(1-INDEX($D21:$D$71,P$1)),0)} -> 0.71585534 | Q21: {=IFERROR(P21*(1-INDEX($D21:$D$71,Q$1)),0)} -> 0.64082082 | R21: {=IFERROR(Q21*(1-INDEX($D21:$D$71,R$1)),0)} -> 0.56565638 | S21: {=IFERROR(R21*(1-INDEX($D21:$D$71,S$1)),0)} -> 0.49133705 | T21: {=IFERROR(S21*(1-INDEX($D21:$D$71,T$1)),0)} -> 0.41895328 | ... BF21: {=IFERROR(BE21*(1-INDEX($D21:$D$71,BF$1)),0)} -> 0
C22: 84 | D22: {=_xlfn.IFS($A$1="Male",Data!O24,$A$1="Female",Data!W24,$A$1="Unspecified",Data!G24)} -> 0.075248 | E22: =-1/2*(LN(1-D21)+LN(1-D22)) -> 0.074066486 | F22: {=SUMPRODUCT($A$6^(($L$1:$BD$1)+1),(L22:BD22),(TRANSPOSE(D22:D66)))} -> 0.81093081 | G22: {=SUMPRODUCT($A$6^($L$1:$BF$1),L22:BF22)} -> 6.4913754 | H22: =(1-$A$4/$A$8*F22)/$A$12 -> 6.0285829 | I22: =G22-(12-1)/2/12-(12^2-1)/12/12^2*(E22+LN(1+$A$4)) -> 6.0244666 | L22: 1 | M22: {=IFERROR(L22*(1-INDEX($D22:$D$71,M$1)),0)} -> 0.924752 | N22: {=IFERROR(M22*(1-INDEX($D22:$D$71,N$1)),0)} -> 0.84711352 | O22: {=IFERROR(N22*(1-INDEX($D22:$D$71,O$1)),0)} -> 0.76768646 | P22: {=IFERROR(O22*(1-INDEX($D22:$D$71,P$1)),0)} -> 0.6872191 | Q22: {=IFERROR(P22*(1-INDEX($D22:$D$71,Q$1)),0)} -> 0.60661243 | R22: {=IFERROR(Q22*(1-INDEX($D22:$D$71,R$1)),0)} -> 0.52691205 | S22: {=IFERROR(R22*(1-INDEX($D22:$D$71,S$1)),0)} -> 0.44928736 | T22: {=IFERROR(S22*(1-INDEX($D22:$D$71,T$1)),0)} -> 0.37522054 | ... BF22: {=IFERROR(BE22*(1-INDEX($D22:$D$71,BF$1)),0)} -> 0
C23: 85 | D23: {=_xlfn.IFS($A$1="Male",Data!O25,$A$1="Female",Data!W25,$A$1="Unspecified",Data!G25)} -> 0.083956 | E23: =-1/2*(LN(1-D22)+LN(1-D23)) -> 0.082960283 | F23: {=SUMPRODUCT($A$6^(($L$1:$BD$1)+1),(L23:BD23),(TRANSPOSE(D23:D67)))} -> 0.82185357 | G23: {=SUMPRODUCT($A$6^($L$1:$BF$1),L23:BF23)} -> 6.1163606 | H23: =(1-$A$4/$A$8*F23)/$A$12 -> 5.6535409 | I23: =G23-(12-1)/2/12-(12^2-1)/12/12^2*(E23+LN(1+$A$4)) -> 5.6487158 | L23: 1 | M23: {=IFERROR(L23*(1-INDEX($D23:$D$71,M$1)),0)} -> 0.916044 | N23: {=IFERROR(M23*(1-INDEX($D23:$D$71,N$1)),0)} -> 0.83015388 | O23: {=IFERROR(N23*(1-INDEX($D23:$D$71,O$1)),0)} -> 0.74313881 | P23: {=IFERROR(O23*(1-INDEX($D23:$D$71,P$1)),0)} -> 0.65597309 | Q23: {=IFERROR(P23*(1-INDEX($D23:$D$71,Q$1)),0)} -> 0.56978741 | R23: {=IFERROR(Q23*(1-INDEX($D23:$D$71,R$1)),0)} -> 0.48584633 | S23: {=IFERROR(R23*(1-INDEX($D23:$D$71,S$1)),0)} -> 0.40575262 | T23: {=IFERROR(S23*(1-INDEX($D23:$D$71,T$1)),0)} -> 0.33127267 | ... BF23: {=IFERROR(BE23*(1-INDEX($D23:$D$71,BF$1)),0)} -> 0
C24: 86 | D24: {=_xlfn.IFS($A$1="Male",Data!O26,$A$1="Female",Data!W26,$A$1="Unspecified",Data!G26)} -> 0.093762 | E24: =-1/2*(LN(1-D23)+LN(1-D24)) -> 0.093072097 | F24: {=SUMPRODUCT($A$6^(($L$1:$BD$1)+1),(L24:BD24),(TRANSPOSE(D24:D68)))} -> 0.83244165 | G24: {=SUMPRODUCT($A$6^($L$1:$BF$1),L24:BF24)} -> 5.7528366 | H24: =(1-$A$4/$A$8*F24)/$A$12 -> 5.2899906 | I24: =G24-(12-1)/2/12-(12^2-1)/12/12^2*(E24+LN(1+$A$4)) -> 5.284355 | L24: 1 | M24: {=IFERROR(L24*(1-INDEX($D24:$D$71,M$1)),0)} -> 0.906238 | N24: {=IFERROR(M24*(1-INDEX($D24:$D$71,N$1)),0)} -> 0.81124795 | O24: {=IFERROR(N24*(1-INDEX($D24:$D$71,O$1)),0)} -> 0.71609343 | P24: {=IFERROR(O24*(1-INDEX($D24:$D$71,P$1)),0)} -> 0.62200878 | Q24: {=IFERROR(P24*(1-INDEX($D24:$D$71,Q$1)),0)} -> 0.53037444 | R24: {=IFERROR(Q24*(1-INDEX($D24:$D$71,R$1)),0)} -> 0.4429401 | S24: {=IFERROR(R24*(1-INDEX($D24:$D$71,S$1)),0)} -> 0.36163401 | T24: {=IFERROR(S24*(1-INDEX($D24:$D$71,T$1)),0)} -> 0.28808706 | ... BF24: {=IFERROR(BE24*(1-INDEX($D24:$D$71,BF$1)),0)} -> 0
... C48: 110 | D48: {=_xlfn.IFS($A$1="Male",Data!O50,$A$1="Female",Data!W50,$A$1="Unspecified",Data!G50)} -> 1 | E48: =-1/2*(LN(1-D47)+LN(1-D48)) -> #NUM! | F48: {=SUMPRODUCT($A$6^(($L$1:$BD$1)+1),(L48:BD48),(TRANSPOSE(D48:D92)))} -> 0.97087379 | G48: {=SUMPRODUCT($A$6^($L$1:$BF$1),L48:BF48)} -> 1 | H48: =(1-$A$4/$A$8*F48)/$A$12 -> 0.53681035 | I48: =G48-(12-1)/2/12-(12^2-1)/12/12^2*(E48+LN(1+$A$4)) -> #NUM! | L48: 1 | M48: {=IFERROR(L48*(1-INDEX($D48:$D$71,M$1)),0)} -> 0 | N48: {=IFERROR(M48*(1-INDEX($D48:$D$71,N$1)),0)} -> 0 | O48: {=IFERROR(N48*(1-INDEX($D48:$D$71,O$1)),0)} -> 0 | P48: {=IFERROR(O48*(1-INDEX($D48:$D$71,P$1)),0)} -> 0 | Q48: {=IFERROR(P48*(1-INDEX($D48:$D$71,Q$1)),0)} -> 0 | R48: {=IFERROR(Q48*(1-INDEX($D48:$D$71,R$1)),0)} -> 0 | S48: {=IFERROR(R48*(1-INDEX($D48:$D$71,S$1)),0)} -> 0 | T48: {=IFERROR(S48*(1-INDEX($D48:$D$71,T$1)),0)} -> 0 | ... BF48: {=IFERROR(BE48*(1-INDEX($D48:$D$71,BF$1)),0)} -> 0

Sheet Data
A2: Gender unspecified | I2: Gender: Male | Q2: Gender: Female
A3: Age group | B3: 2019 | C3: 2020 | D3: 2021 | E3: 2022 | F3: 2023 | G3: Average | I3: Age group | J3: 2019 | K3: 2020 | L3: 2021 | M3: 2022 | N3: 2023 | O3: Average | Q3: Age group | R3: 2019 | S3: 2020 | T3: 2021 | U3: 2022 | V3: 2023 | W3: Average
A4: 64 years | B4: 0.00805 | C4: 0.00843 | D4: 0.00861 | E4: 0.00868 | F4: 0.00834 | G4: =AVERAGE(B4:F4) -> 0.008422 | I4: 64 years | J4: 0.00987 | K4: 0.01041 | L4: 0.0107 | M4: 0.0107 | N4: 0.01026 | O4: =AVERAGE(J4:N4) -> 0.010388 | Q4: 64 years | R4: 0.00627 | S4: 0.00649 | T4: 0.00655 | U4: 0.00668 | V4: 0.00645 | W4: =AVERAGE(R4:V4) -> 0.006488
A5: 65 years | B5: 0.00884 | C5: 0.00923 | D5: 0.00942 | E5: 0.0095 | F5: 0.00912 | G5: =AVERAGE(D5:F5) -> 0.0093466667 | I5: 65 years | J5: 0.01084 | K5: 0.01138 | L5: 0.01167 | M5: 0.0117 | N5: 0.0112 | O5: =AVERAGE(J5:N5) -> 0.011358 | Q5: 65 years | R5: 0.0069 | S5: 0.00714 | T5: 0.0072 | U5: 0.00735 | V5: 0.00709 | W5: =AVERAGE(R5:V5) -> 0.007136
A6: 66 years | B6: 0.00972 | C6: 0.01012 | D6: 0.01031 | E6: 0.01042 | F6: 0.00999 | G6: =AVERAGE(D6:F6) -> 0.01024 | I6: 66 years | J6: 0.01192 | K6: 0.01246 | L6: 0.01275 | M6: 0.01281 | N6: 0.01224 | O6: =AVERAGE(J6:N6) -> 0.012436 | Q6: 66 years | R6: 0.0076 | S6: 0.00786 | T6: 0.00793 | U6: 0.00809 | V6: 0.0078 | W6: =AVERAGE(R6:V6) -> 0.007856
A7: 67 years | B7: 0.0107 | C7: 0.01111 | D7: 0.0113 | E7: 0.01144 | F7: 0.01096 | G7: =AVERAGE(D7:F7) -> 0.011233333 | I7: 67 years | J7: 0.01311 | K7: 0.01366 | L7: 0.01394 | M7: 0.01404 | N7: 0.01339 | O7: =AVERAGE(J7:N7) -> 0.013628 | Q7: 67 years | R7: 0.00839 | S7: 0.00867 | T7: 0.00874 | U7: 0.00891 | V7: 0.0086 | W7: =AVERAGE(R7:V7) -> 0.008662
A8: 68 years | B8: 0.01179 | C8: 0.01221 | D8: 0.01239 | E8: 0.01257 | F8: 0.01203 | G8: =AVERAGE(D8:F8) -> 0.01233 | I8: 68 years | J8: 0.01443 | K8: 0.01498 | L8: 0.01526 | M8: 0.0154 | N8: 0.01467 | O8: =AVERAGE(J8:N8) -> 0.014948 | Q8: 68 years | R8: 0.00927 | S8: 0.00957 | T8: 0.00964 | U8: 0.00983 | V8: 0.00948 | W8: =AVERAGE(R8:V8) -> 0.009558
A9: 69 years | B9: 0.01299 | C9: 0.01344 | D9: 0.01361 | E9: 0.01382 | F9: 0.01321 | G9: =AVERAGE(D9:F9) -> 0.013546667 | I9: 69 years | J9: 0.01589 | K9: 0.01646 | L9: 0.01672 | M9: 0.01691 | N9: 0.01609 | O9: =AVERAGE(J9:N9) -> 0.016414 | Q9: 69 years | R9: 0.01025 | S9: 0.01058 | T9: 0.01064 | U9: 0.01086 | V9: 0.01047 | W9: =AVERAGE(R9:V9) -> 0.01056
A10: 70 years | B10: 0.01433 | C10: 0.0148 | D10: 0.01496 | E10: 0.01522 | F10: 0.01454 | G10: =AVERAGE(D10:F10) -> 0.014906667 | I10: 70 years | J10: 0.01752 | K10: 0.0181 | L10: 0.01834 | M10: 0.0186 | N10: 0.01766 | O10: =AVERAGE(J10:N10) -> 0.018044 | Q10: 70 years | R10: 0.01134 | S10: 0.0117 | T10: 0.01176 | U10: 0.01202 | V10: 0.01157 | W10: =AVERAGE(R10:V10) -> 0.011678
A11: 71 years | B11: 0.01583 | C11: 0.01631 | D11: 0.01645 | E11: 0.01677 | F11: 0.01601 | G11: =AVERAGE(D11:F11) -> 0.01641 | I11: 71 years | J11: 0.01932 | K11: 0.01992 | L11: 0.02014 | M11: 0.02047 | N11: 0.01941 | O11: =AVERAGE(J11:N11) -> 0.019852 | Q11: 71 years | R11: 0.01257 | S11: 0.01297 | T11: 0.01301 | U11: 0.0133 | V11: 0.01281 | W11: =AVERAGE(R11:V11) -> 0.012932
A12: 72 years | B12: 0.01749 | C12: 0.018 | D12: 0.01812 | E12: 0.0185 | F12: 0.01764 | G12: =AVERAGE(D12:F12) -> 0.018086667 | I12: 72 years | J12: 0.02133 | K12: 0.02195 | L12: 0.02213 | M12: 0.02255 | N12: 0.02136 | O12: =AVERAGE(J12:N12) -> 0.021864 | Q12: 72 years | R12: 0.01395 | S12: 0.01438 | T12: 0.01441 | U12: 0.01475 | V12: 0.0142 | W12: =AVERAGE(R12:V12) -> 0.014338
A13: 73 years | B13: 0.01934 | C13: 0.01989 | D13: 0.01997 | E13: 0.02044 | F13: 0.01947 | G13: =AVERAGE(D13:F13) -> 0.01996 | I13: 73 years | J13: 0.02357 | K13: 0.02421 | L13: 0.02435 | M13: 0.02487 | N13: 0.02352 | O13: =AVERAGE(J13:N13) -> 0.024104 | Q13: 73 years | R13: 0.01549 | S13: 0.01597 | T13: 0.01597 | U13: 0.01637 | V13: 0.01575 | W13: =AVERAGE(R13:V13) -> 0.01591
A14: 74 years | B14: 0.02141 | C14: 0.022 | D14: 0.02203 | E14: 0.02259 | F14: 0.02151 | G14: =AVERAGE(D14:F14) -> 0.022043333 | I14: 74 years | J14: 0.02606 | K14: 0.02673 | L14: 0.02681 | M14: 0.02745 | N14: 0.02594 | O14: =AVERAGE(J14:N14) -> 0.026598 | Q14: 74 years | R14: 0.01722 | S14: 0.01775 | T14: 0.01772 | U14: 0.01819 | V14: 0.01749 | W14: =AVERAGE(R14:V14) -> 0.017674
A15: 75 years | B15: 0.02371 | C15: 0.02435 | D15: 0.02433 | E15: 0.025 | F15: 0.02378 | G15: =AVERAGE(D15:F15) -> 0.02437 | I15: 75 years | J15: 0.02883 | K15: 0.02954 | L15: 0.02956 | M15: 0.03034 | N15: 0.02863 | O15: =AVERAGE(J15:N15) -> 0.02938 | Q15: 75 years | R15: 0.01916 | S15: 0.01976 | T15: 0.01969 | U15: 0.02023 | V15: 0.01945 | W15: =AVERAGE(R15:V15) -> 0.019658
A16: 76 years | B16: 0.02629 | C16: 0.02699 | D16: 0.02689 | E16: 0.0277 | F16: 0.02633 | G16: =AVERAGE(D16:F16) -> 0.026973333 | I16: 76 years | J16: 0.03192 | K16: 0.03269 | L16: 0.03262 | M16: 0.03357 | N16: 0.03164 | O16: =AVERAGE(J16:N16) -> 0.032488 | Q16: 76 years | R16: 0.02135 | S16: 0.02202 | T16: 0.02189 | U16: 0.02253 | V16: 0.02165 | W16: =AVERAGE(R16:V16) -> 0.021888
... A50: 110 years and over | B50: 1 | C50: 1 | D50: 1 | E50: 1 | F50: 1 | G50: =AVERAGE(D50:F50) -> 1 | I50: 110 years and over | J50: 1 | K50: 1 | L50: 1 | M50: 1 | N50: 1 | O50: =AVERAGE(J50:N50) -> 1 | Q50: 110 years and over | R50: 1 | S50: 1 | T50: 1 | U50: 1 | V50: 1 | W50: =AVERAGE(R50:V50) -> 1

Sheet CSOM
A1: https://www.soa.org/resources/experience-studies/2015/2017-cso-tables/ | C1: x | D1: q_x | E1: mu_x | F1: A_x | G1: a_x | H1: a(12)_x (UDD) | I1: a(12)_x (WH3) | J1: npx | K1: 0 | L1: 1 | M1: 2 | N1: 3 | O1: 4 | P1: 5 | Q1: 6 | R1: 7 | S1: 8 | T1: 9 | U1: 10 | V1: 11 | W1: 12 | X1: 13 | Y1: 14 | Z1: 15 | AA1: 16 | AB1: 17 | AC1: 18 | AD1: 19 | AE1: 20 | AF1: 21 | AG1: 22 | AH1: 23 | AI1: 24 | AJ1: 25 | AK1: 26 | AL1: 27 | AM1: 28 | AN1: 29 | AO1: 30 | AP1: 31 | AQ1: 32 | AR1: 33 | AS1: 34 | AT1: 35 | AU1: 36 | AV1: 37 | AW1: 38 | AX1: 39 | AY1: 40 | AZ1: 41 | BA1: 42 | BB1: 43 | BC1: 44 | BD1: 45 | BE1: 46 | BF1: 47 | BG1: 48 | BH1: 49 | BI1: 50 | BJ1: 51 | BK1: 52 | BL1: 53 | BM1: 54 | BN1: 55 | BO1: 56 | BP1: 57 | BQ1: 58 | BR1: 59 | BS1: 60 | BT1: 61 | BU1: 62 | BV1: 63 | BW1: 64 | BX1: 65 | BY1: 66 | BZ1: 67 | CA1: 68 | CB1: 69 | CC1: 70 | CD1: 71 | CE1: 72 | CF1: 73 | CG1: 74 | CH1: 75 | CI1: 76 | CJ1: 77 | CK1: 78 | CL1: 79 | CM1: 80 | CN1: 81 | CO1: 82 | CP1: 83 | CQ1: 84 | CR1: 85 | CS1: 86 | CT1: 87 | CU1: 88 | CV1: 89 | CW1: 90 | CX1: 91 | CY1: 92 | CZ1: 93 | DA1: 94 | DB1: 95 | DC1: 96 | DD1: 97 | DE1: 98 | DF1: 99 | DG1: 100 | DH1: 101 | DI1: 102 | DJ1: 103 | DK1: 104 | DL1: 105 | DM1: 106 | DN1: 107 | DO1: 108 | DP1: 109 | DQ1: 110 | DR1: 111 | DS1: 112 | DT1: 113 | DU1: 114 | DV1: 115 | DW1: 116 | DX1: 117
C2: 64 | D2: 0.00962 | K2: 1 | L2: {=IFERROR(K2*(1-INDEX($D2:$D$71,L$1)),0)} -> 0.99038 | M2: {=IFERROR(L2*(1-INDEX($D2:$D$71,M$1)),0)} -> 0.97984236 | N2: {=IFERROR(M2*(1-INDEX($D2:$D$71,N$1)),0)} -> 0.96834881 | O2: {=IFERROR(N2*(1-INDEX($D2:$D$71,O$1)),0)} -> 0.95587647 | P2: {=IFERROR(O2*(1-INDEX($D2:$D$71,P$1)),0)} -> 0.94236994 | Q2: {=IFERROR(P2*(1-INDEX($D2:$D$71,Q$1)),0)} -> 0.92773493 | R2: {=IFERROR(Q2*(1-INDEX($D2:$D$71,R$1)),0)} -> 0.911815 | S2: {=IFERROR(R2*(1-INDEX($D2:$D$71,S$1)),0)} -> 0.89440845 | ... DX2: {=IFERROR(DW2*(1-INDEX($D2:$D$71,DX$1)),0)} -> 0
A3: i | C3: 65 | D3: 0.01064 | E3: =-1/2*(LN(1-D2)+LN(1-D3)) -> 0.01018179 | F3: {=SUMPRODUCT($A$6^($K$1:$DT$1+1),K3:DT3,TRANSPOSE(D3:D116))} -> 0.57711881 | G3: {=SUMPRODUCT($A$6^($K$1:$DT$1),K3:DT3)} -> 14.518921 | H3: =(1-$A$4/$A$9*F3)/$A$15 -> 14.056709 | I3: =G3-(12-1)/2/12-(12^2-1)/12/12^2*(E3+LN(1+$A$4)) -> 14.057299 | K3: 1 | L3: {=IFERROR(K3*(1-INDEX($D3:$D$71,L$1)),0)} -> 0.98936 | M3: {=IFERROR(L3*(1-INDEX($D3:$D$71,M$1)),0)} -> 0.97775481 | N3: {=IFERROR(M3*(1-INDEX($D3:$D$71,N$1)),0)} -> 0.96516133 | O3: {=IFERROR(N3*(1-INDEX($D3:$D$71,O$1)),0)} -> 0.9515236 | P3: {=IFERROR(O3*(1-INDEX($D3:$D$71,P$1)),0)} -> 0.93674643 | Q3: {=IFERROR(P3*(1-INDEX($D3:$D$71,Q$1)),0)} -> 0.92067187 | R3: {=IFERROR(Q3*(1-INDEX($D3:$D$71,R$1)),0)} -> 0.90309624 | S3: {=IFERROR(R3*(1-INDEX($D3:$D$71,S$1)),0)} -> 0.88382417 | ... DX3: {=IFERROR(DW3*(1-INDEX($D3:$D$71,DX$1)),0)} -> 0
A4: =Payments!K2 -> 0.03 | C4: 66 | D4: 0.01173 | E4: =-1/2*(LN(1-D3)+LN(1-D4)) -> 0.011248174 | F4: {=SUMPRODUCT($A$6^($K$1:$DT$1+1),K4:DT4,TRANSPOSE(D4:D117))} -> 0.59007072 | G4: {=SUMPRODUCT($A$6^($K$1:$DT$1),K4:DT4)} -> 14.074239 | H4: =(1-$A$4/$A$9*F4)/$A$15 -> 13.611994 | I4: =G4-(12-1)/2/12-(12^2-1)/12/12^2*(E4+LN(1+$A$4)) -> 13.612528 | K4: 1 | L4: {=IFERROR(K4*(1-INDEX($D4:$D$71,L$1)),0)} -> 0.98827 | M4: {=IFERROR(L4*(1-INDEX($D4:$D$71,M$1)),0)} -> 0.97554108 | N4: {=IFERROR(M4*(1-INDEX($D4:$D$71,N$1)),0)} -> 0.96175669 | O4: {=IFERROR(N4*(1-INDEX($D4:$D$71,O$1)),0)} -> 0.94682061 | P4: {=IFERROR(O4*(1-INDEX($D4:$D$71,P$1)),0)} -> 0.93057316 | Q4: {=IFERROR(P4*(1-INDEX($D4:$D$71,Q$1)),0)} -> 0.91280852 | R4: {=IFERROR(Q4*(1-INDEX($D4:$D$71,R$1)),0)} -> 0.89332919 | S4: {=IFERROR(R4*(1-INDEX($D4:$D$71,S$1)),0)} -> 0.87194289 | ... DX4: {=IFERROR(DW4*(1-INDEX($D4:$D$71,DX$1)),0)} -> 0
A5: v | C5: 67 | D5: 0.01288 | E5: =-1/2*(LN(1-D4)+LN(1-D5)) -> 0.012381503 | F5: {=SUMPRODUCT($A$6^($K$1:$DT$1+1),K5:DT5,TRANSPOSE(D5:D118))} -> 0.60311741 | G5: {=SUMPRODUCT($A$6^($K$1:$DT$1),K5:DT5)} -> 13.626302 | H5: =(1-$A$4/$A$9*F5)/$A$15 -> 13.164026 | I5: =G5-(12-1)/2/12-(12^2-1)/12/12^2*(E5+LN(1+$A$4)) -> 13.164498 | K5: 1 | L5: {=IFERROR(K5*(1-INDEX($D5:$D$71,L$1)),0)} -> 0.98712 | M5: {=IFERROR(L5*(1-INDEX($D5:$D$71,M$1)),0)} -> 0.97317199 | N5: {=IFERROR(M5*(1-INDEX($D5:$D$71,N$1)),0)} -> 0.95805863 | O5: {=IFERROR(N5*(1-INDEX($D5:$D$71,O$1)),0)} -> 0.94161835 | P5: {=IFERROR(O5*(1-INDEX($D5:$D$71,P$1)),0)} -> 0.92364285 | Q5: {=IFERROR(P5*(1-INDEX($D5:$D$71,Q$1)),0)} -> 0.90393231 | R5: {=IFERROR(Q5*(1-INDEX($D5:$D$71,R$1)),0)} -> 0.88229217 | S5: {=IFERROR(R5*(1-INDEX($D5:$D$71,S$1)),0)} -> 0.85859381 | ... DX5: {=IFERROR(DW5*(1-INDEX($D5:$D$71,DX$1)),0)} -> 0
A6: =(1+A4)^-1 -> 0.97087379 | C6: 68 | D6: 0.01413 | E6: =-1/2*(LN(1-D5)+LN(1-D6)) -> 0.013597223 | F6: {=SUMPRODUCT($A$6^($K$1:$DT$1+1),K6:DT6,TRANSPOSE(D6:D119))} -> 0.61626847 | G6: {=SUMPRODUCT($A$6^($K$1:$DT$1),K6:DT6)} -> 13.174782 | H6: =(1-$A$4/$A$9*F6)/$A$15 -> 12.712473 | I6: =G6-(12-1)/2/12-(12^2-1)/12/12^2*(E6+LN(1+$A$4)) -> 12.712878 | K6: 1 | L6: {=IFERROR(K6*(1-INDEX($D6:$D$71,L$1)),0)} -> 0.98587 | M6: {=IFERROR(L6*(1-INDEX($D6:$D$71,M$1)),0)} -> 0.97055944 | N6: {=IFERROR(M6*(1-INDEX($D6:$D$71,N$1)),0)} -> 0.95390464 | O6: {=IFERROR(N6*(1-INDEX($D6:$D$71,O$1)),0)} -> 0.9356946 | P6: {=IFERROR(O6*(1-INDEX($D6:$D$71,P$1)),0)} -> 0.91572688 | Q6: {=IFERROR(P6*(1-INDEX($D6:$D$71,Q$1)),0)} -> 0.89380438 | R6: {=IFERROR(Q6*(1-INDEX($D6:$D$71,R$1)),0)} -> 0.86979679 | S6: {=IFERROR(R6*(1-INDEX($D6:$D$71,S$1)),0)} -> 0.8436507 | ... DX6: {=IFERROR(DW6*(1-INDEX($D6:$D$71,DX$1)),0)} -> 0
C7: 69 | D7: 0.01553 | E7: =-1/2*(LN(1-D6)+LN(1-D7)) -> 0.014941316 | F7: {=SUMPRODUCT($A$6^($K$1:$DT$1+1),K7:DT7,TRANSPOSE(D7:D120))} -> 0.62952167 | G7: {=SUMPRODUCT($A$6^($K$1:$DT$1),K7:DT7)} -> 12.719756 | H7: =(1-$A$4/$A$9*F7)/$A$15 -> 12.257414 | I7: =G7-(12-1)/2/12-(12^2-1)/12/12^2*(E7+LN(1+$A$4)) -> 12.25774 | K7: 1 | L7: {=IFERROR(K7*(1-INDEX($D7:$D$71,L$1)),0)} -> 0.98447 | M7: {=IFERROR(L7*(1-INDEX($D7:$D$71,M$1)),0)} -> 0.96757649 | N7: {=IFERROR(M7*(1-INDEX($D7:$D$71,N$1)),0)} -> 0.94910546 | O7: {=IFERROR(N7*(1-INDEX($D7:$D$71,O$1)),0)} -> 0.92885155 | P7: {=IFERROR(O7*(1-INDEX($D7:$D$71,P$1)),0)} -> 0.90661484 | Q7: {=IFERROR(P7*(1-INDEX($D7:$D$71,Q$1)),0)} -> 0.88226317 | R7: {=IFERROR(Q7*(1-INDEX($D7:$D$71,R$1)),0)} -> 0.85574234 | S7: {=IFERROR(R7*(1-INDEX($D7:$D$71,S$1)),0)} -> 0.82706641 | ... DX7: {=IFERROR(DW7*(1-INDEX($D7:$D$71,DX$1)),0)} -> 0
A8: i_12 | C8: 70 | D8: 0.01716 | E8: =-1/2*(LN(1-D7)+LN(1-D8)) -> 0.016480396 | F8: {=SUMPRODUCT($A$6^($K$1:$DT$1+1),K8:DT8,TRANSPOSE(D8:D121))} -> 0.64286095 | G8: {=SUMPRODUCT($A$6^($K$1:$DT$1),K8:DT8)} -> 12.261774 | H8: =(1-$A$4/$A$9*F8)/$A$15 -> 11.799399 | I8: =G8-(12-1)/2/12-(12^2-1)/12/12^2*(E8+LN(1+$A$4)) -> 11.799631 | K8: 1 | L8: {=IFERROR(K8*(1-INDEX($D8:$D$71,L$1)),0)} -> 0.98284 | M8: {=IFERROR(L8*(1-INDEX($D8:$D$71,M$1)),0)} -> 0.96407758 | N8: {=IFERROR(M8*(1-INDEX($D8:$D$71,N$1)),0)} -> 0.94350417 | O8: {=IFERROR(N8*(1-INDEX($D8:$D$71,O$1)),0)} -> 0.92091668 | P8: {=IFERROR(O8*(1-INDEX($D8:$D$71,P$1)),0)} -> 0.89618086 | Q8: {=IFERROR(P8*(1-INDEX($D8:$D$71,Q$1)),0)} -> 0.86924166 | R8: {=IFERROR(Q8*(1-INDEX($D8:$D$71,R$1)),0)} -> 0.84011337 | S8: {=IFERROR(R8*(1-INDEX($D8:$D$71,S$1)),0)} -> 0.80884435 | ... DX8: {=IFERROR(DW8*(1-INDEX($D8:$D$71,DX$1)),0)} -> 0
A9: =12*((1+A4)^(1/12)-1) -> 0.029595237 | C9: 71 | D9: 0.01909 | E9: =-1/2*(LN(1-D8)+LN(1-D9)) -> 0.018291753 | F9: {=SUMPRODUCT($A$6^($K$1:$DT$1+1),K9:DT9,TRANSPOSE(D9:D122))} -> 0.65624799 | G9: {=SUMPRODUCT($A$6^($K$1:$DT$1),K9:DT9)} -> 11.802152 | H9: =(1-$A$4/$A$9*F9)/$A$15 -> 11.339744 | I9: =G9-(12-1)/2/12-(12^2-1)/12/12^2*(E9+LN(1+$A$4)) -> 11.339859 | K9: 1 | L9: {=IFERROR(K9*(1-INDEX($D9:$D$71,L$1)),0)} -> 0.98091 | M9: {=IFERROR(L9*(1-INDEX($D9:$D$71,M$1)),0)} -> 0.95997738 | N9: {=IFERROR(M9*(1-INDEX($D9:$D$71,N$1)),0)} -> 0.93699552 | O9: {=IFERROR(N9*(1-INDEX($D9:$D$71,O$1)),0)} -> 0.91182782 | P9: {=IFERROR(O9*(1-INDEX($D9:$D$71,P$1)),0)} -> 0.88441828 | Q9: {=IFERROR(P9*(1-INDEX($D9:$D$71,Q$1)),0)} -> 0.85478142 | R9: {=IFERROR(Q9*(1-INDEX($D9:$D$71,R$1)),0)} -> 0.82296646 | S9: {=IFERROR(R9*(1-INDEX($D9:$D$71,S$1)),0)} -> 0.78901909 | ... DX9: {=IFERROR(DW9*(1-INDEX($D9:$D$71,DX$1)),0)} -> 0
C10: 72 | D10: 0.02134 | E10: =-1/2*(LN(1-D9)+LN(1-D10)) -> 0.020422778 | F10: {=SUMPRODUCT($A$6^($K$1:$DT$1+1),K10:DT10,TRANSPOSE(D10:D123))} -> 0.66962864 | G10: {=SUMPRODUCT($A$6^($K$1:$DT$1),K10:DT10)} -> 11.34275 | H10: =(1-$A$4/$A$9*F10)/$A$15 -> 10.880308 | I10: =G10-(12-1)/2/12-(12^2-1)/12/12^2*(E10+LN(1+$A$4)) -> 10.88028 | K10: 1 | L10: {=IFERROR(K10*(1-INDEX($D10:$D$71,L$1)),0)} -> 0.97866 | M10: {=IFERROR(L10*(1-INDEX($D10:$D$71,M$1)),0)} -> 0.95523088 | N10: {=IFERROR(M10*(1-INDEX($D10:$D$71,N$1)),0)} -> 0.92957338 | O10: {=IFERROR(N10*(1-INDEX($D10:$D$71,O$1)),0)} -> 0.9016304 | P10: {=IFERROR(O10*(1-INDEX($D10:$D$71,P$1)),0)} -> 0.87141677 | Q10: {=IFERROR(P10*(1-INDEX($D10:$D$71,Q$1)),0)} -> 0.83898264 | R10: {=IFERROR(Q10*(1-INDEX($D10:$D$71,R$1)),0)} -> 0.8043746 | S10: {=IFERROR(R10*(1-INDEX($D10:$D$71,S$1)),0)} -> 0.76755838 | ... DX10: {=IFERROR(DW10*(1-INDEX($D10:$D$71,DX$1)),0)} -> 0
A11: d | C11: 73 | D11: 0.02394 | E11: =-1/2*(LN(1-D10)+LN(1-D11)) -> 0.022901104 | F11: {=SUMPRODUCT($A$6^($K$1:$DT$1+1),K11:DT11,TRANSPOSE(D11:D124))} -> 0.68295169 | G11: {=SUMPRODUCT($A$6^($K$1:$DT$1),K11:DT11)} -> 10.885325 | H11: =(1-$A$4/$A$9*F11)/$A$15 -> 10.42285 | I11: =G11-(12-1)/2/12-(12^2-1)/12/12^2*(E11+LN(1+$A$4)) -> 10.422651 | K11: 1 | L11: {=IFERROR(K11*(1-INDEX($D11:$D$71,L$1)),0)} -> 0.97606 | M11: {=IFERROR(L11*(1-INDEX($D11:$D$71,M$1)),0)} -> 0.94984303 | N11: {=IFERROR(M11*(1-INDEX($D11:$D$71,N$1)),0)} -> 0.92129075 | O11: {=IFERROR(N11*(1-INDEX($D11:$D$71,O$1)),0)} -> 0.89041829 | P11: {=IFERROR(O11*(1-INDEX($D11:$D$71,P$1)),0)} -> 0.85727693 | Q11: {=IFERROR(P11*(1-INDEX($D11:$D$71,Q$1)),0)} -> 0.82191425 | R11: {=IFERROR(Q11*(1-INDEX($D11:$D$71,R$1)),0)} -> 0.78429524 | S11: {=IFERROR(R11*(1-INDEX($D11:$D$71,S$1)),0)} -> 0.74436677 | ... DX11: {=IFERROR(DW11*(1-INDEX($D11:$D$71,DX$1)),0)} -> 0
A12: =1-1/(1+A4) -> 0.029126214 | C12: 74 | D12: 0.02686 | E12: =-1/2*(LN(1-D11)+LN(1-D12)) -> 0.025729271 | F12: {=SUMPRODUCT($A$6^($K$1:$DT$1+1),K12:DT12,TRANSPOSE(D12:D125))} -> 0.69616647 | G12: {=SUMPRODUCT($A$6^($K$1:$DT$1),K12:DT12)} -> 10.431618 | H12: =(1-$A$4/$A$9*F12)/$A$15 -> 9.9691103 | I12: =G12-(12-1)/2/12-(12^2-1)/12/12^2*(E12+LN(1+$A$4)) -> 9.9687093 | K12: 1 | L12: {=IFERROR(K12*(1-INDEX($D12:$D$71,L$1)),0)} -> 0.97314 | M12: {=IFERROR(L12*(1-INDEX($D12:$D$71,M$1)),0)} -> 0.94388741 | N12: {=IFERROR(M12*(1-INDEX($D12:$D$71,N$1)),0)} -> 0.91225774 | O12: {=IFERROR(N12*(1-INDEX($D12:$D$71,O$1)),0)} -> 0.87830351 | P12: {=IFERROR(O12*(1-INDEX($D12:$D$71,P$1)),0)} -> 0.84207349 | Q12: {=IFERROR(P12*(1-INDEX($D12:$D$71,Q$1)),0)} -> 0.80353179 | R12: {=IFERROR(Q12*(1-INDEX($D12:$D$71,R$1)),0)} -> 0.76262398 | S12: {=IFERROR(R12*(1-INDEX($D12:$D$71,S$1)),0)} -> 0.71928406 | ... DX12: {=IFERROR(DW12*(1-INDEX($D12:$D$71,DX$1)),0)} -> 0
C13: 75 | D13: 0.03006 | E13: =-1/2*(LN(1-D12)+LN(1-D13)) -> 0.028874194 | F13: {=SUMPRODUCT($A$6^($K$1:$DT$1+1),K13:DT13,TRANSPOSE(D13:D126))} -> 0.70924169 | G13: {=SUMPRODUCT($A$6^($K$1:$DT$1),K13:DT13)} -> 9.9827019 | H13: =(1-$A$4/$A$9*F13)/$A$15 -> 9.5201618 | I13: =G13-(12-1)/2/12-(12^2-1)/12/12^2*(E13+LN(1+$A$4)) -> 9.519533 | K13: 1 | L13: {=IFERROR(K13*(1-INDEX($D13:$D$71,L$1)),0)} -> 0.96994 | M13: {=IFERROR(L13*(1-INDEX($D13:$D$71,M$1)),0)} -> 0.93743731 | N13: {=IFERROR(M13*(1-INDEX($D13:$D$71,N$1)),0)} -> 0.90254589 | O13: {=IFERROR(N13*(1-INDEX($D13:$D$71,O$1)),0)} -> 0.86531588 | P13: {=IFERROR(O13*(1-INDEX($D13:$D$71,P$1)),0)} -> 0.82571037 | Q13: {=IFERROR(P13*(1-INDEX($D13:$D$71,Q$1)),0)} -> 0.78367345 | R13: {=IFERROR(Q13*(1-INDEX($D13:$D$71,R$1)),0)} -> 0.73913729 | S13: {=IFERROR(R13*(1-INDEX($D13:$D$71,S$1)),0)} -> 0.69232773 | ... DX13: {=IFERROR(DW13*(1-INDEX($D13:$D$71,DX$1)),0)} -> 0
A14: d_12 | C14: 76 | D14: 0.03351 | E14: =-1/2*(LN(1-D13)+LN(1-D14)) -> 0.032302696 | F14: {=SUMPRODUCT($A$6^($K$1:$DT$1+1),K14:DT14,TRANSPOSE(D14:D127))} -> 0.72216729 | G14: {=SUMPRODUCT($A$6^($K$1:$DT$1),K14:DT14)} -> 9.538923 | H14: =(1-$A$4/$A$9*F14)/$A$15 -> 9.0763508 | I14: =G14-(12-1)/2/12-(12^2-1)/12/12^2*(E14+LN(1+$A$4)) -> 9.0754704 | K14: 1 | L14: {=IFERROR(K14*(1-INDEX($D14:$D$71,L$1)),0)} -> 0.96649 | M14: {=IFERROR(L14*(1-INDEX($D14:$D$71,M$1)),0)} -> 0.93051724 | N14: {=IFERROR(M14*(1-INDEX($D14:$D$71,N$1)),0)} -> 0.89213341 | O14: {=IFERROR(N14*(1-INDEX($D14:$D$71,O$1)),0)} -> 0.85130046 | P14: {=IFERROR(O14*(1-INDEX($D14:$D$71,P$1)),0)} -> 0.80796075 | Q14: {=IFERROR(P14*(1-INDEX($D14:$D$71,Q$1)),0)} -> 0.76204434 | R14: {=IFERROR(Q14*(1-INDEX($D14:$D$71,R$1)),0)} -> 0.71378408 | S14: {=IFERROR(R14*(1-INDEX($D14:$D$71,S$1)),0)} -> 0.66282703 | ... DX14: {=IFERROR(DW14*(1-INDEX($D14:$D$71,DX$1)),0)} -> 0
A15: =(1-(1+A4)^(-1/12))*12 -> 0.029522427 | C15: 77 | D15: 0.03722 | E15: =-1/2*(LN(1-D14)+LN(1-D15)) -> 0.036007337 | F15: {=SUMPRODUCT($A$6^($K$1:$DT$1+1),K15:DT15,TRANSPOSE(D15:D128))} -> 0.7349505 | G15: {=SUMPRODUCT($A$6^($K$1:$DT$1),K15:DT15)} -> 9.1000328 | H15: =(1-$A$4/$A$9*F15)/$A$15 -> 8.6374289 | I15: =G15-(12-1)/2/12-(12^2-1)/12/12^2*(E15+LN(1+$A$4)) -> 8.6362736 | K15: 1 | L15: {=IFERROR(K15*(1-INDEX($D15:$D$71,L$1)),0)} -> 0.96278 | M15: {=IFERROR(L15*(1-INDEX($D15:$D$71,M$1)),0)} -> 0.92306532 | N15: {=IFERROR(M15*(1-INDEX($D15:$D$71,N$1)),0)} -> 0.88081663 | O15: {=IFERROR(N15*(1-INDEX($D15:$D$71,O$1)),0)} -> 0.83597425 | P15: {=IFERROR(O15*(1-INDEX($D15:$D$71,P$1)),0)} -> 0.78846583 | Q15: {=IFERROR(P15*(1-INDEX($D15:$D$71,Q$1)),0)} -> 0.73853229 | R15: {=IFERROR(Q15*(1-INDEX($D15:$D$71,R$1)),0)} -> 0.68580847 | S15: {=IFERROR(R15*(1-INDEX($D15:$D$71,S$1)),0)} -> 0.63051174 | ... DX15: {=IFERROR(DW15*(1-INDEX($D15:$D$71,DX$1)),0)} -> 0
C16: 78 | D16: 0.04125 | E16: =-1/2*(LN(1-D15)+LN(1-D16)) -> 0.040027636 | F16: {=SUMPRODUCT($A$6^($K$1:$DT$1+1),K16:DT16,TRANSPOSE(D16:D129))} -> 0.74760487 | G16: {=SUMPRODUCT($A$6^($K$1:$DT$1),K16:DT16)} -> 8.6655662 | H16: =(1-$A$4/$A$9*F16)/$A$15 -> 8.2029308 | I16: =G16-(12-1)/2/12-(12^2-1)/12/12^2*(E16+LN(1+$A$4)) -> 8.2014742 | K16: 1 | L16: {=IFERROR(K16*(1-INDEX($D16:$D$71,L$1)),0)} -> 0.95875 | M16: {=IFERROR(L16*(1-INDEX($D16:$D$71,M$1)),0)} -> 0.91486801 | N16: {=IFERROR(M16*(1-INDEX($D16:$D$71,N$1)),0)} -> 0.86829208 | O16: {=IFERROR(N16*(1-INDEX($D16:$D$71,O$1)),0)} -> 0.81894704 | P16: {=IFERROR(O16*(1-INDEX($D16:$D$71,P$1)),0)} -> 0.76708313 | Q16: {=IFERROR(P16*(1-INDEX($D16:$D$71,Q$1)),0)} -> 0.71232106 | R16: {=IFERROR(Q16*(1-INDEX($D16:$D$71,R$1)),0)} -> 0.65488662 | S16: {=IFERROR(R16*(1-INDEX($D16:$D$71,S$1)),0)} -> 0.59511511 | ... DX16: {=IFERROR(DW16*(1-INDEX($D16:$D$71,DX$1)),0)} -> 0
C17: 79 | D17: 0.04577 | E17: =-1/2*(LN(1-D16)+LN(1-D17)) -> 0.044487736 | F17: {=SUMPRODUCT($A$6^($K$1:$DT$1+1),K17:DT17,TRANSPOSE(D17:D130))} -> 0.76013874 | G17: {=SUMPRODUCT($A$6^($K$1:$DT$1),K17:DT17)} -> 8.2352367 | H17: =(1-$A$4/$A$9*F17)/$A$15 -> 7.7725702 | I17: =G17-(12-1)/2/12-(12^2-1)/12/12^2*(E17+LN(1+$A$4)) -> 7.7707756 | K17: 1 | L17: {=IFERROR(K17*(1-INDEX($D17:$D$71,L$1)),0)} -> 0.95423 | M17: {=IFERROR(L17*(1-INDEX($D17:$D$71,M$1)),0)} -> 0.90565015 | N17: {=IFERROR(M17*(1-INDEX($D17:$D$71,N$1)),0)} -> 0.85418205 | O17: {=IFERROR(N17*(1-INDEX($D17:$D$71,O$1)),0)} -> 0.8000867 | P17: {=IFERROR(O17*(1-INDEX($D17:$D$71,P$1)),0)} -> 0.74296851 | Q17: {=IFERROR(P17*(1-INDEX($D17:$D$71,Q$1)),0)} -> 0.68306296 | R17: {=IFERROR(Q17*(1-INDEX($D17:$D$71,R$1)),0)} -> 0.62071981 | S17: {=IFERROR(R17*(1-INDEX($D17:$D$71,S$1)),0)} -> 0.55649393 | ... DX17: {=IFERROR(DW17*(1-INDEX($D17:$D$71,DX$1)),0)} -> 0
C18: 80 | D18: 0.05091 | E18: =-1/2*(LN(1-D17)+LN(1-D18)) -> 0.049551097 | F18: {=SUMPRODUCT($A$6^($K$1:$DT$1+1),K18:DT18,TRANSPOSE(D18:D131))} -> 0.77253167 | G18: {=SUMPRODUCT($A$6^($K$1:$DT$1),K18:DT18)} -> 7.8097458 | H18: =(1-$A$4/$A$9*F18)/$A$15 -> 7.3470486 | I18: =G18-(12-1)/2/12-(12^2-1)/12/12^2*(E18+LN(1+$A$4)) -> 7.3448658 | K18: 1 | L18: {=IFERROR(K18*(1-INDEX($D18:$D$71,L$1)),0)} -> 0.94909 | M18: {=IFERROR(L18*(1-INDEX($D18:$D$71,M$1)),0)} -> 0.89515322 | N18: {=IFERROR(M18*(1-INDEX($D18:$D$71,N$1)),0)} -> 0.83846316 | O18: {=IFERROR(N18*(1-INDEX($D18:$D$71,O$1)),0)} -> 0.77860528 | P18: {=IFERROR(O18*(1-INDEX($D18:$D$71,P$1)),0)} -> 0.71582633 | Q18: {=IFERROR(P18*(1-INDEX($D18:$D$71,Q$1)),0)} -> 0.65049286 | R18: {=IFERROR(Q18*(1-INDEX($D18:$D$71,R$1)),0)} -> 0.58318637 | S18: {=IFERROR(R18*(1-INDEX($D18:$D$71,S$1)),0)} -> 0.5148136 | ... DX18: {=IFERROR(DW18*(1-INDEX($D18:$D$71,DX$1)),0)} -> 0
C19: 81 | D19: 0.05683 | E19: =-1/2*(LN(1-D18)+LN(1-D19)) -> 0.055380193 | F19: {=SUMPRODUCT($A$6^($K$1:$DT$1+1),K19:DT19,TRANSPOSE(D19:D132))} -> 0.78474921 | G19: {=SUMPRODUCT($A$6^($K$1:$DT$1),K19:DT19)} -> 7.3902772 | H19: =(1-$A$4/$A$9*F19)/$A$15 -> 6.9275496 | I19: =G19-(12-1)/2/12-(12^2-1)/12/12^2*(E19+LN(1+$A$4)) -> 6.9249148 | K19: 1 | L19: {=IFERROR(K19*(1-INDEX($D19:$D$71,L$1)),0)} -> 0.94317 | M19: {=IFERROR(L19*(1-INDEX($D19:$D$71,M$1)),0)} -> 0.88343904 | N19: {=IFERROR(M19*(1-INDEX($D19:$D$71,N$1)),0)} -> 0.82037033 | O19: {=IFERROR(N19*(1-INDEX($D19:$D$71,O$1)),0)} -> 0.75422387 | P19: {=IFERROR(O19*(1-INDEX($D19:$D$71,P$1)),0)} -> 0.68538586 | Q19: {=IFERROR(P19*(1-INDEX($D19:$D$71,Q$1)),0)} -> 0.61446898 | R19: {=IFERROR(Q19*(1-INDEX($D19:$D$71,R$1)),0)} -> 0.54242864 | S19: {=IFERROR(R19*(1-INDEX($D19:$D$71,S$1)),0)} -> 0.47051345 | ... DX19: {=IFERROR(DW19*(1-INDEX($D19:$D$71,DX$1)),0)} -> 0
C20: 82 | D20: 0.06333 | E20: =-1/2*(LN(1-D19)+LN(1-D20)) -> 0.061966492 | F20: {=SUMPRODUCT($A$6^($K$1:$DT$1+1),K20:DT20,TRANSPOSE(D20:D133))} -> 0.79674044 | G20: {=SUMPRODUCT($A$6^($K$1:$DT$1),K20:DT20)} -> 6.9785781 | H20: =(1-$A$4/$A$9*F20)/$A$15 -> 6.5158208 | I20: =G20-(12-1)/2/12-(12^2-1)/12/12^2*(E20+LN(1+$A$4)) -> 6.5126707 | K20: 1 | L20: {=IFERROR(K20*(1-INDEX($D20:$D$71,L$1)),0)} -> 0.93667 | M20: {=IFERROR(L20*(1-INDEX($D20:$D$71,M$1)),0)} -> 0.86980113 | N20: {=IFERROR(M20*(1-INDEX($D20:$D$71,N$1)),0)} -> 0.79966906 | O20: {=IFERROR(N20*(1-INDEX($D20:$D$71,O$1)),0)} -> 0.72668327 | P20: {=IFERROR(O20*(1-INDEX($D20:$D$71,P$1)),0)} -> 0.65149335 | Q20: {=IFERROR(P20*(1-INDEX($D20:$D$71,Q$1)),0)} -> 0.57511227 | R20: {=IFERROR(Q20*(1-INDEX($D20:$D$71,R$1)),0)} -> 0.49886389 | S20: {=IFERROR(R20*(1-INDEX($D20:$D$71,S$1)),0)} -> 0.4245631 | ... DX20: {=IFERROR(DW20*(1-INDEX($D20:$D$71,DX$1)),0)} -> 0
C21: 83 | D21: 0.07139 | E21: =-1/2*(LN(1-D20)+LN(1-D21)) -> 0.069745341 | F21: {=SUMPRODUCT($A$6^($K$1:$DT$1+1),K21:DT21,TRANSPOSE(D21:D134))} -> 0.80851597 | G21: {=SUMPRODUCT($A$6^($K$1:$DT$1),K21:DT21)} -> 6.5742849 | H21: =(1-$A$4/$A$9*F21)/$A$15 -> 6.1114984 | I21: =G21-(12-1)/2/12-(12^2-1)/12/12^2*(E21+LN(1+$A$4)) -> 6.1077337 | K21: 1 | L21: {=IFERROR(K21*(1-INDEX($D21:$D$71,L$1)),0)} -> 0.92861 | M21: {=IFERROR(L21*(1-INDEX($D21:$D$71,M$1)),0)} -> 0.85373618 | N21: {=IFERROR(M21*(1-INDEX($D21:$D$71,N$1)),0)} -> 0.77581567 | O21: {=IFERROR(N21*(1-INDEX($D21:$D$71,O$1)),0)} -> 0.69554203 | P21: {=IFERROR(O21*(1-INDEX($D21:$D$71,P$1)),0)} -> 0.61399668 | Q21: {=IFERROR(P21*(1-INDEX($D21:$D$71,Q$1)),0)} -> 0.532593 | R21: {=IFERROR(Q21*(1-INDEX($D21:$D$71,R$1)),0)} -> 0.4532686 | S21: {=IFERROR(R21*(1-INDEX($D21:$D$71,S$1)),0)} -> 0.37797162 | ... DX21: {=IFERROR(DW21*(1-INDEX($D21:$D$71,DX$1)),0)} -> 0
C22: 84 | D22: 0.08063 | E22: =-1/2*(LN(1-D21)+LN(1-D22)) -> 0.07906653 | F22: {=SUMPRODUCT($A$6^($K$1:$DT$1+1),K22:DT22,TRANSPOSE(D22:D135))} -> 0.8199152 | G22: {=SUMPRODUCT($A$6^($K$1:$DT$1),K22:DT22)} -> 6.1829115 | H22: =(1-$A$4/$A$9*F22)/$A$15 -> 5.7200967 | I22: =G22-(12-1)/2/12-(12^2-1)/12/12^2*(E22+LN(1+$A$4)) -> 5.715589 | K22: 1 | L22: {=IFERROR(K22*(1-INDEX($D22:$D$71,L$1)),0)} -> 0.91937 | M22: {=IFERROR(L22*(1-INDEX($D22:$D$71,M$1)),0)} -> 0.8354591 | N22: {=IFERROR(M22*(1-INDEX($D22:$D$71,N$1)),0)} -> 0.74901415 | O22: {=IFERROR(N22*(1-INDEX($D22:$D$71,O$1)),0)} -> 0.66119973 | P22: {=IFERROR(O22*(1-INDEX($D22:$D$71,P$1)),0)} -> 0.57353787 | Q22: {=IFERROR(P22*(1-INDEX($D22:$D$71,Q$1)),0)} -> 0.48811514 | R22: {=IFERROR(Q22*(1-INDEX($D22:$D$71,R$1)),0)} -> 0.40702945 | S22: {=IFERROR(R22*(1-INDEX($D22:$D$71,S$1)),0)} -> 0.3323192 | ... DX22: {=IFERROR(DW22*(1-INDEX($D22:$D$71,DX$1)),0)} -> 0
C23: 85 | D23: 0.09127 | E23: =-1/2*(LN(1-D22)+LN(1-D23)) -> 0.089886942 | F23: {=SUMPRODUCT($A$6^($K$1:$DT$1+1),K23:DT23,TRANSPOSE(D23:D136))} -> 0.8308762 | G23: {=SUMPRODUCT($A$6^($K$1:$DT$1),K23:DT23)} -> 5.8065837 | H23: =(1-$A$4/$A$9*F23)/$A$15 -> 5.3437416 | I23: =G23-(12-1)/2/12-(12^2-1)/12/12^2*(E23+LN(1+$A$4)) -> 5.3383657 | K23: 1 | L23: {=IFERROR(K23*(1-INDEX($D23:$D$71,L$1)),0)} -> 0.90873 | M23: {=IFERROR(L23*(1-INDEX($D23:$D$71,M$1)),0)} -> 0.81470371 | N23: {=IFERROR(M23*(1-INDEX($D23:$D$71,N$1)),0)} -> 0.71918784 | O23: {=IFERROR(N23*(1-INDEX($D23:$D$71,O$1)),0)} -> 0.62383792 | P23: {=IFERROR(O23*(1-INDEX($D23:$D$71,P$1)),0)} -> 0.5309235 | Q23: {=IFERROR(P23*(1-INDEX($D23:$D$71,Q$1)),0)} -> 0.44272649 | R23: {=IFERROR(Q23*(1-INDEX($D23:$D$71,R$1)),0)} -> 0.36146404 | S23: {=IFERROR(R23*(1-INDEX($D23:$D$71,S$1)),0)} -> 0.28890014 | ... DX23: {=IFERROR(DW23*(1-INDEX($D23:$D$71,DX$1)),0)} -> 0
C24: 86 | D24: 0.10347 | E24: =-1/2*(LN(1-D23)+LN(1-D24)) -> 0.10246539 | F24: {=SUMPRODUCT($A$6^($K$1:$DT$1+1),K24:DT24,TRANSPOSE(D24:D137))} -> 0.84131974 | G24: {=SUMPRODUCT($A$6^($K$1:$DT$1),K24:DT24)} -> 5.4480222 | H24: =(1-$A$4/$A$9*F24)/$A$15 -> 4.9851542 | I24: =G24-(12-1)/2/12-(12^2-1)/12/12^2*(E24+LN(1+$A$4)) -> 4.9787633 | K24: 1 | L24: {=IFERROR(K24*(1-INDEX($D24:$D$71,L$1)),0)} -> 0.89653 | M24: {=IFERROR(L24*(1-INDEX($D24:$D$71,M$1)),0)} -> 0.79142082 | N24: {=IFERROR(M24*(1-INDEX($D24:$D$71,N$1)),0)} -> 0.68649425 | O24: {=IFERROR(N24*(1-INDEX($D24:$D$71,O$1)),0)} -> 0.5842478 | P24: {=IFERROR(O24*(1-INDEX($D24:$D$71,P$1)),0)} -> 0.48719255 | Q24: {=IFERROR(P24*(1-INDEX($D24:$D$71,Q$1)),0)} -> 0.39776836 | R24: {=IFERROR(Q24*(1-INDEX($D24:$D$71,R$1)),0)} -> 0.31791636 | S24: {=IFERROR(R24*(1-INDEX($D24:$D$71,S$1)),0)} -> 0.2487314 | ... DX24: {=IFERROR(DW24*(1-INDEX($D24:$D$71,DX$1)),0)} -> 0
C25: 87 | D25: 0.11724 | E25: =-1/2*(LN(1-D24)+LN(1-D25)) -> 0.11696272 | F25: {=SUMPRODUCT($A$6^($K$1:$DT$1+1),K25:DT25,TRANSPOSE(D25:D138))} -> 0.85115873 | G25: {=SUMPRODUCT($A$6^($K$1:$DT$1),K25:DT25)} -> 5.1102171 | H25: =(1-$A$4/$A$9*F25)/$A$15 -> 4.6473246 | I25: =G25-(12-1)/2/12-(12^2-1)/12/12^2*(E25+LN(1+$A$4)) -> 4.6397584 | K25: 1 | L25: {=IFERROR(K25*(1-INDEX($D25:$D$71,L$1)),0)} -> 0.88276 | M25: {=IFERROR(L25*(1-INDEX($D25:$D$71,M$1)),0)} -> 0.76572368 | N25: {=IFERROR(M25*(1-INDEX($D25:$D$71,N$1)),0)} -> 0.65167679 | O25: {=IFERROR(N25*(1-INDEX($D25:$D$71,O$1)),0)} -> 0.54342025 | P25: {=IFERROR(O25*(1-INDEX($D25:$D$71,P$1)),0)} -> 0.44367546 | Q25: {=IFERROR(P25*(1-INDEX($D25:$D$71,Q$1)),0)} -> 0.35460761 | R25: {=IFERROR(Q25*(1-INDEX($D25:$D$71,R$1)),0)} -> 0.2774379 | S25: {=IFERROR(R25*(1-INDEX($D25:$D$71,S$1)),0)} -> 0.21270887 | ... DX25: {=IFERROR(DW25*(1-INDEX($D25:$D$71,DX$1)),0)} -> 0
C26: 88 | D26: 0.13258 | E26: =-1/2*(LN(1-D25)+LN(1-D26)) -> 0.13346695 | F26: {=SUMPRODUCT($A$6^($K$1:$DT$1+1),K26:DT26,TRANSPOSE(D26:D139))} -> 0.86031706 | G26: {=SUMPRODUCT($A$6^($K$1:$DT$1),K26:DT26)} -> 4.7957809 | H26: =(1-$A$4/$A$9*F26)/$A$15 -> 4.3328658 | I26: =G26-(12-1)/2/12-(12^2-1)/12/12^2*(E26+LN(1+$A$4)) -> 4.3239565 | K26: 1 | L26: {=IFERROR(K26*(1-INDEX($D26:$D$71,L$1)),0)} -> 0.86742 | M26: {=IFERROR(L26*(1-INDEX($D26:$D$71,M$1)),0)} -> 0.73822647 | N26: {=IFERROR(M26*(1-INDEX($D26:$D$71,N$1)),0)} -> 0.61559228 | O26: {=IFERROR(N26*(1-INDEX($D26:$D$71,O$1)),0)} -> 0.50260032 | P26: {=IFERROR(O26*(1-INDEX($D26:$D$71,P$1)),0)} -> 0.40170331 | Q26: {=IFERROR(P26*(1-INDEX($D26:$D$71,Q$1)),0)} -> 0.31428463 | R26: {=IFERROR(Q26*(1-INDEX($D26:$D$71,R$1)),0)} -> 0.24095889 | S26: {=IFERROR(R26*(1-INDEX($D26:$D$71,S$1)),0)} -> 0.18140831 | ... DX26: {=IFERROR(DW26*(1-INDEX($D26:$D$71,DX$1)),0)} -> 0
C27: 89 | D27: 0.14894 | E27: =-1/2*(LN(1-D26)+LN(1-D27)) -> 0.15175232 | F27: {=SUMPRODUCT($A$6^($K$1:$DT$1+1),K27:DT27,TRANSPOSE(D27:D140))} -> 0.86872169 | G27: {=SUMPRODUCT($A$6^($K$1:$DT$1),K27:DT27)} -> 4.5072218 | H27: =(1-$A$4/$A$9*F27)/$A$15 -> 4.0442858 | I27: =G27-(12-1)/2/12-(12^2-1)/12/12^2*(E27+LN(1+$A$4)) -> 4.0338842 | K27: 1 | L27: {=IFERROR(K27*(1-INDEX($D27:$D$71,L$1)),0)} -> 0.85106 | M27: {=IFERROR(L27*(1-INDEX($D27:$D$71,M$1)),0)} -> 0.70968191 | N27: {=IFERROR(M27*(1-INDEX($D27:$D$71,N$1)),0)} -> 0.5794198 | O27: {=IFERROR(N27*(1-INDEX($D27:$D$71,O$1)),0)} -> 0.46310127 | P27: {=IFERROR(O27*(1-INDEX($D27:$D$71,P$1)),0)} -> 0.36232117 | Q27: {=IFERROR(P27*(1-INDEX($D27:$D$71,Q$1)),0)} -> 0.27778802 | R27: {=IFERROR(Q27*(1-INDEX($D27:$D$71,R$1)),0)} -> 0.20913549 | S27: {=IFERROR(R27*(1-INDEX($D27:$D$71,S$1)),0)} -> 0.15369158 | ... DX27: {=IFERROR(DW27*(1-INDEX($D27:$D$71,DX$1)),0)} -> 0
... C71: 133 | D71: 0 | E71: =-1/2*(LN(1-D70)+LN(1-D71)) -> 0 | F71: {=SUMPRODUCT($A$6^($K$1:$DT$1+1),K71:DT71,TRANSPOSE(D71:D184))} -> 0 | G71: {=SUMPRODUCT($A$6^($K$1:$DT$1),K71:DT71)} -> 1.9708738 | H71: =(1-$A$4/$A$9*F71)/$A$15 -> 33.872554 | I71: =G71-(12-1)/2/12-(12^2-1)/12/12^2*(E71+LN(1+$A$4)) -> 1.5100943 | K71: 1 | L71: {=IFERROR(K71*(1-INDEX($D71:$D$71,L$1)),0)} -> 1 | M71: {=IFERROR(L71*(1-INDEX($D71:$D$71,M$1)),0)} -> 0 | N71: {=IFERROR(M71*(1-INDEX($D71:$D$71,N$1)),0)} -> 0 | O71: {=IFERROR(N71*(1-INDEX($D71:$D$71,O$1)),0)} -> 0 | P71: {=IFERROR(O71*(1-INDEX($D71:$D$71,P$1)),0)} -> 0 | Q71: {=IFERROR(P71*(1-INDEX($D71:$D$71,Q$1)),0)} -> 0 | R71: {=IFERROR(Q71*(1-INDEX($D71:$D$71,R$1)),0)} -> 0 | S71: {=IFERROR(R71*(1-INDEX($D71:$D$71,S$1)),0)} -> 0 | ... DX71: {=IFERROR(DW71*(1-INDEX($D71:$D$71,DX$1)),0)} -> 0

Sheet Payments (CSO Male)
A1: Age | B1: B(65,0) | C1: Income | D1: Residentship | E1: 10yr bond | F1: i_12 | G1: d | H1: d_12 | DN1: mu_75 | DO1: A_75 | DP1: a_75 | DQ1: (UDD) | DR1: (WH3)
A2: 65 | B2: =727.67*D2/40 -> 727.67 | C2: 0 | D2: 40 | E2: 0.03 | F2: =12*((1+E2)^(1/12)-1) -> 0.029595237 | G2: =1-1/(1+E2) -> 0.029126214 | H2: =(1-(1+E2)^(-1/12))*12 -> 0.029522427 | DN2: =CSOM!E13 -> 0.028874194 | DO2: =CSOM!F13 -> 0.70924169 | DP2: =CSOM!G13 -> 9.9827019 | DQ2: =CSOM!H13 -> 9.5201618 | DR2: =CSOM!I13 -> 9.519533
A3: k | B3: 0 | C3: 1 | D3: 2 | E3: 3 | F3: 4 | G3: 5 | H3: 6 | I3: 7 | J3: 8 | K3: 9 | L3: 10 | M3: 11 | N3: 12 | O3: 13 | P3: 14 | Q3: 15 | R3: 16 | S3: 17 | T3: 18 | U3: 19 | V3: 20 | W3: 21 | X3: 22 | Y3: 23 | Z3: 24 | AA3: 25 | AB3: 26 | AC3: 27 | AD3: 28 | AE3: 29 | AF3: 30 | AG3: 31 | AH3: 32 | AI3: 33 | AJ3: 34 | AK3: 35 | AL3: 36 | AM3: 37 | AN3: 38 | AO3: 39 | AP3: 40 | AQ3: 41 | AR3: 42 | AS3: 43 | AT3: 44 | AU3: 45 | AV3: 46 | AW3: 47 | AX3: 48 | AY3: 49 | AZ3: 50 | BA3: 51 | BB3: 52 | BC3: 53 | BD3: 54 | BE3: 55 | BF3: 56 | BG3: 57 | BH3: 58 | BI3: 59 | BJ3: 60 | BK3: 61 | BL3: 62 | BM3: 63 | BN3: 64 | BO3: 65 | BP3: 66 | BQ3: 67 | BR3: 68 | BS3: 69 | BT3: 70 | BU3: 71 | BV3: 72 | BW3: 73 | BX3: 74 | BY3: 75 | BZ3: 76 | CA3: 77 | CB3: 78 | CC3: 79 | CD3: 80 | CE3: 81 | CF3: 82 | CG3: 83 | CH3: 84 | CI3: 85 | CJ3: 86 | CK3: 87 | CL3: 88 | CM3: 89 | CN3: 90 | CO3: 91 | CP3: 92 | CQ3: 93 | CR3: 94 | CS3: 95 | CT3: 96 | CU3: 97 | CV3: 98 | CW3: 99 | CX3: 100 | CY3: 101 | CZ3: 102 | DA3: 103 | DB3: 104 | DC3: 105 | DD3: 106 | DE3: 107 | DF3: 108 | DG3: 109 | DH3: 110 | DI3: 111 | DJ3: 112 | DK3: 113 | DL3: 114 | DM3: 115 | DN3: 116 | DO3: 117 | DP3: 118 | DQ3: 119 | DR3: 120
A4: k/12_p_65 | B4: {=INDEX(CSOM!$K$3:$DX$71,1,1+FLOOR(B3/12,1))*(1-(B3/12-FLOOR(B3/12,1))*INDEX(CSOM!$D$3:$D$71,1+FLOOR(B3/12,1)))} -> 1 | C4: {=INDEX(CSOM!$K$3:$DX$71,1,1+FLOOR(C3/12,1))*(1-(C3/12-FLOOR(C3/12,1))*INDEX(CSOM!$D$3:$D$71,1+FLOOR(C3/12,1)))} -> 0.99911333 | D4: {=INDEX(CSOM!$K$3:$DX$71,1,1+FLOOR(D3/12,1))*(1-(D3/12-FLOOR(D3/12,1))*INDEX(CSOM!$D$3:$D$71,1+FLOOR(D3/12,1)))} -> 0.99822667 | E4: {=INDEX(CSOM!$K$3:$DX$71,1,1+FLOOR(E3/12,1))*(1-(E3/12-FLOOR(E3/12,1))*INDEX(CSOM!$D$3:$D$71,1+FLOOR(E3/12,1)))} -> 0.99734 | F4: {=INDEX(CSOM!$K$3:$DX$71,1,1+FLOOR(F3/12,1))*(1-(F3/12-FLOOR(F3/12,1))*INDEX(CSOM!$D$3:$D$71,1+FLOOR(F3/12,1)))} -> 0.99645333 | G4: {=INDEX(CSOM!$K$3:$DX$71,1,1+FLOOR(G3/12,1))*(1-(G3/12-FLOOR(G3/12,1))*INDEX(CSOM!$D$3:$D$71,1+FLOOR(G3/12,1)))} -> 0.99556667 | H4: {=INDEX(CSOM!$K$3:$DX$71,1,1+FLOOR(H3/12,1))*(1-(H3/12-FLOOR(H3/12,1))*INDEX(CSOM!$D$3:$D$71,1+FLOOR(H3/12,1)))} -> 0.99468 | I4: {=INDEX(CSOM!$K$3:$DX$71,1,1+FLOOR(I3/12,1))*(1-(I3/12-FLOOR(I3/12,1))*INDEX(CSOM!$D$3:$D$71,1+FLOOR(I3/12,1)))} -> 0.99379333 | ... DR4: {=INDEX(CSOM!$K$3:$DX$71,1,1+FLOOR(DR3/12,1))*(1-(DR3/12-FLOOR(DR3/12,1))*INDEX(CSOM!$D$3:$D$71,1+FLOOR(DR3/12,1)))} -> 0.83949422
A5: k/12_E_65 | B5: =B4/(1+$F$2/12)^B3 -> 1 | C5: =C4/(1+$F$2/12)^C3 -> 0.99665531 | D5: =D4/(1+$F$2/12)^D3 -> 0.99332103 | E5: =E4/(1+$F$2/12)^E3 -> 0.98999712 | F5: =F4/(1+$F$2/12)^F3 -> 0.98668355 | G5: =G4/(1+$F$2/12)^G3 -> 0.9833803 | H5: =H4/(1+$F$2/12)^H3 -> 0.98008733 | I5: =I4/(1+$F$2/12)^I3 -> 0.9768046 | ... DR5: =DR4/(1+$F$2/12)^DR3 -> 0.62466254
A6: Received Age | B6: 65 | C6: 65.083333 | D6: 65.166667 | E6: 65.25 | F6: 65.333333 | G6: 65.416667 | H6: 65.5 | I6: 65.583333 | J6: 65.666667 | K6: 65.75 | L6: 65.833333 | M6: 65.916667 | N6: 66 | O6: 66.083333 | P6: 66.166667 | Q6: 66.25 | R6: 66.333333 | S6: 66.416667 | T6: 66.5 | U6: 66.583333 | V6: 66.666667 | W6: 66.75 | X6: 66.833333 | Y6: 66.916667 | Z6: 67 | AA6: 67.083333 | AB6: 67.166667 | AC6: 67.25 | AD6: 67.333333 | AE6: 67.416667 | AF6: 67.5 | AG6: 67.583333 | AH6: 67.666667 | AI6: 67.75 | AJ6: 67.833333 | AK6: 67.916667 | AL6: 68 | AM6: 68.083333 | AN6: 68.166667 | AO6: 68.25 | AP6: 68.333333 | AQ6: 68.416667 | AR6: 68.5 | AS6: 68.583333 | AT6: 68.666667 | AU6: 68.75 | AV6: 68.833333 | AW6: 68.916667 | AX6: 69 | AY6: 69.083333 | AZ6: 69.166667 | BA6: 69.25 | BB6: 69.333333 | BC6: 69.416667 | BD6: 69.5 | BE6: 69.583333 | BF6: 69.666667 | BG6: 69.75 | BH6: 69.833333 | BI6: 69.916667 | BJ6: 70 | BK6: 70.083333 | BL6: 70.166667 | BM6: 70.25 | BN6: 70.333333 | BO6: 70.416667 | BP6: 70.5 | BQ6: 70.583333 | BR6: 70.666667 | BS6: 70.75 | BT6: 70.833333 | BU6: 70.916667 | BV6: 71 | BW6: 71.083333 | BX6: 71.166667 | BY6: 71.25 | BZ6: 71.333333 | CA6: 71.416667 | CB6: 71.5 | CC6: 71.583333 | CD6: 71.666667 | CE6: 71.75 | CF6: 71.833333 | CG6: 71.916667 | CH6: 72 | CI6: 72.083333 | CJ6: 72.166667 | CK6: 72.25 | CL6: 72.333333 | CM6: 72.416667 | CN6: 72.5 | CO6: 72.583333 | CP6: 72.666667 | CQ6: 72.75 | CR6: 72.833333 | CS6: 72.916667 | CT6: 73 | CU6: 73.083333 | CV6: 73.166667 | CW6: 73.25 | CX6: 73.333333 | CY6: 73.416667 | CZ6: 73.5 | DA6: 73.583333 | DB6: 73.666667 | DC6: 73.75 | DD6: 73.833333 | DE6: 73.916667 | DF6: 74 | DG6: 74.083333 | DH6: 74.166667 | DI6: 74.25 | DJ6: 74.333333 | DK6: 74.416667 | DL6: 74.5 | DM6: 74.583333 | DN6: 74.666667 | DO6: 74.75 | DP6: 74.833333 | DQ6: 74.916667 | DR6: 75
A7: Deferred Age | DS7: PV
A8: =A2 -> 65 | B8: =$B$2*IF($A$2+B$3/12<$A8,0,1)*(1+0.072*MIN($A8-$A$2,5))*IF(B$3>=120,1.1,1)*IF($C$2<=148450,1,0) -> 727.67 | C8: =$B$2*IF($A$2+C$3/12<$A8,0,1)*(1+0.072*MIN($A8-$A$2,5))*IF(C$3>=120,1.1,1)*IF($C$2<=148450,1,0) -> 727.67 | D8: =$B$2*IF($A$2+D$3/12<$A8,0,1)*(1+0.072*MIN($A8-$A$2,5))*IF(D$3>=120,1.1,1)*IF($C$2<=148450,1,0) -> 727.67 | E8: =$B$2*IF($A$2+E$3/12<$A8,0,1)*(1+0.072*MIN($A8-$A$2,5))*IF(E$3>=120,1.1,1)*IF($C$2<=148450,1,0) -> 727.67 | F8: =$B$2*IF($A$2+F$3/12<$A8,0,1)*(1+0.072*MIN($A8-$A$2,5))*IF(F$3>=120,1.1,1)*IF($C$2<=148450,1,0) -> 727.67 | G8: =$B$2*IF($A$2+G$3/12<$A8,0,1)*(1+0.072*MIN($A8-$A$2,5))*IF(G$3>=120,1.1,1)*IF($C$2<=148450,1,0) -> 727.67 | H8: =$B$2*IF($A$2+H$3/12<$A8,0,1)*(1+0.072*MIN($A8-$A$2,5))*IF(H$3>=120,1.1,1)*IF($C$2<=148450,1,0) -> 727.67 | I8: =$B$2*IF($A$2+I$3/12<$A8,0,1)*(1+0.072*MIN($A8-$A$2,5))*IF(I$3>=120,1.1,1)*IF($C$2<=148450,1,0) -> 727.67 | ... DR8: =$B$2*IF($A$2+DR$3/12<$A8,0,1)*(1+0.072*MIN($A8-$A$2,5))*IF(DR$3>=120,1.1,1)*IF($C$2<=148450,1,0) -> 800.437 | DS8: =SUMPRODUCT($B$5:$DQ$5,B8:DQ8)+DR8*12*$DQ$2 -> 162258.75
A9: =A8+1/12 -> 65.083333 | B9: =$B$2*IF($A$2+B$3/12<$A9,0,1)*(1+0.072*MIN($A9-$A$2,5))*IF(B$3>=120,1.1,1)*IF($C$2<=148450,1,0) -> 0 | C9: =$B$2*IF($A$2+C$3/12<$A9,0,1)*(1+0.072*MIN($A9-$A$2,5))*IF(C$3>=120,1.1,1)*IF($C$2<=148450,1,0) -> 732.03602 | D9: =$B$2*IF($A$2+D$3/12<$A9,0,1)*(1+0.072*MIN($A9-$A$2,5))*IF(D$3>=120,1.1,1)*IF($C$2<=148450,1,0) -> 732.03602 | E9: =$B$2*IF($A$2+E$3/12<$A9,0,1)*(1+0.072*MIN($A9-$A$2,5))*IF(E$3>=120,1.1,1)*IF($C$2<=148450,1,0) -> 732.03602 | F9: =$B$2*IF($A$2+F$3/12<$A9,0,1)*(1+0.072*MIN($A9-$A$2,5))*IF(F$3>=120,1.1,1)*IF($C$2<=148450,1,0) -> 732.03602 | G9: =$B$2*IF($A$2+G$3/12<$A9,0,1)*(1+0.072*MIN($A9-$A$2,5))*IF(G$3>=120,1.1,1)*IF($C$2<=148450,1,0) -> 732.03602 | H9: =$B$2*IF($A$2+H$3/12<$A9,0,1)*(1+0.072*MIN($A9-$A$2,5))*IF(H$3>=120,1.1,1)*IF($C$2<=148450,1,0) -> 732.03602 | I9: =$B$2*IF($A$2+I$3/12<$A9,0,1)*(1+0.072*MIN($A9-$A$2,5))*IF(I$3>=120,1.1,1)*IF($C$2<=148450,1,0) -> 732.03602 | ... DR9: =$B$2*IF($A$2+DR$3/12<$A9,0,1)*(1+0.072*MIN($A9-$A$2,5))*IF(DR$3>=120,1.1,1)*IF($C$2<=148450,1,0) -> 805.23962 | DS9: =SUMPRODUCT($B$5:$DQ$5,B9:DQ9)+DR9*12*$DQ$2 -> 162500.27
A10: =A9+1/12 -> 65.166667 | B10: =$B$2*IF($A$2+B$3/12<$A10,0,1)*(1+0.072*MIN($A10-$A$2,5))*IF(B$3>=120,1.1,1)*IF($C$2<=148450,1,0) -> 0 | C10: =$B$2*IF($A$2+C$3/12<$A10,0,1)*(1+0.072*MIN($A10-$A$2,5))*IF(C$3>=120,1.1,1)*IF($C$2<=148450,1,0) -> 0 | D10: =$B$2*IF($A$2+D$3/12<$A10,0,1)*(1+0.072*MIN($A10-$A$2,5))*IF(D$3>=120,1.1,1)*IF($C$2<=148450,1,0) -> 736.40204 | E10: =$B$2*IF($A$2+E$3/12<$A10,0,1)*(1+0.072*MIN($A10-$A$2,5))*IF(E$3>=120,1.1,1)*IF($C$2<=148450,1,0) -> 736.40204 | F10: =$B$2*IF($A$2+F$3/12<$A10,0,1)*(1+0.072*MIN($A10-$A$2,5))*IF(F$3>=120,1.1,1)*IF($C$2<=148450,1,0) -> 736.40204 | G10: =$B$2*IF($A$2+G$3/12<$A10,0,1)*(1+0.072*MIN($A10-$A$2,5))*IF(G$3>=120,1.1,1)*IF($C$2<=148450,1,0) -> 736.40204 | H10: =$B$2*IF($A$2+H$3/12<$A10,0,1)*(1+0.072*MIN($A10-$A$2,5))*IF(H$3>=120,1.1,1)*IF($C$2<=148450,1,0) -> 736.40204 | I10: =$B$2*IF($A$2+I$3/12<$A10,0,1)*(1+0.072*MIN($A10-$A$2,5))*IF(I$3>=120,1.1,1)*IF($C$2<=148450,1,0) -> 736.40204 | ... DR10: =$B$2*IF($A$2+DR$3/12<$A10,0,1)*(1+0.072*MIN($A10-$A$2,5))*IF(DR$3>=120,1.1,1)*IF($C$2<=148450,1,0) -> 810.04224 | DS10: =SUMPRODUCT($B$5:$DQ$5,B10:DQ10)+DR10*12*$DQ$2 -> 162735.52
A11: =A10+1/12 -> 65.25 | B11: =$B$2*IF($A$2+B$3/12<$A11,0,1)*(1+0.072*MIN($A11-$A$2,5))*IF(B$3>=120,1.1,1)*IF($C$2<=148450,1,0) -> 0 | C11: =$B$2*IF($A$2+C$3/12<$A11,0,1)*(1+0.072*MIN($A11-$A$2,5))*IF(C$3>=120,1.1,1)*IF($C$2<=148450,1,0) -> 0 | D11: =$B$2*IF($A$2+D$3/12<$A11,0,1)*(1+0.072*MIN($A11-$A$2,5))*IF(D$3>=120,1.1,1)*IF($C$2<=148450,1,0) -> 0 | E11: =$B$2*IF($A$2+E$3/12<$A11,0,1)*(1+0.072*MIN($A11-$A$2,5))*IF(E$3>=120,1.1,1)*IF($C$2<=148450,1,0) -> 740.76806 | F11: =$B$2*IF($A$2+F$3/12<$A11,0,1)*(1+0.072*MIN($A11-$A$2,5))*IF(F$3>=120,1.1,1)*IF($C$2<=148450,1,0) -> 740.76806 | G11: =$B$2*IF($A$2+G$3/12<$A11,0,1)*(1+0.072*MIN($A11-$A$2,5))*IF(G$3>=120,1.1,1)*IF($C$2<=148450,1,0) -> 740.76806 | H11: =$B$2*IF($A$2+H$3/12<$A11,0,1)*(1+0.072*MIN($A11-$A$2,5))*IF(H$3>=120,1.1,1)*IF($C$2<=148450,1,0) -> 740.76806 | I11: =$B$2*IF($A$2+I$3/12<$A11,0,1)*(1+0.072*MIN($A11-$A$2,5))*IF(I$3>=120,1.1,1)*IF($C$2<=148450,1,0) -> 740.76806 | ... DR11: =$B$2*IF($A$2+DR$3/12<$A11,0,1)*(1+0.072*MIN($A11-$A$2,5))*IF(DR$3>=120,1.1,1)*IF($C$2<=148450,1,0) -> 814.84487 | DS11: =SUMPRODUCT($B$5:$DQ$5,B11:DQ11)+DR11*12*$DQ$2 -> 162964.53
A12: =A11+1/12 -> 65.333333 | B12: =$B$2*IF($A$2+B$3/12<$A12,0,1)*(1+0.072*MIN($A12-$A$2,5))*IF(B$3>=120,1.1,1)*IF($C$2<=148450,1,0) -> 0 | C12: =$B$2*IF($A$2+C$3/12<$A12,0,1)*(1+0.072*MIN($A12-$A$2,5))*IF(C$3>=120,1.1,1)*IF($C$2<=148450,1,0) -> 0 | D12: =$B$2*IF($A$2+D$3/12<$A12,0,1)*(1+0.072*MIN($A12-$A$2,5))*IF(D$3>=120,1.1,1)*IF($C$2<=148450,1,0) -> 0 | E12: =$B$2*IF($A$2+E$3/12<$A12,0,1)*(1+0.072*MIN($A12-$A$2,5))*IF(E$3>=120,1.1,1)*IF($C$2<=148450,1,0) -> 0 | F12: =$B$2*IF($A$2+F$3/12<$A12,0,1)*(1+0.072*MIN($A12-$A$2,5))*IF(F$3>=120,1.1,1)*IF($C$2<=148450,1,0) -> 745.13408 | G12: =$B$2*IF($A$2+G$3/12<$A12,0,1)*(1+0.072*MIN($A12-$A$2,5))*IF(G$3>=120,1.1,1)*IF($C$2<=148450,1,0) -> 745.13408 | H12: =$B$2*IF($A$2+H$3/12<$A12,0,1)*(1+0.072*MIN($A12-$A$2,5))*IF(H$3>=120,1.1,1)*IF($C$2<=148450,1,0) -> 745.13408 | I12: =$B$2*IF($A$2+I$3/12<$A12,0,1)*(1+0.072*MIN($A12-$A$2,5))*IF(I$3>=120,1.1,1)*IF($C$2<=148450,1,0) -> 745.13408 | ... DR12: =$B$2*IF($A$2+DR$3/12<$A12,0,1)*(1+0.072*MIN($A12-$A$2,5))*IF(DR$3>=120,1.1,1)*IF($C$2<=148450,1,0) -> 819.64749 | DS12: =SUMPRODUCT($B$5:$DQ$5,B12:DQ12)+DR12*12*$DQ$2 -> 163187.35
A13: =A12+1/12 -> 65.416667 | B13: =$B$2*IF($A$2+B$3/12<$A13,0,1)*(1+0.072*MIN($A13-$A$2,5))*IF(B$3>=120,1.1,1)*IF($C$2<=148450,1,0) -> 0 | C13: =$B$2*IF($A$2+C$3/12<$A13,0,1)*(1+0.072*MIN($A13-$A$2,5))*IF(C$3>=120,1.1,1)*IF($C$2<=148450,1,0) -> 0 | D13: =$B$2*IF($A$2+D$3/12<$A13,0,1)*(1+0.072*MIN($A13-$A$2,5))*IF(D$3>=120,1.1,1)*IF($C$2<=148450,1,0) -> 0 | E13: =$B$2*IF($A$2+E$3/12<$A13,0,1)*(1+0.072*MIN($A13-$A$2,5))*IF(E$3>=120,1.1,1)*IF($C$2<=148450,1,0) -> 0 | F13: =$B$2*IF($A$2+F$3/12<$A13,0,1)*(1+0.072*MIN($A13-$A$2,5))*IF(F$3>=120,1.1,1)*IF($C$2<=148450,1,0) -> 0 | G13: =$B$2*IF($A$2+G$3/12<$A13,0,1)*(1+0.072*MIN($A13-$A$2,5))*IF(G$3>=120,1.1,1)*IF($C$2<=148450,1,0) -> 749.5001 | H13: =$B$2*IF($A$2+H$3/12<$A13,0,1)*(1+0.072*MIN($A13-$A$2,5))*IF(H$3>=120,1.1,1)*IF($C$2<=148450,1,0) -> 749.5001 | I13: =$B$2*IF($A$2+I$3/12<$A13,0,1)*(1+0.072*MIN($A13-$A$2,5))*IF(I$3>=120,1.1,1)*IF($C$2<=148450,1,0) -> 749.5001 | ... DR13: =$B$2*IF($A$2+DR$3/12<$A13,0,1)*(1+0.072*MIN($A13-$A$2,5))*IF(DR$3>=120,1.1,1)*IF($C$2<=148450,1,0) -> 824.45011 | DS13: =SUMPRODUCT($B$5:$DQ$5,B13:DQ13)+DR13*12*$DQ$2 -> 163404.01
A14: =A13+1/12 -> 65.5 | B14: =$B$2*IF($A$2+B$3/12<$A14,0,1)*(1+0.072*MIN($A14-$A$2,5))*IF(B$3>=120,1.1,1)*IF($C$2<=148450,1,0) -> 0 | C14: =$B$2*IF($A$2+C$3/12<$A14,0,1)*(1+0.072*MIN($A14-$A$2,5))*IF(C$3>=120,1.1,1)*IF($C$2<=148450,1,0) -> 0 | D14: =$B$2*IF($A$2+D$3/12<$A14,0,1)*(1+0.072*MIN($A14-$A$2,5))*IF(D$3>=120,1.1,1)*IF($C$2<=148450,1,0) -> 0 | E14: =$B$2*IF($A$2+E$3/12<$A14,0,1)*(1+0.072*MIN($A14-$A$2,5))*IF(E$3>=120,1.1,1)*IF($C$2<=148450,1,0) -> 0 | F14: =$B$2*IF($A$2+F$3/12<$A14,0,1)*(1+0.072*MIN($A14-$A$2,5))*IF(F$3>=120,1.1,1)*IF($C$2<=148450,1,0) -> 0 | G14: =$B$2*IF($A$2+G$3/12<$A14,0,1)*(1+0.072*MIN($A14-$A$2,5))*IF(G$3>=120,1.1,1)*IF($C$2<=148450,1,0) -> 0 | H14: =$B$2*IF($A$2+H$3/12<$A14,0,1)*(1+0.072*MIN($A14-$A$2,5))*IF(H$3>=120,1.1,1)*IF($C$2<=148450,1,0) -> 753.86612 | I14: =$B$2*IF($A$2+I$3/12<$A14,0,1)*(1+0.072*MIN($A14-$A$2,5))*IF(I$3>=120,1.1,1)*IF($C$2<=148450,1,0) -> 753.86612 | ... DR14: =$B$2*IF($A$2+DR$3/12<$A14,0,1)*(1+0.072*MIN($A14-$A$2,5))*IF(DR$3>=120,1.1,1)*IF($C$2<=148450,1,0) -> 829.25273 | DS14: =SUMPRODUCT($B$5:$DQ$5,B14:DQ14)+DR14*12*$DQ$2 -> 163614.54
A15: =A14+1/12 -> 65.583333 | B15: =$B$2*IF($A$2+B$3/12<$A15,0,1)*(1+0.072*MIN($A15-$A$2,5))*IF(B$3>=120,1.1,1)*IF($C$2<=148450,1,0) -> 0 | C15: =$B$2*IF($A$2+C$3/12<$A15,0,1)*(1+0.072*MIN($A15-$A$2,5))*IF(C$3>=120,1.1,1)*IF($C$2<=148450,1,0) -> 0 | D15: =$B$2*IF($A$2+D$3/12<$A15,0,1)*(1+0.072*MIN($A15-$A$2,5))*IF(D$3>=120,1.1,1)*IF($C$2<=148450,1,0) -> 0 | E15: =$B$2*IF($A$2+E$3/12<$A15,0,1)*(1+0.072*MIN($A15-$A$2,5))*IF(E$3>=120,1.1,1)*IF($C$2<=148450,1,0) -> 0 | F15: =$B$2*IF($A$2+F$3/12<$A15,0,1)*(1+0.072*MIN($A15-$A$2,5))*IF(F$3>=120,1.1,1)*IF($C$2<=148450,1,0) -> 0 | G15: =$B$2*IF($A$2+G$3/12<$A15,0,1)*(1+0.072*MIN($A15-$A$2,5))*IF(G$3>=120,1.1,1)*IF($C$2<=148450,1,0) -> 0 | H15: =$B$2*IF($A$2+H$3/12<$A15,0,1)*(1+0.072*MIN($A15-$A$2,5))*IF(H$3>=120,1.1,1)*IF($C$2<=148450,1,0) -> 0 | I15: =$B$2*IF($A$2+I$3/12<$A15,0,1)*(1+0.072*MIN($A15-$A$2,5))*IF(I$3>=120,1.1,1)*IF($C$2<=148450,1,0) -> 758.23214 | ... DR15: =$B$2*IF($A$2+DR$3/12<$A15,0,1)*(1+0.072*MIN($A15-$A$2,5))*IF(DR$3>=120,1.1,1)*IF($C$2<=148450,1,0) -> 834.05535 | DS15: =SUMPRODUCT($B$5:$DQ$5,B15:DQ15)+DR15*12*$DQ$2 -> 163818.98
A16: =A15+1/12 -> 65.666667 | B16: =$B$2*IF($A$2+B$3/12<$A16,0,1)*(1+0.072*MIN($A16-$A$2,5))*IF(B$3>=120,1.1,1)*IF($C$2<=148450,1,0) -> 0 | C16: =$B$2*IF($A$2+C$3/12<$A16,0,1)*(1+0.072*MIN($A16-$A$2,5))*IF(C$3>=120,1.1,1)*IF($C$2<=148450,1,0) -> 0 | D16: =$B$2*IF($A$2+D$3/12<$A16,0,1)*(1+0.072*MIN($A16-$A$2,5))*IF(D$3>=120,1.1,1)*IF($C$2<=148450,1,0) -> 0 | E16: =$B$2*IF($A$2+E$3/12<$A16,0,1)*(1+0.072*MIN($A16-$A$2,5))*IF(E$3>=120,1.1,1)*IF($C$2<=148450,1,0) -> 0 | F16: =$B$2*IF($A$2+F$3/12<$A16,0,1)*(1+0.072*MIN($A16-$A$2,5))*IF(F$3>=120,1.1,1)*IF($C$2<=148450,1,0) -> 0 | G16: =$B$2*IF($A$2+G$3/12<$A16,0,1)*(1+0.072*MIN($A16-$A$2,5))*IF(G$3>=120,1.1,1)*IF($C$2<=148450,1,0) -> 0 | H16: =$B$2*IF($A$2+H$3/12<$A16,0,1)*(1+0.072*MIN($A16-$A$2,5))*IF(H$3>=120,1.1,1)*IF($C$2<=148450,1,0) -> 0 | I16: =$B$2*IF($A$2+I$3/12<$A16,0,1)*(1+0.072*MIN($A16-$A$2,5))*IF(I$3>=120,1.1,1)*IF($C$2<=148450,1,0) -> 0 | ... DR16: =$B$2*IF($A$2+DR$3/12<$A16,0,1)*(1+0.072*MIN($A16-$A$2,5))*IF(DR$3>=120,1.1,1)*IF($C$2<=148450,1,0) -> 838.85798 | DS16: =SUMPRODUCT($B$5:$DQ$5,B16:DQ16)+DR16*12*$DQ$2 -> 164017.36
A17: =A16+1/12 -> 65.75 | B17: =$B$2*IF($A$2+B$3/12<$A17,0,1)*(1+0.072*MIN($A17-$A$2,5))*IF(B$3>=120,1.1,1)*IF($C$2<=148450,1,0) -> 0 | C17: =$B$2*IF($A$2+C$3/12<$A17,0,1)*(1+0.072*MIN($A17-$A$2,5))*IF(C$3>=120,1.1,1)*IF($C$2<=148450,1,0) -> 0 | D17: =$B$2*IF($A$2+D$3/12<$A17,0,1)*(1+0.072*MIN($A17-$A$2,5))*IF(D$3>=120,1.1,1)*IF($C$2<=148450,1,0) -> 0 | E17: =$B$2*IF($A$2+E$3/12<$A17,0,1)*(1+0.072*MIN($A17-$A$2,5))*IF(E$3>=120,1.1,1)*IF($C$2<=148450,1,0) -> 0 | F17: =$B$2*IF($A$2+F$3/12<$A17,0,1)*(1+0.072*MIN($A17-$A$2,5))*IF(F$3>=120,1.1,1)*IF($C$2<=148450,1,0) -> 0 | G17: =$B$2*IF($A$2+G$3/12<$A17,0,1)*(1+0.072*MIN($A17-$A$2,5))*IF(G$3>=120,1.1,1)*IF($C$2<=148450,1,0) -> 0 | H17: =$B$2*IF($A$2+H$3/12<$A17,0,1)*(1+0.072*MIN($A17-$A$2,5))*IF(H$3>=120,1.1,1)*IF($C$2<=148450,1,0) -> 0 | I17: =$B$2*IF($A$2+I$3/12<$A17,0,1)*(1+0.072*MIN($A17-$A$2,5))*IF(I$3>=120,1.1,1)*IF($C$2<=148450,1,0) -> 0 | ... DR17: =$B$2*IF($A$2+DR$3/12<$A17,0,1)*(1+0.072*MIN($A17-$A$2,5))*IF(DR$3>=120,1.1,1)*IF($C$2<=148450,1,0) -> 843.6606 | DS17: =SUMPRODUCT($B$5:$DQ$5,B17:DQ17)+DR17*12*$DQ$2 -> 164209.73
A18: =A17+1/12 -> 65.833333 | B18: =$B$2*IF($A$2+B$3/12<$A18,0,1)*(1+0.072*MIN($A18-$A$2,5))*IF(B$3>=120,1.1,1)*IF($C$2<=148450,1,0) -> 0 | C18: =$B$2*IF($A$2+C$3/12<$A18,0,1)*(1+0.072*MIN($A18-$A$2,5))*IF(C$3>=120,1.1,1)*IF($C$2<=148450,1,0) -> 0 | D18: =$B$2*IF($A$2+D$3/12<$A18,0,1)*(1+0.072*MIN($A18-$A$2,5))*IF(D$3>=120,1.1,1)*IF($C$2<=148450,1,0) -> 0 | E18: =$B$2*IF($A$2+E$3/12<$A18,0,1)*(1+0.072*MIN($A18-$A$2,5))*IF(E$3>=120,1.1,1)*IF($C$2<=148450,1,0) -> 0 | F18: =$B$2*IF($A$2+F$3/12<$A18,0,1)*(1+0.072*MIN($A18-$A$2,5))*IF(F$3>=120,1.1,1)*IF($C$2<=148450,1,0) -> 0 | G18: =$B$2*IF($A$2+G$3/12<$A18,0,1)*(1+0.072*MIN($A18-$A$2,5))*IF(G$3>=120,1.1,1)*IF($C$2<=148450,1,0) -> 0 | H18: =$B$2*IF($A$2+H$3/12<$A18,0,1)*(1+0.072*MIN($A18-$A$2,5))*IF(H$3>=120,1.1,1)*IF($C$2<=148450,1,0) -> 0 | I18: =$B$2*IF($A$2+I$3/12<$A18,0,1)*(1+0.072*MIN($A18-$A$2,5))*IF(I$3>=120,1.1,1)*IF($C$2<=148450,1,0) -> 0 | ... DR18: =$B$2*IF($A$2+DR$3/12<$A18,0,1)*(1+0.072*MIN($A18-$A$2,5))*IF(DR$3>=120,1.1,1)*IF($C$2<=148450,1,0) -> 848.46322 | DS18: =SUMPRODUCT($B$5:$DQ$5,B18:DQ18)+DR18*12*$DQ$2 -> 164396.11
A19: =A18+1/12 -> 65.916667 | B19: =$B$2*IF($A$2+B$3/12<$A19,0,1)*(1+0.072*MIN($A19-$A$2,5))*IF(B$3>=120,1.1,1)*IF($C$2<=148450,1,0) -> 0 | C19: =$B$2*IF($A$2+C$3/12<$A19,0,1)*(1+0.072*MIN($A19-$A$2,5))*IF(C$3>=120,1.1,1)*IF($C$2<=148450,1,0) -> 0 | D19: =$B$2*IF($A$2+D$3/12<$A19,0,1)*(1+0.072*MIN($A19-$A$2,5))*IF(D$3>=120,1.1,1)*IF($C$2<=148450,1,0) -> 0 | E19: =$B$2*IF($A$2+E$3/12<$A19,0,1)*(1+0.072*MIN($A19-$A$2,5))*IF(E$3>=120,1.1,1)*IF($C$2<=148450,1,0) -> 0 | F19: =$B$2*IF($A$2+F$3/12<$A19,0,1)*(1+0.072*MIN($A19-$A$2,5))*IF(F$3>=120,1.1,1)*IF($C$2<=148450,1,0) -> 0 | G19: =$B$2*IF($A$2+G$3/12<$A19,0,1)*(1+0.072*MIN($A19-$A$2,5))*IF(G$3>=120,1.1,1)*IF($C$2<=148450,1,0) -> 0 | H19: =$B$2*IF($A$2+H$3/12<$A19,0,1)*(1+0.072*MIN($A19-$A$2,5))*IF(H$3>=120,1.1,1)*IF($C$2<=148450,1,0) -> 0 | I19: =$B$2*IF($A$2+I$3/12<$A19,0,1)*(1+0.072*MIN($A19-$A$2,5))*IF(I$3>=120,1.1,1)*IF($C$2<=148450,1,0) -> 0 | ... DR19: =$B$2*IF($A$2+DR$3/12<$A19,0,1)*(1+0.072*MIN($A19-$A$2,5))*IF(DR$3>=120,1.1,1)*IF($C$2<=148450,1,0) -> 853.26584 | DS19: =SUMPRODUCT($B$5:$DQ$5,B19:DQ19)+DR19*12*$DQ$2 -> 164576.54
A20: =A19+1/12 -> 66 | B20: =$B$2*IF($A$2+B$3/12<$A20,0,1)*(1+0.072*MIN($A20-$A$2,5))*IF(B$3>=120,1.1,1)*IF($C$2<=148450,1,0) -> 0 | C20: =$B$2*IF($A$2+C$3/12<$A20,0,1)*(1+0.072*MIN($A20-$A$2,5))*IF(C$3>=120,1.1,1)*IF($C$2<=148450,1,0) -> 0 | D20: =$B$2*IF($A$2+D$3/12<$A20,0,1)*(1+0.072*MIN($A20-$A$2,5))*IF(D$3>=120,1.1,1)*IF($C$2<=148450,1,0) -> 0 | E20: =$B$2*IF($A$2+E$3/12<$A20,0,1)*(1+0.072*MIN($A20-$A$2,5))*IF(E$3>=120,1.1,1)*IF($C$2<=148450,1,0) -> 0 | F20: =$B$2*IF($A$2+F$3/12<$A20,0,1)*(1+0.072*MIN($A20-$A$2,5))*IF(F$3>=120,1.1,1)*IF($C$2<=148450,1,0) -> 0 | G20: =$B$2*IF($A$2+G$3/12<$A20,0,1)*(1+0.072*MIN($A20-$A$2,5))*IF(G$3>=120,1.1,1)*IF($C$2<=148450,1,0) -> 0 | H20: =$B$2*IF($A$2+H$3/12<$A20,0,1)*(1+0.072*MIN($A20-$A$2,5))*IF(H$3>=120,1.1,1)*IF($C$2<=148450,1,0) -> 0 | I20: =$B$2*IF($A$2+I$3/12<$A20,0,1)*(1+0.072*MIN($A20-$A$2,5))*IF(I$3>=120,1.1,1)*IF($C$2<=148450,1,0) -> 0 | ... DR20: =$B$2*IF($A$2+DR$3/12<$A20,0,1)*(1+0.072*MIN($A20-$A$2,5))*IF(DR$3>=120,1.1,1)*IF($C$2<=148450,1,0) -> 858.06846 | DS20: =SUMPRODUCT($B$5:$DQ$5,B20:DQ20)+DR20*12*$DQ$2 -> 164751.06
... A128: =A127+1/12 -> 75 | B128: =$B$2*IF($A$2+B$3/12<$A128,0,1)*(1+0.072*MIN($A128-$A$2,5))*IF(B$3>=120,1.1,1)*IF($C$2<=148450,1,0) -> 0 | C128: =$B$2*IF($A$2+C$3/12<$A128,0,1)*(1+0.072*MIN($A128-$A$2,5))*IF(C$3>=120,1.1,1)*IF($C$2<=148450,1,0) -> 0 | D128: =$B$2*IF($A$2+D$3/12<$A128,0,1)*(1+0.072*MIN($A128-$A$2,5))*IF(D$3>=120,1.1,1)*IF($C$2<=148450,1,0) -> 0 | E128: =$B$2*IF($A$2+E$3/12<$A128,0,1)*(1+0.072*MIN($A128-$A$2,5))*IF(E$3>=120,1.1,1)*IF($C$2<=148450,1,0) -> 0 | F128: =$B$2*IF($A$2+F$3/12<$A128,0,1)*(1+0.072*MIN($A128-$A$2,5))*IF(F$3>=120,1.1,1)*IF($C$2<=148450,1,0) -> 0 | G128: =$B$2*IF($A$2+G$3/12<$A128,0,1)*(1+0.072*MIN($A128-$A$2,5))*IF(G$3>=120,1.1,1)*IF($C$2<=148450,1,0) -> 0 | H128: =$B$2*IF($A$2+H$3/12<$A128,0,1)*(1+0.072*MIN($A128-$A$2,5))*IF(H$3>=120,1.1,1)*IF($C$2<=148450,1,0) -> 0 | I128: =$B$2*IF($A$2+I$3/12<$A128,0,1)*(1+0.072*MIN($A128-$A$2,5))*IF(I$3>=120,1.1,1)*IF($C$2<=148450,1,0) -> 0 | ... DR128: =$B$2*IF($A$2+DR$3/12<$A128,0,1)*(1+0.072*MIN($A128-$A$2,5))*IF(DR$3>=120,1.1,1)*IF($C$2<=148450,1,0) -> 1088.5943 | DS128: =SUMPRODUCT($B$5:$DQ$5,B128:DQ128)+DR128*12*$DQ$2 -> 124363.13

Sheet CSOF
C1: x | D1: q_x | E1: mu_x | F1: A_x | G1: a_x | H1: a(12)_x (UDD) | I1: a(12)_x (WH3) | J1: npx | K1: 0 | L1: 1 | M1: 2 | N1: 3 | O1: 4 | P1: 5 | Q1: 6 | R1: 7 | S1: 8 | T1: 9 | U1: 10 | V1: 11 | W1: 12 | X1: 13 | Y1: 14 | Z1: 15 | AA1: 16 | AB1: 17 | AC1: 18 | AD1: 19 | AE1: 20 | AF1: 21 | AG1: 22 | AH1: 23 | AI1: 24 | AJ1: 25 | AK1: 26 | AL1: 27 | AM1: 28 | AN1: 29 | AO1: 30 | AP1: 31 | AQ1: 32 | AR1: 33 | AS1: 34 | AT1: 35 | AU1: 36 | AV1: 37 | AW1: 38 | AX1: 39 | AY1: 40 | AZ1: 41 | BA1: 42 | BB1: 43 | BC1: 44 | BD1: 45 | BE1: 46 | BF1: 47 | BG1: 48 | BH1: 49 | BI1: 50 | BJ1: 51 | BK1: 52 | BL1: 53 | BM1: 54 | BN1: 55 | BO1: 56 | BP1: 57 | BQ1: 58 | BR1: 59 | BS1: 60 | BT1: 61 | BU1: 62 | BV1: 63 | BW1: 64 | BX1: 65 | BY1: 66 | BZ1: 67 | CA1: 68 | CB1: 69 | CC1: 70 | CD1: 71 | CE1: 72 | CF1: 73 | CG1: 74 | CH1: 75 | CI1: 76 | CJ1: 77 | CK1: 78 | CL1: 79 | CM1: 80 | CN1: 81 | CO1: 82 | CP1: 83 | CQ1: 84 | CR1: 85 | CS1: 86 | CT1: 87 | CU1: 88 | CV1: 89 | CW1: 90 | CX1: 91 | CY1: 92 | CZ1: 93 | DA1: 94 | DB1: 95 | DC1: 96 | DD1: 97 | DE1: 98 | DF1: 99 | DG1: 100 | DH1: 101 | DI1: 102 | DJ1: 103 | DK1: 104 | DL1: 105 | DM1: 106 | DN1: 107 | DO1: 108 | DP1: 109 | DQ1: 110 | DR1: 111 | DS1: 112 | DT1: 113 | DU1: 114 | DV1: 115 | DW1: 116 | DX1: 117
C2: 64 | D2: 0.00747 | K2: 1 | L2: {=IFERROR(K2*(1-INDEX($D2:$D$71,L$1)),0)} -> 0.99253 | M2: {=IFERROR(L2*(1-INDEX($D2:$D$71,M$1)),0)} -> 0.98428208 | N2: {=IFERROR(M2*(1-INDEX($D2:$D$71,N$1)),0)} -> 0.97518731 | O2: {=IFERROR(N2*(1-INDEX($D2:$D$71,O$1)),0)} -> 0.96517214 | P2: {=IFERROR(O2*(1-INDEX($D2:$D$71,P$1)),0)} -> 0.95415952 | Q2: {=IFERROR(P2*(1-INDEX($D2:$D$71,Q$1)),0)} -> 0.94207986 | R2: {=IFERROR(Q2*(1-INDEX($D2:$D$71,R$1)),0)} -> 0.92885306 | S2: {=IFERROR(R2*(1-INDEX($D2:$D$71,S$1)),0)} -> 0.91442797 | ... DX2: {=IFERROR(DW2*(1-INDEX($D2:$D$71,DX$1)),0)} -> 0
A3: i | C3: 65 | D3: 0.00831 | E3: =-1/2*(LN(1-D2)+LN(1-D3)) -> 0.0079213804 | F3: {=SUMPRODUCT($A$6^($K$1:$DT$1+1),K3:DT3,TRANSPOSE(D3:D116))} -> 0.54976512 | G3: {=SUMPRODUCT($A$6^($K$1:$DT$1),K3:DT3)} -> 15.458064 | H3: =(1-$A$4/$A$9*F3)/$A$15 -> 14.99592 | I3: =G3-(12-1)/2/12-(12^2-1)/12/12^2*(E3+LN(1+$A$4)) -> 14.996629 | K3: 1 | L3: {=IFERROR(K3*(1-INDEX($D3:$D$71,L$1)),0)} -> 0.99169 | M3: {=IFERROR(L3*(1-INDEX($D3:$D$71,M$1)),0)} -> 0.98252678 | N3: {=IFERROR(M3*(1-INDEX($D3:$D$71,N$1)),0)} -> 0.97243623 | O3: {=IFERROR(N3*(1-INDEX($D3:$D$71,O$1)),0)} -> 0.96134074 | P3: {=IFERROR(O3*(1-INDEX($D3:$D$71,P$1)),0)} -> 0.94917016 | Q3: {=IFERROR(P3*(1-INDEX($D3:$D$71,Q$1)),0)} -> 0.93584381 | R3: {=IFERROR(Q3*(1-INDEX($D3:$D$71,R$1)),0)} -> 0.92131016 | S3: {=IFERROR(R3*(1-INDEX($D3:$D$71,S$1)),0)} -> 0.90549126 | ... DX3: {=IFERROR(DW3*(1-INDEX($D3:$D$71,DX$1)),0)} -> 0
A4: =Payments!K2 -> 0.03 | C4: 66 | D4: 0.00924 | E4: =-1/2*(LN(1-D3)+LN(1-D4)) -> 0.0088138371 | F4: {=SUMPRODUCT($A$6^($K$1:$DT$1+1),K4:DT4,TRANSPOSE(D4:D117))} -> 0.56262348 | G4: {=SUMPRODUCT($A$6^($K$1:$DT$1),K4:DT4)} -> 15.016594 | H4: =(1-$A$4/$A$9*F4)/$A$15 -> 14.554418 | I4: =G4-(12-1)/2/12-(12^2-1)/12/12^2*(E4+LN(1+$A$4)) -> 14.555085 | K4: 1 | L4: {=IFERROR(K4*(1-INDEX($D4:$D$71,L$1)),0)} -> 0.99076 | M4: {=IFERROR(L4*(1-INDEX($D4:$D$71,M$1)),0)} -> 0.98058489 | N4: {=IFERROR(M4*(1-INDEX($D4:$D$71,N$1)),0)} -> 0.96939642 | O4: {=IFERROR(N4*(1-INDEX($D4:$D$71,O$1)),0)} -> 0.95712386 | P4: {=IFERROR(O4*(1-INDEX($D4:$D$71,P$1)),0)} -> 0.94368584 | Q4: {=IFERROR(P4*(1-INDEX($D4:$D$71,Q$1)),0)} -> 0.9290304 | R4: {=IFERROR(Q4*(1-INDEX($D4:$D$71,R$1)),0)} -> 0.91307895 | S4: {=IFERROR(R4*(1-INDEX($D4:$D$71,S$1)),0)} -> 0.89575784 | ... DX4: {=IFERROR(DW4*(1-INDEX($D4:$D$71,DX$1)),0)} -> 0
A5: v | C5: 67 | D5: 0.01027 | E5: =-1/2*(LN(1-D4)+LN(1-D5)) -> 0.009803027 | F5: {=SUMPRODUCT($A$6^($K$1:$DT$1+1),K5:DT5,TRANSPOSE(D5:D118))} -> 0.57558055 | G5: {=SUMPRODUCT($A$6^($K$1:$DT$1),K5:DT5)} -> 14.571735 | H5: =(1-$A$4/$A$9*F5)/$A$15 -> 14.109526 | I5: =G5-(12-1)/2/12-(12^2-1)/12/12^2*(E5+LN(1+$A$4)) -> 14.110144 | K5: 1 | L5: {=IFERROR(K5*(1-INDEX($D5:$D$71,L$1)),0)} -> 0.98973 | M5: {=IFERROR(L5*(1-INDEX($D5:$D$71,M$1)),0)} -> 0.97843718 | N5: {=IFERROR(M5*(1-INDEX($D5:$D$71,N$1)),0)} -> 0.96605017 | O5: {=IFERROR(N5*(1-INDEX($D5:$D$71,O$1)),0)} -> 0.95248682 | P5: {=IFERROR(O5*(1-INDEX($D5:$D$71,P$1)),0)} -> 0.9376947 | Q5: {=IFERROR(P5*(1-INDEX($D5:$D$71,Q$1)),0)} -> 0.92159448 | R5: {=IFERROR(Q5*(1-INDEX($D5:$D$71,R$1)),0)} -> 0.90411184 | S5: {=IFERROR(R5*(1-INDEX($D5:$D$71,S$1)),0)} -> 0.88514357 | ... DX5: {=IFERROR(DW5*(1-INDEX($D5:$D$71,DX$1)),0)} -> 0
A6: =(1+A4)^-1 -> 0.97087379 | C6: 68 | D6: 0.01141 | E6: =-1/2*(LN(1-D5)+LN(1-D6)) -> 0.010899347 | F6: {=SUMPRODUCT($A$6^($K$1:$DT$1+1),K6:DT6,TRANSPOSE(D6:D119))} -> 0.58862312 | G6: {=SUMPRODUCT($A$6^($K$1:$DT$1),K6:DT6)} -> 14.123939 | H6: =(1-$A$4/$A$9*F6)/$A$15 -> 13.661699 | I6: =G6-(12-1)/2/12-(12^2-1)/12/12^2*(E6+LN(1+$A$4)) -> 13.662258 | K6: 1 | L6: {=IFERROR(K6*(1-INDEX($D6:$D$71,L$1)),0)} -> 0.98859 | M6: {=IFERROR(L6*(1-INDEX($D6:$D$71,M$1)),0)} -> 0.97607445 | N6: {=IFERROR(M6*(1-INDEX($D6:$D$71,N$1)),0)} -> 0.96237037 | O6: {=IFERROR(N6*(1-INDEX($D6:$D$71,O$1)),0)} -> 0.94742475 | P6: {=IFERROR(O6*(1-INDEX($D6:$D$71,P$1)),0)} -> 0.93115747 | Q6: {=IFERROR(P6*(1-INDEX($D6:$D$71,Q$1)),0)} -> 0.91349341 | R6: {=IFERROR(Q6*(1-INDEX($D6:$D$71,R$1)),0)} -> 0.89432832 | S6: {=IFERROR(R6*(1-INDEX($D6:$D$71,S$1)),0)} -> 0.87353519 | ... DX6: {=IFERROR(DW6*(1-INDEX($D6:$D$71,DX$1)),0)} -> 0
C7: 69 | D7: 0.01266 | E7: =-1/2*(LN(1-D6)+LN(1-D7)) -> 0.012108207 | F7: {=SUMPRODUCT($A$6^($K$1:$DT$1+1),K7:DT7,TRANSPOSE(D7:D120))} -> 0.60173764 | G7: {=SUMPRODUCT($A$6^($K$1:$DT$1),K7:DT7)} -> 13.673674 | H7: =(1-$A$4/$A$9*F7)/$A$15 -> 13.211401 | I7: =G7-(12-1)/2/12-(12^2-1)/12/12^2*(E7+LN(1+$A$4)) -> 13.211893 | K7: 1 | L7: {=IFERROR(K7*(1-INDEX($D7:$D$71,L$1)),0)} -> 0.98734 | M7: {=IFERROR(L7*(1-INDEX($D7:$D$71,M$1)),0)} -> 0.97347775 | N7: {=IFERROR(M7*(1-INDEX($D7:$D$71,N$1)),0)} -> 0.95835964 | O7: {=IFERROR(N7*(1-INDEX($D7:$D$71,O$1)),0)} -> 0.9419046 | P7: {=IFERROR(O7*(1-INDEX($D7:$D$71,P$1)),0)} -> 0.92403667 | Q7: {=IFERROR(P7*(1-INDEX($D7:$D$71,Q$1)),0)} -> 0.90465038 | R7: {=IFERROR(Q7*(1-INDEX($D7:$D$71,R$1)),0)} -> 0.88361726 | S7: {=IFERROR(R7*(1-INDEX($D7:$D$71,S$1)),0)} -> 0.86081994 | ... DX7: {=IFERROR(DW7*(1-INDEX($D7:$D$71,DX$1)),0)} -> 0
